Workbook

Sheet 4
A1: Prospect Name | B1: Number | C1: Attempts Missing | D1: Status | E1: stage | F1: Call Slot 1 | G1: Attempt 1 | H1: Call Slot 2 | I1: Attempt 2 | J1: Call Slot 3 | K1: Attempt-3 | L1: Call Slot 4 | M1: Attempt-4 | N1: Notes | O1: Next Step
B2: 92 349 6567518 | D2: Not Attended | E2: Call not Recieved | F2: 10:00 - 12:00 PM | G2: Not Recieved | H2: 12:00-02:30 | I2: Not Recieved | J2: 02:30-04:30 | K2: Not Recieved | L2: 04:30-06:00 | N2: not picking up the call / I message
B3: 92 320 5311945 | D3: Not Attended | E3: enroll in next batch | F3: 10:00 - 12:00 PM | G3: Please Call later | H3: 12:00-02:30 | I3: Please Call later | J3: 02:30-04:30 | K3: Please Call later | L3: 04:30-06:00 | M3: Please Call later | N3: next batch
B4: 92 321 4635594 | D4: Not Attended | E4: Call not Recieved | F4: 10:00 - 12:00 PM | G4: Not Recieved | H4: 12:00-02:30 | I4: Not Recieved | J4: 02:30-04:30 | K4: Not Recieved | L4: 04:30-06:00 | N4: not picking up the call / I message
B5: 92 326 9883188 | D5: Not Attended | E5: Awaiting Response | F5: 10:00 - 12:00 PM | G5: Call Recieved | H5: 12:00-02:30 | I5: Not Recieved | J5: 02:30-04:30 | K5: Not Recieved | L5: 04:30-06:00 | N5: Not answer / I message him
B6: 92 332 4382744 | D6: Call Attended | E6: Awaiting payment | F6: 10:00 - 12:00 PM | G6: Call Recieved | H6: 12:00-02:30 | I6: Not Recieved | J6: 02:30-04:30 | K6: Call Recieved | L6: 04:30-06:00 | N6: 26TH
B7: 92 314 3150050 | D7: Not Attended | E7: Call not Recieved | F7: 10:00 - 12:00 PM | G7: Not Recieved | H7: 12:00-02:30 | I7: Not Recieved | J7: 02:30-04:30 | K7: Not Recieved | L7: 04:30-06:00 | N7: number off
B8: 92 345 9634325 | D8: Call Attended | E8: Contacted | F8: 10:00 - 12:00 PM | G8: Call Recieved | H8: 12:00-02:30 | I8: Not Recieved | J8: 02:30-04:30 | K8: Call Recieved | L8: 04:30-06:00 | N8: 29th may
B9: 92 308 6361988 | D9: Call Attended | E9: Contacted | F9: 10:00 - 12:00 PM | G9: Call Recieved | H9: 12:00-02:30 | I9: Not Recieved | J9: 02:30-04:30 | K9: Call Recieved | L9: 04:30-06:00 | N9: he'll update BY TODAY
B10: 92 332 3103893 | D10: Not Attended | E10: Call not Recieved | F10: 10:00 - 12:00 PM | G10: Not Recieved | H10: 12:00-02:30 | I10: Not Recieved | J10: 02:30-04:30 | K10: Not Recieved | L10: 04:30-06:00 | N10: Not picking up the call
B11: 92 317 1397129 | D11: Not Attended | E11: Call not Recieved | F11: 10:00 - 12:00 PM | G11: Not Recieved | H11: 12:00-02:30 | I11: Not Recieved | J11: 02:30-04:30 | K11: Not Recieved | L11: 04:30-06:00 | N11: no message
B12: 92 328 3427019 | D12: Call Attended | E12: Closed - Lost | F12: 10:00 - 12:00 PM | G12: Client lost | H12: 12:00-02:30 | I12: Client lost | J12: 02:30-04:30 | K12: Client lost | L12: 04:30-06:00 | M12: Client lost | N12: lost
B13: 92 309 2050008 | D13: Not Attended | E13: Call not Recieved | F13: 10:00 - 12:00 PM | G13: Not Recieved | H13: 12:00-02:30 | I13: Not Recieved | J13: 02:30-04:30 | K13: Not Recieved | L13: 04:30-06:00 | N13: Not answer / I message him
B14: 92 310 0470538 | D14: Not Attended | E14: Call not Recieved | F14: 10:00 - 12:00 PM | G14: Not Recieved | H14: 12:00-02:30 | I14: Not Recieved | J14: 02:30-04:30 | K14: Not Recieved | L14: 04:30-06:00 | N14: Not answer / I message him
B15: 92 324 1328331 | D15: Not Attended | E15: Call not Recieved | F15: 10:00 - 12:00 PM | G15: Not Recieved | H15: 12:00-02:30 | I15: Not Recieved | J15: 02:30-04:30 | K15: Not Recieved | L15: 04:30-06:00 | N15: Not answer / I message him
B16: 92 309 9622347 | D16: Not Attended | E16: Call not Recieved | F16: 10:00 - 12:00 PM | G16: Not Recieved | H16: 12:00-02:30 | I16: Not Recieved | J16: 02:30-04:30 | K16: Not Recieved | L16: 04:30-06:00 | N16: Not answer / I message him
B17: 92 304 1809388 | D17: Call Attended | E17: Closed - Lost | F17: 10:00 - 12:00 PM | G17: Client lost | H17: 12:00-02:30 | I17: Client lost | J17: 02:30-04:30 | K17: Client lost | L17: 04:30-06:00 | M17: Client lost | N17: he is going in Army academicfor 6 month
B18: 92 302 7117295 | D18: Call Attended | E18: Closed - Lost | F18: 10:00 - 12:00 PM | G18: Client lost | H18: 12:00-02:30 | I18: Client lost | J18: 02:30-04:30 | K18: Client lost | L18: 04:30-06:00 | M18: Client lost | N18: lost
B19: 92 308 2050360 | D19: Call Attended | E19: Closed - Lost | F19: 10:00 - 12:00 PM | G19: Client lost | H19: 12:00-02:30 | I19: Client lost | J19: 02:30-04:30 | K19: Client lost | L19: 04:30-06:00 | M19: Client lost | N19: want course in free
B20: 92 314 9977301 | D20: Call Attended | E20: Awaiting Response | F20: 10:00 - 12:00 PM | G20: Not Recieved | H20: 12:00-02:30 | I20: Not Recieved | J20: 02:30-04:30 | K20: Call Recieved | L20: 04:30-06:00 | N20: not picking up the call
B21: 92 316 9322437 | D21: Call Attended | E21: Contacted | F21: 10:00 - 12:00 PM | G21: Call Recieved | H21: 12:00-02:30 | I21: Not Recieved | J21: 02:30-04:30 | K21: Call Recieved | L21: 04:30-06:00 | N21: 28th
B22: 92 345 0500366 | D22: Call Attended | E22: Call not Recieved | F22: 10:00 - 12:00 PM | G22: Call Recieved | H22: 12:00-02:30 | I22: Call Recieved | J22: 02:30-04:30 | K22: Not Recieved | L22: 04:30-06:00 | N22: she cut the call
B23: 92 335 2151199 | D23: Not Attended | E23: Call not Recieved | F23: 10:00 - 12:00 PM | G23: Not Recieved | H23: 12:00-02:30 | I23: Not Recieved | J23: 02:30-04:30 | K23: Not Recieved | L23: 04:30-06:00 | N23: not picking up the call
B24: 92 313 8247251 | D24: Not Attended | E24: Call not Recieved | F24: 10:00 - 12:00 PM | G24: Not Recieved | H24: 12:00-02:30 | J24: 02:30-04:30 | K24: Not Recieved | L24: 04:30-06:00 | N24: not picking up the call
B25: 92 322 6573551 | D25: Not Attended | E25: Contacted | F25: 10:00 - 12:00 PM | G25: Not Recieved | H25: 12:00-02:30 | J25: 02:30-04:30 | K25: Not Recieved | L25: 04:30-06:00 | N25: not picking up the call
B26: 92 333 8053700 | D26: Not Attended | E26: Call not Recieved | F26: 10:00 - 12:00 PM | G26: Call Recieved | H26: 12:00-02:30 | J26: 02:30-04:30 | K26: Not Recieved | L26: 04:30-06:00 | N26: not picking up the call
A27: Junaid | B27: 92 355 6369605 | D27: Not Attended | E27: enroll in next batch | F27: 10:00 - 12:00 PM | G27: Please Call later | H27: 12:00-02:30 | I27: Please Call later | J27: 02:30-04:30 | K27: Please Call later | L27: 04:30-06:00 | M27: Please Call later | N27: next batch
B28: 92 308 0411714 | D28: Call Attended | E28: Closed - Lost | F28: 10:00 - 12:00 PM | G28: Client lost | H28: 12:00-02:30 | I28: Client lost | J28: 02:30-04:30 | K28: Client lost | L28: 04:30-06:00 | M28: Client lost | N28: lost
B29: 92 313 2132428 | D29: Not Attended | E29: Call not Recieved | F29: 10:00 - 12:00 PM | G29: Not Recieved | H29: 12:00-02:30 | J29: 02:30-04:30 | K29: Not Recieved | L29: 04:30-06:00 | N29: not picking up the call
B30: 92 325 0805768 | D30: Not Attended | E30: Call not Recieved | F30: 10:00 - 12:00 PM | G30: Not Recieved | H30: 12:00-02:30 | J30: 02:30-04:30 | K30: Not Recieved | L30: 04:30-06:00 | N30: not picking up the call
B31: 92 327 8363492 | D31: Not Attended | E31: Call not Recieved | F31: 10:00 - 12:00 PM | G31: Not Recieved | H31: 12:00-02:30 | J31: 02:30-04:30 | K31: Not Recieved | L31: 04:30-06:00 | N31: not picking up the call
B32: 92 347 9111801 | D32: Not Attended | E32: Call not Recieved | F32: 10:00 - 12:00 PM | G32: Not Recieved | H32: 12:00-02:30 | J32: 02:30-04:30 | K32: Not Recieved | L32: 04:30-06:00 | N32: not picking up the call
B33: 92 319 6819015 | D33: Not Attended | E33: Call not Recieved | F33: 10:00 - 12:00 PM | G33: Not Recieved | H33: 12:00-02:30 | J33: 02:30-04:30 | K33: Not Recieved | L33: 04:30-06:00 | N33: not picking up the call
B34: 92 321 4742155 | D34: Not Attended | E34: Call not Recieved | F34: 10:00 - 12:00 PM | H34: 12:00-02:30 | J34: 02:30-04:30 | K34: Not Recieved | L34: 04:30-06:00 | N34: not picking up the call
B35: 92 330 2840635 | D35: Call Attended | E35: Awaiting payment | F35: 10:00 - 12:00 PM | H35: 12:00-02:30 | I35: Call Recieved | J35: 02:30-04:30 | K35: Not Recieved | L35: 04:30-06:00 | N35: 1s june
B36: 92 333 9608073 | D36: Call Attended | E36: Awaiting Response | F36: 10:00 - 12:00 PM | H36: 12:00-02:30 | J36: 02:30-04:30 | K36: Call Recieved | L36: 04:30-06:00 | N36: he'll update
A37: inam ullah | B37: 92 310 8271844 | D37: Call Attended | E37: Awaiting Response | F37: 10:00 - 12:00 PM | H37: 12:00-02:30 | J37: 02:30-04:30 | K37: Call Recieved | L37: 04:30-06:00 | N37: he'll update
B38: 92 333 3684329 | D38: Call Attended | E38: Contacted | F38: 10:00 - 12:00 PM | H38: 12:00-02:30 | J38: 02:30-04:30 | K38: Call Recieved | L38: 04:30-06:00 | N38: no answer
B39: 92 348 2064372 | D39: Call Attended | E39: Awaiting Response | F39: 10:00 - 12:00 PM | H39: 12:00-02:30 | J39: 02:30-04:30 | K39: Call Recieved | L39: 04:30-06:00 | N39: he'll update
B40: 92 342 3607032 | D40: Call Attended | E40: Closed - Lost | F40: 10:00 - 12:00 PM | G40: Client lost | H40: 12:00-02:30 | I40: Client lost | J40: 02:30-04:30 | K40: Client lost | L40: 04:30-06:00 | M40: Client lost | N40: lost
B41: 92 313 3358988 | D41: Call Attended | E41: enroll in next batch | F41: 10:00 - 12:00 PM | G41: Please Call later | H41: 12:00-02:30 | I41: Please Call later | J41: 02:30-04:30 | K41: Please Call later | L41: 04:30-06:00 | M41: Please Call later | N41: next batch
B42: 92 312 0916979 | D42: Not Attended | E42: Call not Recieved | F42: 10:00 - 12:00 PM | H42: 12:00-02:30 | I42: Not Recieved | J42: 02:30-04:30 | K42: Not Recieved | L42: 04:30-06:00 | N42: not picking up the call
B43: 92 304 3609780 | D43: Call Attended | E43: Closed - Lost | F43: 10:00 - 12:00 PM | G43: Client lost | H43: 12:00-02:30 | I43: Client lost | J43: 02:30-04:30 | K43: Client lost | L43: 04:30-06:00 | M43: Client lost | N43: lost
B44: 92 355 4781124 | D44: Not Attended | E44: Call not Recieved | F44: 10:00 - 12:00 PM | H44: 12:00-02:30 | I44: Not Recieved | J44: 02:30-04:30 | K44: Not Recieved | L44: 04:30-06:00 | N44: no off
A45: Sindh/ larkana / zubair / artificial inteligence | B45: 92 319 3289538 | D45: Call Attended | E45: Awaiting Response | F45: 10:00 - 12:00 PM | G45: Not Recieved | H45: 12:00-02:30 | I45: Call Recieved | J45: 02:30-04:30 | K45: Call Recieved | L45: 04:30-06:00 | N45: Not answer / I message him
B46: 92 317 2787873 | D46: Not Attended | E46: Call not Recieved | F46: 10:00 - 12:00 PM | G46: Not Recieved | H46: 12:00-02:30 | J46: 02:30-04:30 | K46: Not Recieved | L46: 04:30-06:00 | N46: Not answer / I message him
B47: 92 334 2647920 | D47: Call Attended | E47: Contacted | F47: 10:00 - 12:00 PM | H47: 12:00-02:30 | J47: 02:30-04:30 | K47: Call Recieved | L47: 04:30-06:00 | N47: he'll update
B48: 92 335 2223525 | D48: Not Attended | E48: Call not Recieved | F48: 10:00 - 12:00 PM | G48: Not Recieved | H48: 12:00-02:30 | J48: 02:30-04:30 | K48: Not Recieved | L48: 04:30-06:00 | N48: Not answer / I message him
B49: 92 345 2580728 | D49: Not Attended | E49: Call not Recieved | F49: 10:00 - 12:00 PM | H49: 12:00-02:30 | J49: 02:30-04:30 | K49: Not Recieved | L49: 04:30-06:00 | N49: not picking up the call
B50: 92 323 2072337 | D50: Call Attended | E50: Closed - Lost | F50: 10:00 - 12:00 PM | G50: Client lost | H50: 12:00-02:30 | I50: Client lost | J50: 02:30-04:30 | K50: Client lost | L50: 04:30-06:00 | M50: Client lost | N50: lost
B51: 92 326 8186540 | D51: Not Attended | E51: Call not Recieved | F51: 10:00 - 12:00 PM | G51: Not Recieved | H51: 12:00-02:30 | J51: 02:30-04:30 | K51: Not Recieved | L51: 04:30-06:00 | N51: not picking up the call
B52: 92 315 9564075 | D52: Not Attended | E52: Call not Recieved | F52: 10:00 - 12:00 PM | G52: Not Recieved | H52: 12:00-02:30 | J52: 02:30-04:30 | K52: Not Recieved | L52: 04:30-06:00 | N52: not picking up the call
B53: 92 321 2882129 | D53: Call Attended | E53: Awaiting Response | F53: 10:00 - 12:00 PM | G53: Call Recieved | H53: 12:00-02:30 | J53: 02:30-04:30 | K53: Not Recieved | L53: 04:30-06:00 | N53: not picking up the call
B54: 92 313 2375076 | D54: Call Attended | E54: Contacted | F54: 10:00 - 12:00 PM | H54: 12:00-02:30 | J54: 02:30-04:30 | K54: Call Recieved | L54: 04:30-06:00 | N54: he'll update
B55: 92 344 5360410 | D55: Not Attended | E55: Call not Recieved | F55: 10:00 - 12:00 PM | H55: 12:00-02:30 | J55: 02:30-04:30 | K55: Not Recieved | L55: 04:30-06:00 | N55: not picking up the call
B56: 92 313 9077227 | D56: Call Attended | E56: Closed - Lost | F56: 10:00 - 12:00 PM | G56: Client lost | H56: 12:00-02:30 | I56: Client lost | J56: 02:30-04:30 | K56: Client lost | L56: 04:30-06:00 | M56: Client lost | N56: lost
B57: 92 323 8138274 | D57: Not Attended | E57: Call not Recieved | F57: 10:00 - 12:00 PM | G57: Not Recieved | H57: 12:00-02:30 | J57: 02:30-04:30 | K57: Not Recieved | L57: 04:30-06:00 | N57: Not answer / I message him
B58: 92 318 0429921 | D58: Call Attended | E58: Closed - Lost | F58: 10:00 - 12:00 PM | G58: Client lost | H58: 12:00-02:30 | I58: Client lost | J58: 02:30-04:30 | K58: Client lost | L58: 04:30-06:00 | M58: Client lost | N58: lost
B59: 92 325 9370608 | D59: Call Attended | E59: Closed - Lost | F59: 10:00 - 12:00 PM | G59: Client lost | H59: 12:00-02:30 | I59: Client lost | J59: 02:30-04:30 | K59: Client lost | L59: 04:30-06:00 | M59: Client lost | N59: lost
B60: 92 303 8322216 | D60: Call Attended | E60: Closed - Lost | F60: 10:00 - 12:00 PM | G60: Client lost | H60: 12:00-02:30 | I60: Client lost | J60: 02:30-04:30 | K60: Client lost | L60: 04:30-06:00 | M60: Client lost | N60: lost
B61: 92 342 2942900 | D61: Not Attended | E61: Call not Recieved | F61: 10:00 - 12:00 PM | G61: Not Recieved | H61: 12:00-02:30 | J61: 02:30-04:30 | K61: Not Recieved | L61: 04:30-06:00 | N61: Not answer / I message him
B62: 92 346 0026809 | D62: Call Attended | E62: Contacted | F62: 10:00 - 12:00 PM | H62: 12:00-02:30 | J62: 02:30-04:30 | K62: Call Recieved | L62: 04:30-06:00 | N62: he'll update
B63: 92 321 2753078 | D63: Call Attended | E63: enroll in next batch | F63: 10:00 - 12:00 PM | G63: Please Call later | H63: 12:00-02:30 | I63: Please Call later | J63: 02:30-04:30 | K63: Please Call later | L63: 04:30-06:00 | M63: Please Call later | N63: next batch
B64: 92 348 2064372 | D64: Call Attended | E64: Awaiting Response | F64: 10:00 - 12:00 PM | G64: Not Recieved | H64: 12:00-02:30 | I64: Not Recieved | J64: 02:30-04:30 | K64: Call Recieved | L64: 04:30-06:00 | M64: Not Recieved | N64: Not answer / I message him
B65: 92 306 3657024 | D65: Call Attended | E65: Closed - Lost | F65: 10:00 - 12:00 PM | G65: Client lost | H65: 12:00-02:30 | I65: Client lost | J65: 02:30-04:30 | K65: Client lost | L65: 04:30-06:00 | M65: Client lost | N65: Lost
B66: 92 311 6625741 | D66: Call Attended | E66: Contacted | F66: 10:00 - 12:00 PM | G66: Not Recieved | H66: 12:00-02:30 | I66: Not Recieved | J66: 02:30-04:30 | K66: Not Recieved | L66: 04:30-06:00 | M66: Call Recieved | N66: He'll update on 25
B67: 92 313 9864820 | D67: Not Attended | E67: Call not Recieved | F67: 10:00 - 12:00 PM | H67: 12:00-02:30 | I67: Call Recieved | J67: 02:30-04:30 | K67: Not Recieved | L67: 04:30-06:00 | M67: Not Recieved | N67: he is busy
B68: 92 319 6721954 | D68: Call Attended | E68: Contacted | F68: 10:00 - 12:00 PM | H68: 12:00-02:30 | J68: 02:30-04:30 | K68: Call Recieved | L68: 04:30-06:00 | M68: Call Recieved | N68: He'll update
B69: 92 327 3803953 | D69: Call Attended | E69: Closed - Lost | F69: 10:00 - 12:00 PM | G69: Client lost | H69: 12:00-02:30 | I69: Client lost | J69: 02:30-04:30 | K69: Client lost | L69: 04:30-06:00 | M69: Client lost | N69: lost
B70: 92 305 6685245 | D70: Call Attended | E70: Contacted | F70: 10:00 - 12:00 PM | G70: Not Recieved | H70: 12:00-02:30 | I70: Not Recieved | J70: 02:30-04:30 | K70: Not Recieved | L70: 04:30-06:00 | M70: Call Recieved | N70: not picking up the call
B71: 92 306 3715091 | D71: Call Attended | E71: Contacted | F71: 10:00 - 12:00 PM | G71: Not Recieved | H71: 12:00-02:30 | I71: Not Recieved | J71: 02:30-04:30 | K71: Call Recieved | L71: 04:30-06:00 | M71: Call Recieved | N71: he'll update
B72: 92 311 3209412 | D72: Call Attended | E72: Closed - Lost | F72: 10:00 - 12:00 PM | G72: Client lost | H72: 12:00-02:30 | I72: Client lost | J72: 02:30-04:30 | K72: Client lost | L72: 04:30-06:00 | M72: Client lost | N72: lost
B73: 92 315 9153383 | D73: Not Attended | E73: Call not Recieved | F73: 10:00 - 12:00 PM | G73: Not Recieved | H73: 12:00-02:30 | I73: Not Recieved | J73: 02:30-04:30 | K73: Not Recieved | L73: 04:30-06:00 | M73: Not Recieved | N73: no off
B74: 92 319 5051778 | D74: Call Attended | E74: Closed - Lost | F74: 10:00 - 12:00 PM | G74: Client lost | H74: 12:00-02:30 | I74: Client lost | J74: 02:30-04:30 | K74: Client lost | L74: 04:30-06:00 | M74: Client lost | N74: lost
B75: 92 300 9747088 | D75: Call Attended | E75: Contacted | F75: 10:00 - 12:00 PM | H75: 12:00-02:30 | I75: Not Recieved | J75: 02:30-04:30 | K75: Not Recieved | L75: 04:30-06:00 | M75: Call Recieved | N75: He'll update
B76: 92 310 3836652 | D76: Not Attended | E76: Call not Recieved | F76: 10:00 - 12:00 PM | G76: Not Recieved | H76: 12:00-02:30 | I76: Not Recieved | J76: 02:30-04:30 | K76: Not Recieved | L76: 04:30-06:00 | M76: Not Recieved | N76: not picking up the call
B77: 92 328 2139980 | D77: Call Attended | E77: Awaiting payment | F77: 10:00 - 12:00 PM | H77: 12:00-02:30 | I77: Call Recieved | J77: 02:30-04:30 | K77: Call Recieved | L77: 04:30-06:00 | M77: Call Recieved | N77: 1st june expected
B78: 92 341 9841425 | D78: Call Attended | E78: Closed - Lost | F78: 10:00 - 12:00 PM | G78: Client lost | H78: 12:00-02:30 | I78: Client lost | J78: 02:30-04:30 | K78: Client lost | L78: 04:30-06:00 | M78: Client lost | N78: Not interested
B79: 92 343 5477234 | D79: Not Attended | E79: Call not Recieved | F79: 10:00 - 12:00 PM | H79: 12:00-02:30 | I79: Not Recieved | J79: 02:30-04:30 | K79: Not Recieved | L79: 04:30-06:00 | N79: number off
B80: 92 306 2347214 | D80: Call Attended | E80: Contacted | F80: 10:00 - 12:00 PM | H80: 12:00-02:30 | I80: Not Recieved | J80: 02:30-04:30 | K80: Call Recieved | L80: 04:30-06:00 | N80: He'll update
B81: 92 328 3728287 | D81: Call Attended | E81: Contacted | F81: 10:00 - 12:00 PM | G81: Call Recieved | H81: 12:00-02:30 | J81: 02:30-04:30 | K81: Call Recieved | L81: 04:30-06:00 | M81: Not Recieved | N81: he cut the call
B82: 92 331 0396815 | D82: Call Attended | E82: Awaiting Response | F82: 10:00 - 12:00 PM | G82: Not Recieved | H82: 12:00-02:30 | I82: Not Recieved | J82: 02:30-04:30 | K82: Not Recieved | L82: 04:30-06:00 | M82: Call Recieved | N82: Not answer / I message him
B83: 92 343 9323130 | D83: Not Attended | E83: Call not Recieved | F83: 10:00 - 12:00 PM | H83: 12:00-02:30 | I83: Not Recieved | J83: 02:30-04:30 | K83: Not Recieved | L83: 04:30-06:00 | M83: Not Recieved | N83: not picking up the call
B84: 92 344 0201688 | D84: Call Attended | E84: Closed - Lost | F84: 10:00 - 12:00 PM | G84: Client lost | H84: 12:00-02:30 | I84: Client lost | J84: 02:30-04:30 | K84: Client lost | L84: 04:30-06:00 | M84: Client lost | N84: lost
B85: 92 315 4688409 | D85: Call Attended | E85: Contacted | F85: 10:00 - 12:00 PM | H85: 12:00-02:30 | I85: Not Recieved | J85: 02:30-04:30 | K85: Call Recieved | L85: 04:30-06:00 | M85: Not Recieved | N85: not picking up the call
B86: 92 340 7012882 | D86: Not Attended | E86: Call not Recieved | F86: 10:00 - 12:00 PM | H86: 12:00-02:30 | I86: Not Recieved | J86: 02:30-04:30 | K86: Not Recieved | L86: 04:30-06:00 | M86: Not Recieved | N86: not picking up the call
B87: 92 341 2378885 | D87: Not Attended | E87: Call not Recieved | F87: 10:00 - 12:00 PM | H87: 12:00-02:30 | I87: Not Recieved | J87: 02:30-04:30 | K87: Not Recieved | L87: 04:30-06:00 | M87: Not Recieved | N87: not picking up the call
B88: 92 344 2274780 | D88: Call Attended | E88: Closed - Lost | F88: 10:00 - 12:00 PM | G88: Client lost | H88: 12:00-02:30 | I88: Call Recieved | J88: 02:30-04:30 | K88: Call Recieved | L88: 04:30-06:00 | M88: Client lost | N88: lost
B89: 92 349 4013035 | D89: Not Attended | E89: Call not Recieved | F89: 10:00 - 12:00 PM | H89: 12:00-02:30 | I89: Not Recieved | J89: 02:30-04:30 | K89: Not Recieved | L89: 04:30-06:00 | M89: Not Recieved | N89: not picking up the call
B90: 92 343 4332884 | D90: Not Attended | E90: Call not Recieved | F90: 10:00 - 12:00 PM | H90: 12:00-02:30 | I90: Not Recieved | J90: 02:30-04:30 | K90: Not Recieved | L90: 04:30-06:00 | M90: Not Recieved | N90: not picking up the call
B91: 92 316 0224704 | D91: Call Attended | E91: Awaiting Response | F91: 10:00 - 12:00 PM | H91: 12:00-02:30 | I91: Call Recieved | J91: 02:30-04:30 | K91: Call Recieved | L91: 04:30-06:00 | M91: Call Recieved | N91: his brother come after 5 minutes
B92: 92 328 1330003 | D92: Not Attended | E92: Closed - Lost | F92: 10:00 - 12:00 PM | G92: Client lost | H92: 12:00-02:30 | I92: Client lost | J92: 02:30-04:30 | K92: Client lost | L92: 04:30-06:00 | M92: Client lost | N92: not interested
F93: 10:00 - 12:00 PM | H93: 12:00-02:30 | J93: 02:30-04:30 | L93: 04:30-06:00
F94: 10:00 - 12:00 PM | H94: 12:00-02:30 | J94: 02:30-04:30 | L94: 04:30-06:00
F95: 10:00 - 12:00 PM | H95: 12:00-02:30 | J95: 02:30-04:30 | L95: 04:30-06:00
F96: 10:00 - 12:00 PM | H96: 12:00-02:30 | J96: 02:30-04:30 | L96: 04:30-06:00
F97: 10:00 - 12:00 PM | H97: 12:00-02:30 | J97: 02:30-04:30 | L97: 04:30-06:00
F98: 10:00 - 12:00 PM | H98: 12:00-02:30 | J98: 02:30-04:30 | L98: 04:30-06:00
F99: 10:00 - 12:00 PM | H99: 12:00-02:30 | J99: 02:30-04:30 | L99: 04:30-06:00
F100: 10:00 - 12:00 PM | H100: 12:00-02:30 | J100: 02:30-04:30 | L100: 04:30-06:00
...

Sheet 5
A1: Prospect Name | B1: Number | C1: Attempts Missing | D1: Status | E1: stage | F1: Call Slot 1 | G1: Attempt 1 | H1: Call Slot 2 | I1: Attempt 2 | J1: Call Slot 3 | K1: Attempt-3 | L1: Call Slot 4 | M1: Attempt-4 | N1: Notes | O1: Next Step
A2: Closed - Lost | B2: 0307-3875280 (0343-7833258) | C2: 2 | D2: Call Attended | E2: Closed - Lost | F2: 10:00 - 12:00 PM | G2: Call Recieved | H2: 12:00-02:30 | J2: 02:30-04:30 | K2: Call Recieved | L2: 04:30-06:00 | N2: he said he has some personal issues so for now he drop his plan to enroll in course. | O2: nil
B3: 0343-1336539 | C3: 4 | D3: Not Attended | E3: Call not Recieved | F3: 10:00 - 12:00 PM | H3: 12:00-02:30 | I3: Not Recieved | J3: 02:30-04:30 | K3: Not Recieved | L3: 04:30-06:00 | M3: Not Recieved | N3: still didnt respond on call not on whtsapp | O3: call tomorrow
A4: Mrs Ajmal | B4: 0321-7067642 | C4: 1 | D4: Call Attended | E4: Closed - Lost | F4: 10:00 - 12:00 PM | H4: 12:00-02:30 | J4: 02:30-04:30 | L4: 04:30-06:00 | M4: Call Recieved | N4: she run a welfare asking to join with her.
A5: Waseem | B5: 0306-7362137 (03055640707) | C5: 4 | D5: Not Attended | E5: Contacted | F5: 10:00 - 12:00 PM | G5: Not Recieved | H5: 12:00-02:30 | I5: Not Recieved | J5: 02:30-04:30 | L5: 04:30-06:00 | N5: call him but he didn't respond not on whtsapp. | O5: call him later.
A6: Ubaidullah | B6: 0332-7848087 | C6: 4 | D6: Not Attended | E6: Closed - Lost | F6: 10:00 - 12:00 PM | G6: Not Recieved | H6: 12:00-02:30 | I6: Not Recieved | J6: 02:30-04:30 | L6: 04:30-06:00 | N6: call but didnt attend the call. had talke on whtsapp he is interested but he said he cant take online classes. due to he is living in joint family i asked him to manage and sort out this problem. cant manage to take online classes. | O6: approach him later.
A7: Sufiyan | B7: 0314-5964493 | C7: 2 | D7: Call Attended | E7: Closed - Lost | F7: 10:00 - 12:00 PM | G7: Call Recieved | H7: 12:00-02:30 | I7: Call Recieved | J7: 02:30-04:30 | L7: 04:30-06:00 | N7: said not interested in course. | O7: Nil
B8: 0347-3063900 | C8: 4 | D8: Not Attended | E8: Call not Recieved | F8: 10:00 - 12:00 PM | G8: Not Recieved | H8: 12:00-02:30 | I8: Not Recieved | J8: 02:30-04:30 | K8: Not Recieved | L8: 04:30-06:00 | N8: still num off not respond on whtsapp. | O8: call tomorrow.
A9: Iqra | B9: 0347-2790767 | C9: 2 | D9: Call Attended | E9: Contacted | F9: 10:00 - 12:00 PM | G9: Call Recieved | H9: 12:00-02:30 | I9: Call Recieved | J9: 02:30-04:30 | L9: 04:30-06:00 | N9: had talked with her she said she cant manage time as she is doing job in US based comapany so cant manage time to take online classes. | O9: -
A10: Attaullah | B10: 0312-5872866 | C10: 4 | D10: Not Attended | E10: Call not Recieved | F10: 10:00 - 12:00 PM | G10: Not Recieved | H10: 12:00-02:30 | I10: Not Recieved | J10: 02:30-04:30 | L10: 04:30-06:00 | N10: num off didn't respond on whtsapp | O10: call tomorrow.
A11: Mamoona | B11: 0347-2292892 | C11: 4 | D11: Not Attended | E11: Call not Recieved | F11: 10:00 - 12:00 PM | G11: Not Recieved | H11: 12:00-02:30 | I11: Not Recieved | J11: 02:30-04:30 | L11: 04:30-06:00 | N11: not answer but shared detail on whtsapp . not responding on calll not on whtsapp. | O11: call tomorrow.
A12: Abdul Waheed | B12: 0314-5046175 | C12: 1 | D12: Call Attended | E12: Closed - Lost | F12: 10:00 - 12:00 PM | G12: Call Recieved | H12: 12:00-02:30 | J12: 02:30-04:30 | L12: 04:30-06:00 | N12: had talk he is currently enroll in other course so cant afford at one time 2 courses. | O12: -
A13: Shafaq | B13: 0325-4279620 | C13: 3 | D13: Call Attended | E13: Closed - Lost | F13: 10:00 - 12:00 PM | G13: Not Recieved | H13: 12:00-02:30 | I13: Call Recieved | J13: 02:30-04:30 | L13: 04:30-06:00 | N13: had talked she said she is interested in specific data anylst course. moreover said currently not want to enroll. approch her again but she said she dont want to enroll in this time. | O13: -
A14: Sami | B14: 0300-3563354 | C14: 3 | D14: Not Attended | E14: Closed - Lost | F14: 10:00 - 12:00 PM | G14: Not Recieved | H14: 12:00-02:30 | I14: Call Recieved | J14: 02:30-04:30 | L14: 04:30-06:00 | N14: had talked with him he think that course is free i asked him about how much he can pay he didn't say and hang up. ( number is busy) drop msg on whtsapp. | O14: call after 3 days
A15: Muneeb | B15: 0334-9722883 | C15: 4 | D15: Call Attended | E15: Contacted | F15: 10:00 - 12:00 PM | G15: Call Recieved | H15: 12:00-02:30 | I15: Call Recieved | J15: 02:30-04:30 | L15: 04:30-06:00 | M15: Not Recieved | N15: he is busy in class said call me later. (busy). not answering | O15: call 2 days later
A16: Ahmed | B16: 0320-7807857 | C16: 5 | D16: Call Attended | E16: Contacted | F16: 10:00 - 12:00 PM | G16: Call Recieved | H16: 12:00-02:30 | I16: Call Recieved | J16: 02:30-04:30 | L16: 04:30-06:00 | N16: his bro is interested in course i called him but his bro is not at home. moreover i asked him to call me when his bro is at home. so i can describe it whole course. | O16: call in evening
B17: 0330-8675442 | C17: 4 | D17: Not Attended | E17: Call not Recieved | F17: 10:00 - 12:00 PM | H17: 12:00-02:30 | I17: Not Recieved | J17: 02:30-04:30 | K17: Not Recieved | L17: 04:30-06:00 | N17: still num off not replying on whtsapp. | O17: call 2 days later
A18: Safwan | B18: 0321 5482238 | C18: 3 | D18: Call Attended | E18: Closed - Lost | F18: 10:00 - 12:00 PM | H18: 12:00-02:30 | I18: Not Recieved | J18: 02:30-04:30 | L18: 04:30-06:00 | M18: Call Recieved | N18: Had talked with him he said he is interested in cost accounting .so not interested in this | O18: -
B19: 0348 8815169 | C19: 4 | D19: Call Attended | E19: Closed - Lost | F19: 10:00 - 12:00 PM | G19: Call Recieved | H19: 12:00-02:30 | I19: Not Recieved | J19: 02:30-04:30 | L19: 04:30-06:00 | N19: not interested. | O19: NIL
A20: Shoaib | B20: 0349 5635598 | C20: 6 | D20: Not Attended | E20: Contacted | F20: 10:00 - 12:00 PM | G20: Not Recieved | H20: 12:00-02:30 | I20: Not Recieved | J20: 02:30-04:30 | L20: 04:30-06:00 | N20: had talked he said he didnt have any laptop or pc i asked him to find and let me know.( call him but he didnt recieved call) | O20: -
A21: Ibrahim | B21: 0310 5255500 | C21: 3 | D21: Call Attended | E21: Closed - Lost | F21: 10:00 - 12:00 PM | G21: Call Recieved | H21: 12:00-02:30 | I21: Not Recieved | J21: 02:30-04:30 | L21: 04:30-06:00 | N21: had talked with him told him about course he is interested but cant afford course i asked how much he can pay but he said he coudlnt pay. | O21: NIl
A22: Hadia | B22: 0331 5600623 | C22: 3 | D22: Not Attended | E22: Awaiting Response | F22: 10:00 - 12:00 PM | H22: 12:00-02:30 | I22: Not Recieved | J22: 02:30-04:30 | K22: Call Recieved | L22: 04:30-06:00 | N22: she is interested but she said on whtsapp her father is not convence for online course. moreover i asked her to make him convence. she would told me about today. | O22: reach her out again later.
A23: Hameedullah | B23: 0313 8978984 | C23: 6 | D23: Not Attended | E23: Awaiting Response | F23: 10:00 - 12:00 PM | G23: Not Recieved | H23: 12:00-02:30 | I23: Not Recieved | J23: 02:30-04:30 | L23: 04:30-06:00 | M23: Not Recieved | N23: he has done B.sc and want to start his career in tech industry thats why want to avail this course. will confirm in 1 or 2 days. ( not recieved call drop msg on whtsapp) still not responding | O23: reach out again later.
A24: Shahid | B24: 0328-2187990 | C24: 2 | D24: Call Attended | E24: Closed - Lost | F24: 10:00 - 12:00 PM | H24: 12:00-02:30 | I24: Call Recieved | J24: 02:30-04:30 | L24: 04:30-06:00 | M24: Call Recieved | N24: had talked with him he was looking for dropshipping .. not have any interest in this course. | O24: nil
A25: Babar | B25: 0348-9451791 | C25: 1 | D25: Call Attended | E25: Closed - Lost | F25: 10:00 - 12:00 PM | H25: 12:00-02:30 | J25: 02:30-04:30 | L25: 04:30-06:00 | M25: Call Recieved | N25: he has no money jobless lives in KPK want to learn this course in free cant pay one single peny as per his say. | O25: _
A26: Abuzar | B26: 0335-9161732 | C26: 2 | D26: Call Attended | E26: Closed - Lost | F26: 10:00 - 12:00 PM | H26: 12:00-02:30 | I26: Call Recieved | J26: 02:30-04:30 | L26: 04:30-06:00 | M26: Call Recieved | N26: had talked but they reacting like a stranger as they dont know about course or anything and last he said we dont want to enroll | O26: -
A27: Sarmad | B27: 0307-0004297 | C27: 3 | D27: Not Attended | E27: Awaiting Response | F27: 10:00 - 12:00 PM | H27: 12:00-02:30 | I27: Call Recieved | J27: 02:30-04:30 | L27: 04:30-06:00 | M27: Not Recieved | N27: he is in office said call me later ( didnt recieved call drop msg on whtsapp) | O27: call tomorrow
A28: Murtuza | B28: 92 300 2530903 | C28: 4 | D28: Not Attended | E28: Call not Recieved | F28: 10:00 - 12:00 PM | G28: Not Recieved | H28: 12:00-02:30 | I28: Not Recieved | J28: 02:30-04:30 | K28: Not Recieved | L28: 04:30-06:00 | M28: Not Recieved | N28: didn't pick up the call. didnt respond on whtsapp. | O28: NIL
A29: Zahid | B29: 92 343 8277690 | C29: 4 | D29: Not Attended | E29: Call not Recieved | F29: 10:00 - 12:00 PM | G29: Not Recieved | H29: 12:00-02:30 | I29: Not Recieved | J29: 02:30-04:30 | K29: Not Recieved | L29: 04:30-06:00 | M29: Not Recieved | N29: can't connect call drop msg on whtsapp but didnt reply. | O29: call him after 2 days
A30: Farhan | B30: 92 347 2694975 | C30: 1 | D30: Call Attended | E30: Closed - Lost | F30: 10:00 - 12:00 PM | H30: 12:00-02:30 | J30: 02:30-04:30 | K30: Call Recieved | L30: 04:30-06:00 | N30: Had talked with him he didnt have any pc or laptop said can i do it over phone / | O30: -
B31: 92 342 9105279 | C31: 3 | D31: Not Attended | E31: Call not Recieved | F31: 10:00 - 12:00 PM | G31: Not Recieved | H31: 12:00-02:30 | I31: Not Recieved | J31: 02:30-04:30 | K31: Not Recieved | L31: 04:30-06:00 | N31: Still not recieved call not replying on whtsapp. | O31: reach out again today
A32: Naeem | B32: 92 332 2735044 | C32: 2 | D32: Call Attended | E32: Closed - Lost | F32: 10:00 - 12:00 PM | H32: 12:00-02:30 | J32: 02:30-04:30 | K32: Call Recieved | L32: 04:30-06:00 | N32: call recieved but didnt talk properly and didnt understand anything about course | O32: NIL
A33: Arshad | B33: 92 327 1458765 | C33: 4 | D33: Not Attended | E33: Contacted | F33: 10:00 - 12:00 PM | G33: Not Recieved | H33: 12:00-02:30 | I33: Call Recieved | J33: 02:30-04:30 | K33: Not Recieved | L33: 04:30-06:00 | M33: Not Recieved | N33: had talked with him he said may b his bro generate query he said call me at 5 i will let you talk to my bro.( i call at 5 but he didnt pick up the call). didnt pick up the call not responding on whtsapp.) | O33: call him after 2 days
A34: Samra | B34: 92 344 4853224 | C34: 3 | D34: Not Attended | E34: Contacted | F34: 10:00 - 12:00 PM | G34: Not Recieved | H34: 12:00-02:30 | I34: Call Recieved | J34: 02:30-04:30 | K34: Please Call later | L34: 04:30-06:00 | N34: had talked i told her that she show interest in our course she hang up on me . drop msg on whtsapp. ( not attending call) | O34: reach out again today
A35: Hussain | B35: 92 304 8098804 | C35: 4 | D35: Not Attended | E35: Awaiting Response | F35: 10:00 - 12:00 PM | G35: Not Recieved | H35: 12:00-02:30 | J35: 02:30-04:30 | K35: Not Recieved | L35: 04:30-06:00 | N35: had talked with him he is interested share details of demo and bank he said he will review it & will confirm about payment.( didnt pick up the call drop msg on whtsapp) still not answering | O35: call him tomorrow.
A36: Yasir | B36: 92 332 5106008 | C36: 1 | D36: Not Attended | E36: Closed - Lost | F36: 10:00 - 12:00 PM | G36: Not Recieved | H36: 12:00-02:30 | J36: 02:30-04:30 | L36: 04:30-06:00 | N36: had talked on whtsapp bascially want job or want to reach our someone through our platform. not interested in course. | O36: NIL
A37: Irfan | B37: 92 342 0821163 | C37: 4 | D37: Call Attended | E37: Contacted | F37: 10:00 - 12:00 PM | G37: Not Recieved | H37: 12:00-02:30 | I37: Call Recieved | J37: 02:30-04:30 | K37: Call Recieved | L37: 04:30-06:00 | M37: Call Recieved | N37: had a little talk with him he said he is busy in office call him after office hours. | O37: call him after 6 pm
A38: Arsalan | B38: 92 333 7551611 | C38: 4 | D38: Not Attended | E38: Contacted | F38: 10:00 - 12:00 PM | G38: Not Recieved | H38: 12:00-02:30 | J38: 02:30-04:30 | K38: Not Recieved | L38: 04:30-06:00 | N38: had little talk on call as he was busy he said we will talk later. moreover i shared details with him. ( not attending call not respond on whtsapp). | O38: call today at 4
A39: Farhan | B39: 92 314 5001584 | C39: 5 | D39: Not Attended | E39: Contacted | F39: 10:00 - 12:00 PM | G39: Not Recieved | H39: 12:00-02:30 | J39: 02:30-04:30 | K39: Not Recieved | L39: 04:30-06:00 | M39: Not Recieved | N39: call but someone else pick up the call and said farhan is not at home i told him when he back tell him to cll me back.(not attend call not reply on whtsapp) | O39: call today at 4
A40: Shams | B40: 92 307 0079544 | C40: 2 | D40: Not Attended | E40: Contacted | F40: 10:00 - 12:00 PM | G40: Not Recieved | H40: 12:00-02:30 | I40: Call Recieved | J40: 02:30-04:30 | L40: 04:30-06:00 | N40: had talked he is in office said call me in evening moreover send details on whtsapp.( not attending call not reply on whtsapp). | O40: call in evening
A41: Ahmed (Muzamil) | B41: 92 344 6913804 | C41: 3 | D41: Call Attended | E41: Awaiting Response | F41: 10:00 - 12:00 PM | G41: Not Recieved | H41: 12:00-02:30 | I41: Not Recieved | J41: 02:30-04:30 | L41: 04:30-06:00 | M41: Call Recieved | N41: had talked with him he said his bro is apply for this moreover thy both are interested in this course. they said they will call me & told me about their plans | O41: reach out again today
A42: Dr Farzana | B42: 92 332 3633535 | C42: 1 | D42: Call Attended | E42: Awaiting Response | F42: 10:00 - 12:00 PM | H42: 12:00-02:30 | I42: Call Recieved | J42: 02:30-04:30 | L42: 04:30-06:00 | N42: Had talked with her she is interested in learning about tech industry.. i had send her details she said she will discuss it with her sons and husband & will let me know. | O42: call on Saturday
B43: 92 314 3381692 | C43: 2 | D43: Call Attended | E43: Contacted | F43: 10:00 - 12:00 PM | G43: Call Recieved | H43: 12:00-02:30 | J43: 02:30-04:30 | K43: Call Recieved | L43: 04:30-06:00 | N43: had talked with her breif her about our course she is looking it for her sister. moreover she said she will told me about her plan by today. | O43: reach out later.
A44: Mubashir | B44: 92 340 7624354 | C44: 3 | D44: Call Attended | E44: Contacted | F44: 10:00 - 12:00 PM | G44: Call Recieved | H44: 12:00-02:30 | I44: Call Recieved | J44: 02:30-04:30 | K44: Not Recieved | L44: 04:30-06:00 | N44: had talked with him he said he is interested but cant afford fee say can pay3500 i asked how maximum can he pay so i can discuss it with managment. | O44: call after jummah.
A45: Javeria | B45: 92 315 6184168 | C45: 2 | D45: Not Attended | E45: Contacted | F45: 10:00 - 12:00 PM | G45: Not Recieved | H45: 12:00-02:30 | J45: 02:30-04:30 | K45: Call Recieved | L45: 04:30-06:00 | N45: had talked with her told her about course. send pdf on whtsapp. she said contact me on wtsapp.(not attend call not reply on whtsapp). | O45: reach her out again later.
A46: Nazeer | B46: 92 348 6270085 | C46: 2 | D46: Not Attended | E46: Call not Recieved | F46: 10:00 - 12:00 PM | G46: Not Recieved | H46: 12:00-02:30 | J46: 02:30-04:30 | K46: Not Recieved | L46: 04:30-06:00 | N46: not responding on call drop msg on whtsapp. | O46: reach out again later.
A47: Matloob | B47: 92 343 7872615 | C47: 2 | D47: Not Attended | E47: Contacted | F47: 10:00 - 12:00 PM | H47: 12:00-02:30 | I47: Not Recieved | J47: 02:30-04:30 | K47: Call Recieved | L47: 04:30-06:00 | N47: his son pick up the call said his father is at office. will return in evening i told him tell his father to call back. (not answering) | O47: reach out again later.
A48: Ahsan | B48: 92 318 5142595 | C48: 2 | D48: Not Attended | E48: Contacted | F48: 10:00 - 12:00 PM | H48: 12:00-02:30 | I48: Not Recieved | J48: 02:30-04:30 | K48: Call Recieved | L48: 04:30-06:00 | N48: he is busy said call me later moreover said i will connect with you on whtsapp.( didn't pick up the call not reply on whtsapp. | O48: reach out again later.
A49: Haider | B49: 92 340 8950034 | C49: 2 | D49: Not Attended | E49: Call not Recieved | F49: 10:00 - 12:00 PM | G49: Not Recieved | H49: 12:00-02:30 | J49: 02:30-04:30 | K49: Not Recieved | L49: 04:30-06:00 | N49: num busy drop msg on whtspp | O49: reach out again later.
A50: Dr Sadia | B50: 92 333 7496392 | C50: 2 | D50: Not Attended | E50: Call not Recieved | F50: 10:00 - 12:00 PM | G50: Not Recieved | H50: 12:00-02:30 | J50: 02:30-04:30 | K50: Not Recieved | L50: 04:30-06:00 | N50: not attend call drop msg on whtsapp. | O50: reach out again later.
A51: Asima | B51: 92 333 5113441 | C51: 1 | D51: Call Attended | E51: Closed - Lost | F51: 10:00 - 12:00 PM | H51: 12:00-02:30 | J51: 02:30-04:30 | K51: Call Recieved | L51: 04:30-06:00 | N51: had talked with her she said she is searching for her children. her children. today i called her folr follow up she said her kids aren't interested in this course at this time. | O51: reach out again later.
A52: Shamsa | B52: 92 300 9413794 | C52: 3 | D52: Not Attended | E52: Call not Recieved | F52: 10:00 - 12:00 PM | G52: Not Recieved | H52: 12:00-02:30 | J52: 02:30-04:30 | K52: Not Recieved | L52: 04:30-06:00 | N52: not recieved call send msg on whtsapp. but didnt reply . | O52: reach out again later.
B53: 92 333 9024738 | C53: 1 | D53: Call Attended | E53: Closed - Lost | F53: 10:00 - 12:00 PM | H53: 12:00-02:30 | J53: 02:30-04:30 | K53: Call Recieved | L53: 04:30-06:00 | N53: said just checking out add dont have any interest in course. | O53: NIL
A54: Hadi | B54: 92 315 8531876 | C54: 2 | D54: Call Attended | E54: Closed - Lost | F54: 10:00 - 12:00 PM | H54: 12:00-02:30 | I54: Call Recieved | J54: 02:30-04:30 | K54: Call Recieved | L54: 04:30-06:00 | N54: he said he dont know english and dont know how to use pc. | O54: NIL
B55: 92 336 6222293 | C55: 2 | D55: Not Attended | E55: Call not Recieved | F55: 10:00 - 12:00 PM | G55: Not Recieved | H55: 12:00-02:30 | J55: 02:30-04:30 | K55: Not Recieved | L55: 04:30-06:00 | N55: not attend call drop msg on whtsapp. | O55: reach out again later.
A56: Atya | B56: 92 309 1949587 | C56: 2 | D56: Not Attended | E56: Awaiting Response | F56: 10:00 - 12:00 PM | H56: 12:00-02:30 | J56: 02:30-04:30 | K56: Not Recieved | L56: 04:30-06:00 | N56: had talked with her told her about course. send pdf on whtsapp. she will review it & will let me know. didnt pick up the call. | O56: reach out again later.
A57: Laiba | B57: 92 342 7904194 | C57: 1 | D57: Call Attended | E57: Closed - Lost | F57: 10:00 - 12:00 PM | H57: 12:00-02:30 | J57: 02:30-04:30 | K57: Call Recieved | L57: 04:30-06:00 | N57: intrested told her about our course she said she will confirm by today or tomorrow. about enrolling. ( she said she is not interested said its not possible to contimue it with study) | O57: NIL
A58: Riffat | B58: 92 322 8165516 | C58: 1 | D58: Call Attended | E58: Closed - Lost | F58: 10:00 - 12:00 PM | H58: 12:00-02:30 | J58: 02:30-04:30 | L58: 04:30-06:00 | M58: Call Recieved | N58: said just checking out add dont have any interest in course. | O58: NIL
B59: 92 307 1707563 | C59: 2 | D59: Not Attended | E59: Call not Recieved | F59: 10:00 - 12:00 PM | G59: Not Recieved | H59: 12:00-02:30 | J59: 02:30-04:30 | L59: 04:30-06:00 | M59: Not Recieved | N59: not attend call drop msg on whtsapp. | O59: reach out again later.
B60: 92 316 5282321 | C60: 1 | D60: Call Attended | E60: Contacted | F60: 10:00 - 12:00 PM | H60: 12:00-02:30 | J60: 02:30-04:30 | L60: 04:30-06:00 | M60: Call Recieved | N60: pick up the call said how much is the charges i told her she didnt talk much just hang up. | O60: reach out again later.
A61: Yasmeen | B61: 92 314 7547932 | C61: 2 | D61: Call Attended | E61: Contacted | F61: 10:00 - 12:00 PM | H61: 12:00-02:30 | I61: Call Recieved | J61: 02:30-04:30 | L61: 04:30-06:00 | M61: Call Recieved | N61: didnt talk properly on call . | O61: call tomorrow.
A62: Aroob | B62: 92 318 0864406 | C62: 2 | D62: Not Attended | E62: Call not Recieved | F62: 10:00 - 12:00 PM | G62: Not Recieved | H62: 12:00-02:30 | J62: 02:30-04:30 | L62: 04:30-06:00 | M62: Not Recieved | N62: not attend call drop msg on whtsapp. | O62: reach out again later.
A63: Jawad | B63: 0333-3014183 | C63: 2 | D63: Not Attended | E63: Call not Recieved | F63: 10:00 - 12:00 PM | G63: Not Recieved | H63: 12:00-02:30 | J63: 02:30-04:30 | L63: 04:30-06:00 | M63: Not Recieved | N63: busy on other call. drop msg on whtsapp. | O63: reach out again later.
A64: Hassan | B64: 92 341 3529509 | C64: 1 | D64: Call Attended | E64: Closed - Lost | F64: 10:00 - 12:00 PM | H64: 12:00-02:30 | J64: 02:30-04:30 | L64: 04:30-06:00 | M64: Call Recieved | N64: had talked with her she is a single mother want to ear onine but cant afford course moreover dosent have any pc or laptop . | O64: NIL
A65: Kiramat Shah | B65: 92 316 1218074 | C65: 2 | D65: Not Attended | E65: Call not Recieved | F65: 10:00 - 12:00 PM | G65: Not Recieved | H65: 12:00-02:30 | J65: 02:30-04:30 | L65: 04:30-06:00 | M65: Not Recieved | N65: num off drop msg on whtsapp. | O65: reach out again later.
A66: Urooj Fatima | B66: 92 331 3927816 | C66: 2 | D66: Not Attended | E66: Contacted | F66: 10:00 - 12:00 PM | H66: 12:00-02:30 | J66: 02:30-04:30 | K66: Not Recieved | L66: 04:30-06:00 | M66: Call Recieved | N66: she is busy in namaz said will call later. drop msg on whtsapp i called her number is busy. | O66: reach out again later.
B67: 92 355 5986501 | C67: 3 | D67: Not Attended | E67: Contacted | F67: 10:00 - 12:00 PM | G67: Call Recieved | H67: 12:00-02:30 | I67: Not Recieved | J67: 02:30-04:30 | L67: 04:30-06:00 | M67: Not Recieved | N67: had called with him he said he was busy somewhere . told me to send details on whtsapp so he can review it and will let me know . (not answered). | O67: call in evening
A68: Wajid | B68: 92 307 0427470 | C68: 1 | D68: Call Attended | E68: Closed - Lost | F68: 10:00 - 12:00 PM | H68: 12:00-02:30 | J68: 02:30-04:30 | L68: 04:30-06:00 | M68: Call Recieved | N68: cant understand what i am saying said his son may be shown interest but say his on cant undersstand urdu. | O68: NIl
A69: Wasif | B69: 92 332 5130344 | C69: 2 | D69: Not Attended | E69: Call not Recieved | F69: 10:00 - 12:00 PM | G69: Not Recieved | H69: 12:00-02:30 | J69: 02:30-04:30 | L69: 04:30-06:00 | M69: Not Recieved | N69: not attend call drop msg on whtsapp. | O69: reach out again later.
F70: 10:00 - 12:00 PM | H70: 12:00-02:30 | J70: 02:30-04:30 | L70: 04:30-06:00
F71: 10:00 - 12:00 PM | H71: 12:00-02:30 | J71: 02:30-04:30 | L71: 04:30-06:00
F72: 10:00 - 12:00 PM | H72: 12:00-02:30 | J72: 02:30-04:30 | L72: 04:30-06:00
F73: 10:00 - 12:00 PM | H73: 12:00-02:30 | J73: 02:30-04:30 | L73: 04:30-06:00
F74: 10:00 - 12:00 PM | H74: 12:00-02:30 | J74: 02:30-04:30 | L74: 04:30-06:00
F75: 10:00 - 12:00 PM | H75: 12:00-02:30 | J75: 02:30-04:30 | L75: 04:30-06:00
F76: 10:00 - 12:00 PM | H76: 12:00-02:30 | J76: 02:30-04:30 | L76: 04:30-06:00
F77: 10:00 - 12:00 PM | H77: 12:00-02:30 | J77: 02:30-04:30 | L77: 04:30-06:00
F78: 10:00 - 12:00 PM | H78: 12:00-02:30 | J78: 02:30-04:30 | L78: 04:30-06:00
F79: 10:00 - 12:00 PM | H79: 12:00-02:30 | J79: 02:30-04:30 | L79: 04:30-06:00
F80: 10:00 - 12:00 PM | H80: 12:00-02:30 | J80: 02:30-04:30 | L80: 04:30-06:00
F81: 10:00 - 12:00 PM | H81: 12:00-02:30 | J81: 02:30-04:30 | L81: 04:30-06:00
... F810: 10:00 - 12:00 PM | H810: 12:00-02:30 | J810: 02:30-04:30 | L810: 04:30-06:00

Sheet 6
A1: Prospect Name | B1: Number | C1: Attempts Missing | D1: Status | E1: stage | F1: Call Slot 1 | G1: Attempt 1 | H1: Call Slot 2 | I1: Attempt 2 | J1: Call Slot 3 | K1: Attempt-3 | L1: Call Slot 4 | M1: Attempt-4 | N1: Lead Type | O1: Notes | P1: Next Step | Q1: date
B2: 92 333 3597982 | D2: Call Attended | E2: Awaiting Response | F2: 10:00 - 12:00 PM | G2: Call Recieved | H2: 12:00-02:30 | J2: 02:30-04:30 | L2: 04:30-06:00 | O2: will confirm me in 30 mins, call him back on 5th may
A3: Shoaib Malik | B3: 92 308 3635652 | D3: Call Attended | E3: Awaiting payment | F3: 10:00 - 12:00 PM | G3: Call Recieved | H3: 12:00-02:30 | J3: 02:30-04:30 | L3: 04:30-06:00 | O3: form filled, will pay fees till 6 june
B4: 92 309 7109717 | D4: Not Attended | E4: Contacted | F4: 10:00 - 12:00 PM | G4: Not Recieved | H4: 12:00-02:30 | I4: Call Recieved | J4: 02:30-04:30 | K4: Call Recieved | L4: 04:30-06:00 | M4: Not Recieved | O4: immediately cut the call
B5: 92 336 4429052 | D5: Not Attended | E5: Closed - Lost | F5: 10:00 - 12:00 PM | G5: Client lost | H5: 12:00-02:30 | I5: Client lost | J5: 02:30-04:30 | K5: Client lost | L5: 04:30-06:00 | M5: Client lost | O5: lost lead
B6: 92 336 8238809 | D6: Not Attended | E6: Contacted | F6: 10:00 - 12:00 PM | G6: Not Recieved | H6: 12:00-02:30 | I6: Not Recieved | J6: 02:30-04:30 | L6: 04:30-06:00 | M6: Call Recieved | O6: details shared again on whatsapp
B7: 92 355 4420566 | D7: Not Attended | E7: Call not Recieved | F7: 10:00 - 12:00 PM | G7: Not Recieved | H7: 12:00-02:30 | I7: Not Recieved | J7: 02:30-04:30 | K7: Not Recieved | L7: 04:30-06:00 | M7: Not Recieved | O7: no response
B8: 92 328 6000794 | D8: Not Attended | E8: Call not Recieved | F8: 10:00 - 12:00 PM | G8: Not Recieved | H8: 12:00-02:30 | I8: Not Recieved | J8: 02:30-04:30 | K8: Not Recieved | L8: 04:30-06:00 | M8: Not Recieved | O8: no response
B9: 92 340 0581572 | D9: Call Attended | E9: Awaiting Response | F9: 10:00 - 12:00 PM | G9: Call Recieved | H9: 12:00-02:30 | J9: 02:30-04:30 | K9: Call Recieved | L9: 04:30-06:00 | M9: Call Recieved | O9: details shared again on whatsapp
B10: 92 333 9712136 | D10: Call Attended | E10: Contacted | F10: 10:00 - 12:00 PM | G10: Call Recieved | H10: 12:00-02:30 | J10: 02:30-04:30 | K10: Not Recieved | L10: 04:30-06:00 | M10: Not Recieved | O10: he cut the call
B11: 92 341 0045963 | D11: Not Attended | E11: Closed - Lost | F11: 10:00 - 12:00 PM | G11: Client lost | H11: 12:00-02:30 | I11: Client lost | J11: 02:30-04:30 | K11: Client lost | L11: 04:30-06:00 | M11: Client lost | O11: lost lead
B12: 92 329 7685207 | D12: Not Attended | E12: Closed - Lost | F12: 10:00 - 12:00 PM | G12: Client lost | H12: 12:00-02:30 | I12: Client lost | J12: 02:30-04:30 | K12: Client lost | L12: 04:30-06:00 | M12: Client lost | O12: not interested
B13: 92 348 4534609 | D13: Not Attended | E13: Call not Recieved | F13: 10:00 - 12:00 PM | G13: Not Recieved | H13: 12:00-02:30 | I13: Not Recieved | J13: 02:30-04:30 | K13: Not Recieved | L13: 04:30-06:00 | M13: Not Recieved | O13: no response
B14: 92 319 0382503 | D14: Call Attended | E14: Closed - Lost | F14: 10:00 - 12:00 PM | G14: Client lost | H14: 12:00-02:30 | I14: Client lost | J14: 02:30-04:30 | K14: Client lost | L14: 04:30-06:00 | M14: Client lost | O14: lost lead
B15: 92 340 7363012 | D15: Not Attended | E15: Call not Recieved | F15: 10:00 - 12:00 PM | G15: Not Recieved | H15: 12:00-02:30 | I15: Not Recieved | J15: 02:30-04:30 | K15: Not Recieved | L15: 04:30-06:00 | M15: Not Recieved | O15: no response
B16: 92 331 8910393 | E16: Awaiting payment | F16: 10:00 - 12:00 PM | H16: 12:00-02:30 | J16: 02:30-04:30 | L16: 04:30-06:00 | O16: will pay fees after till 11 june
B17: 92 311 7576492 | D17: Not Attended | E17: Call not Recieved | F17: 10:00 - 12:00 PM | G17: Not Recieved | H17: 12:00-02:30 | I17: Not Recieved | J17: 02:30-04:30 | K17: Not Recieved | L17: 04:30-06:00 | M17: Not Recieved | O17: no response
B18: 92 301 6802186 | D18: Not Attended | E18: Contacted | F18: 10:00 - 12:00 PM | G18: Call Recieved | H18: 12:00-02:30 | I18: Not Recieved | J18: 02:30-04:30 | K18: Not Recieved | L18: 04:30-06:00 | M18: Not Recieved | O18: his brother allpied for the course
B19: 92 325 9206535 | D19: Not Attended | E19: Call not Recieved | F19: 10:00 - 12:00 PM | G19: Not Recieved | H19: 12:00-02:30 | I19: Not Recieved | J19: 02:30-04:30 | K19: Not Recieved | L19: 04:30-06:00 | M19: Not Recieved | O19: no response
B20: 92 340 5544831 | D20: Call Attended | E20: Awaiting Response | F20: 10:00 - 12:00 PM | H20: 12:00-02:30 | I20: Call Recieved | J20: 02:30-04:30 | L20: 04:30-06:00 | O20: details shared again on whatsapp
B21: 92 332 1626073 | D21: Not Attended | E21: Call not Recieved | F21: 10:00 - 12:00 PM | G21: Not Recieved | H21: 12:00-02:30 | I21: Not Recieved | J21: 02:30-04:30 | K21: Not Recieved | L21: 04:30-06:00 | M21: Not Recieved | O21: no response
B22: 92 315 3721344 | D22: Not Attended | E22: Call not Recieved | F22: 10:00 - 12:00 PM | G22: Not Recieved | H22: 12:00-02:30 | I22: Not Recieved | J22: 02:30-04:30 | K22: Not Recieved | L22: 04:30-06:00 | M22: Not Recieved | O22: no response
A23: Khansa ch | B23: 92 305 6189462 | D23: Call Attended | E23: Closed - Lost | F23: 10:00 - 12:00 PM | G23: Client lost | H23: 12:00-02:30 | I23: Client lost | J23: 02:30-04:30 | K23: Client lost | L23: 04:30-06:00 | M23: Client lost | O23: blocked me after see the price
B24: 92 313 1347114 | D24: Not Attended | E24: Call not Recieved | F24: 10:00 - 12:00 PM | G24: Not Recieved | H24: 12:00-02:30 | I24: Not Recieved | J24: 02:30-04:30 | K24: Not Recieved | L24: 04:30-06:00 | M24: Not Recieved | O24: no response
B25: 92 314 1272749 | E25: enroll in next batch | F25: 10:00 - 12:00 PM | H25: 12:00-02:30 | J25: 02:30-04:30 | L25: 04:30-06:00 | O25: cannot attend classes because of finals
B26: 92 319 6934822 | D26: Not Attended | E26: Closed - Lost | F26: 10:00 - 12:00 PM | G26: Client lost | H26: 12:00-02:30 | I26: Client lost | J26: 02:30-04:30 | K26: Client lost | L26: 04:30-06:00 | M26: Client lost | O26: lost lead
B27: 92 342 1213536 | D27: Not Attended | E27: Closed - Lost | F27: 10:00 - 12:00 PM | G27: Client lost | H27: 12:00-02:30 | I27: Client lost | J27: 02:30-04:30 | K27: Client lost | L27: 04:30-06:00 | M27: Client lost | O27: not interested in data science
B28: 92 349 1836928 | D28: Not Attended | E28: Call not Recieved | F28: 10:00 - 12:00 PM | G28: Not Recieved | H28: 12:00-02:30 | I28: Not Recieved | J28: 02:30-04:30 | K28: Not Recieved | L28: 04:30-06:00 | M28: Not Recieved | O28: no response
B29: 92 340 6508936 | D29: Call Attended | E29: Closed - Lost | F29: 10:00 - 12:00 PM | G29: Client lost | H29: 12:00-02:30 | I29: Client lost | J29: 02:30-04:30 | K29: Client lost | L29: 04:30-06:00 | M29: Client lost | O29: details again shared on whatsapp
A30: Aiman | B30: 92 312 5592849 | D30: Not Attended | E30: demo | F30: 10:00 - 12:00 PM | G30: Not Recieved | H30: 12:00-02:30 | I30: Not Recieved | J30: 02:30-04:30 | K30: Not Recieved | L30: 04:30-06:00 | M30: Not Recieved | O30: no response
B31: 92 304 1282405 | D31: Not Attended | E31: Call not Recieved | F31: 10:00 - 12:00 PM | G31: Not Recieved | H31: 12:00-02:30 | I31: Not Recieved | J31: 02:30-04:30 | K31: Not Recieved | L31: 04:30-06:00 | M31: Not Recieved | O31: no response
B32: 92 301 3283498 | D32: Call Attended | E32: Awaiting Response | F32: 10:00 - 12:00 PM | H32: 12:00-02:30 | I32: Call Recieved | J32: 02:30-04:30 | L32: 04:30-06:00 | O32: rn he's in a village, he'll confirm me once he come to the city
B33: 92 300 8797662 | D33: Not Attended | E33: Call not Recieved | F33: 10:00 - 12:00 PM | G33: Not Recieved | H33: 12:00-02:30 | I33: Not Recieved | J33: 02:30-04:30 | K33: Not Recieved | L33: 04:30-06:00 | M33: Not Recieved | O33: no response
B34: 92 342 6064181 | D34: Call Attended | E34: Closed - Lost | F34: 10:00 - 12:00 PM | G34: Client lost | H34: 12:00-02:30 | I34: Client lost | J34: 02:30-04:30 | K34: Client lost | L34: 04:30-06:00 | M34: Client lost | O34: lost lead
B35: 92 325 5171370 | D35: Call Attended | E35: Contacted | F35: 10:00 - 12:00 PM | G35: Call Recieved | H35: 12:00-02:30 | I35: Call Recieved | J35: 02:30-04:30 | K35: Not Recieved | L35: 04:30-06:00 | M35: Not Recieved | O35: Will fill form
A36: Shahzina shahbaz | B36: 92 309 6144786 | D36: Call Attended | E36: form filled | F36: 10:00 - 12:00 PM | G36: Call Recieved | H36: 12:00-02:30 | I36: Not Recieved | J36: 02:30-04:30 | L36: 04:30-06:00 | M36: Not Recieved | O36: she's not at home
B37: 92 319 7634505 | D37: Call Attended | E37: Awaiting Response | F37: 10:00 - 12:00 PM | H37: 12:00-02:30 | I37: Call Recieved | J37: 02:30-04:30 | L37: 04:30-06:00 | O37: busy in exams. will contact him again on 16th june
B38: 92 324 9506696 | D38: Call Attended | E38: Awaiting Response | F38: 10:00 - 12:00 PM | H38: 12:00-02:30 | I38: Call Recieved | J38: 02:30-04:30 | L38: 04:30-06:00 | O38: will confirm me by today evening
B39: 92 320 7433220 | D39: Call Attended | E39: Closed - Lost | F39: 10:00 - 12:00 PM | G39: Client lost | H39: 12:00-02:30 | I39: Client lost | J39: 02:30-04:30 | K39: Client lost | L39: 04:30-06:00 | M39: Client lost | O39: not interested
B40: 92 325 8804362 | D40: Not Attended | E40: Closed - Lost | F40: 10:00 - 12:00 PM | G40: Client lost | H40: 12:00-02:30 | I40: Client lost | J40: 02:30-04:30 | K40: Client lost | L40: 04:30-06:00 | M40: Client lost | O40: not interested in data science and AI course
B41: 92 333 2266514 | D41: Call Attended | E41: Closed - Lost | F41: 10:00 - 12:00 PM | G41: Client lost | H41: 12:00-02:30 | I41: Client lost | J41: 02:30-04:30 | K41: Client lost | L41: 04:30-06:00 | M41: Client lost | O41: details shared again on whatsapp
B42: 92 306 3074585 | D42: Call Attended | E42: Closed - Lost | F42: 10:00 - 12:00 PM | G42: Client lost | H42: 12:00-02:30 | I42: Client lost | J42: 02:30-04:30 | K42: Client lost | L42: 04:30-06:00 | M42: Client lost | O42: lost lead
B43: 92 355 4594875 | D43: Call Attended | E43: Closed - Lost | F43: 10:00 - 12:00 PM | G43: Client lost | H43: 12:00-02:30 | I43: Client lost | J43: 02:30-04:30 | K43: Client lost | L43: 04:30-06:00 | M43: Client lost | O43: lost lead
B44: 92 343 2332260 | D44: Not Attended | E44: Call not Recieved | F44: 10:00 - 12:00 PM | G44: Not Recieved | H44: 12:00-02:30 | I44: Not Recieved | J44: 02:30-04:30 | K44: Not Recieved | L44: 04:30-06:00 | M44: Not Recieved | O44: no response
B45: 92 308 6540681 | D45: Call Attended | E45: demo | F45: 10:00 - 12:00 PM | H45: 12:00-02:30 | I45: Call Recieved | J45: 02:30-04:30 | K45: Call Recieved | L45: 04:30-06:00 | O45: Demo class
B46: 92 309 1189769 | D46: Call Attended | E46: Awaiting payment | F46: 10:00 - 12:00 PM | H46: 12:00-02:30 | I46: Not Recieved | J46: 02:30-04:30 | K46: Call Recieved | L46: 04:30-06:00 | M46: Call Recieved | O46: form filled, will apy fees till 18 june
B47: 92 332 3746451 | D47: Call Attended | E47: Awaiting Response | F47: 10:00 - 12:00 PM | H47: 12:00-02:30 | J47: 02:30-04:30 | K47: Call Recieved | L47: 04:30-06:00 | O47: will confirm me till evening
B48: 92 355 4466976 | D48: Not Attended | E48: Call not Recieved | F48: 10:00 - 12:00 PM | G48: Not Recieved | H48: 12:00-02:30 | I48: Not Recieved | J48: 02:30-04:30 | K48: Not Recieved | L48: 04:30-06:00 | M48: Not Recieved | O48: no response
B49: 92 333 5286871 | D49: Not Attended | E49: Call not Recieved | F49: 10:00 - 12:00 PM | G49: Not Recieved | H49: 12:00-02:30 | I49: Not Recieved | J49: 02:30-04:30 | K49: Not Recieved | L49: 04:30-06:00 | M49: Not Recieved | O49: no response
B50: 92 342 2882784 | D50: Not Attended | E50: Closed - Lost | F50: 10:00 - 12:00 PM | G50: Client lost | H50: 12:00-02:30 | I50: Client lost | J50: 02:30-04:30 | K50: Client lost | L50: 04:30-06:00 | M50: Client lost | O50: not interested
B51: 92 335 8291028 | D51: Call Attended | E51: Contacted | F51: 10:00 - 12:00 PM | G51: Not Recieved | H51: 12:00-02:30 | I51: Not Recieved | J51: 02:30-04:30 | K51: Call Recieved | L51: 04:30-06:00 | M51: Not Recieved | O51: signal issue, texted her on whatsapp again
B52: 92 333 2181611 | D52: Not Attended | E52: Call not Recieved | F52: 10:00 - 12:00 PM | G52: Not Recieved | H52: 12:00-02:30 | I52: Not Recieved | J52: 02:30-04:30 | K52: Not Recieved | L52: 04:30-06:00 | M52: Not Recieved | O52: no response
B53: 92 317 5699767 | D53: Not Attended | E53: form filled | F53: 10:00 - 12:00 PM | G53: Not Recieved | H53: 12:00-02:30 | J53: 02:30-04:30 | K53: Not Recieved | L53: 04:30-06:00 | M53: Not Recieved | O53: form filled, no response
B54: 92 327 0808621 | D54: Call Attended | E54: Closed - Lost | F54: 10:00 - 12:00 PM | G54: Client lost | H54: 12:00-02:30 | I54: Client lost | J54: 02:30-04:30 | K54: Client lost | L54: 04:30-06:00 | M54: Client lost | O54: she thought it is related to business, not interested in course
B55: 92 302 0747748 | D55: Not Attended | E55: Call not Recieved | F55: 10:00 - 12:00 PM | G55: Not Recieved | H55: 12:00-02:30 | I55: Not Recieved | J55: 02:30-04:30 | K55: Not Recieved | L55: 04:30-06:00 | M55: Not Recieved | O55: no response
B56: 92 321 3344514 | D56: Call Attended | E56: demo | F56: 10:00 - 12:00 PM | H56: 12:00-02:30 | J56: 02:30-04:30 | K56: Call Recieved | L56: 04:30-06:00 | O56: will join demo class
B57: 1 (204) 479-2673 | E57: Closed - Lost | F57: 10:00 - 12:00 PM | G57: Client lost | H57: 12:00-02:30 | I57: Client lost | J57: Client lost | K57: Client lost | L57: 04:30-06:00 | O57: busy in other stuff
B58: 92 329 5846537 | D58: Not Attended | E58: Call not Recieved | F58: 10:00 - 12:00 PM | G58: Not Recieved | H58: 12:00-02:30 | I58: Not Recieved | J58: 02:30-04:30 | K58: Not Recieved | L58: 04:30-06:00 | M58: Not Recieved | O58: no response
B59: 92 326 2784281 | D59: Not Attended | E59: Closed - Lost | F59: 10:00 - 12:00 PM | G59: Client lost | H59: 12:00-02:30 | I59: Client lost | J59: 02:30-04:30 | K59: Client lost | L59: 04:30-06:00 | M59: Client lost | O59: not interested
B60: 92 310 3140187 | D60: Call Attended | E60: Contacted | F60: 10:00 - 12:00 PM | G60: Not Recieved | H60: 12:00-02:30 | I60: Not Recieved | J60: 02:30-04:30 | K60: Not Recieved | L60: 04:30-06:00 | M60: Call Recieved | O60: details again shared on whatsapp
B61: 92 332 1139547 | D61: Not Attended | E61: Call not Recieved | F61: 10:00 - 12:00 PM | G61: Not Recieved | H61: 12:00-02:30 | I61: Not Recieved | J61: 02:30-04:30 | K61: Not Recieved | L61: 04:30-06:00 | M61: Not Recieved | O61: no response
B62: 92 302 5374476 | D62: Call Attended | E62: Contacted | F62: 10:00 - 12:00 PM | G62: Not Recieved | H62: 12:00-02:30 | I62: Not Recieved | J62: 02:30-04:30 | K62: Not Recieved | L62: 04:30-06:00 | M62: Please Call later | O62: busy rn, call me later
B63: 92 317 8775599 | D63: Not Attended | E63: Closed - Lost | F63: 10:00 - 12:00 PM | G63: Client lost | H63: 12:00-02:30 | I63: Client lost | J63: 02:30-04:30 | K63: Client lost | L63: 04:30-06:00 | M63: Client lost | O63: not interested
A64: Vishal | B64: 92 349 4434360 | D64: Call Attended | E64: Closed - Lost | F64: 10:00 - 12:00 PM | G64: Client lost | H64: 12:00-02:30 | I64: Client lost | J64: 02:30-04:30 | K64: Client lost | L64: 04:30-06:00 | M64: Client lost | O64: He'll do from youtube.
B65: 92 321 2040491 | D65: Call Attended | E65: Awaiting Response | F65: 10:00 - 12:00 PM | G65: Not Recieved | H65: 12:00-02:30 | I65: Please Call later | J65: 02:30-04:30 | L65: 04:30-06:00 | M65: Call Recieved | O65: signal issue
B66: 92 348 9926130 | D66: Call Attended | E66: Contacted | F66: 10:00 - 12:00 PM | G66: Not Recieved | H66: 12:00-02:30 | I66: Call Recieved | J66: 02:30-04:30 | K66: Not Recieved | L66: 04:30-06:00 | M66: Not Recieved | O66: immediately cut the call.
B67: 92 345 5376131 | D67: Not Attended | E67: Call not Recieved | F67: 10:00 - 12:00 PM | G67: Not Recieved | H67: 12:00-02:30 | I67: Not Recieved | J67: 02:30-04:30 | K67: Not Recieved | L67: 04:30-06:00 | M67: Not Recieved | O67: no response
B68: 92 332 1510544 | D68: Not Attended | E68: Closed - Lost | F68: 10:00 - 12:00 PM | G68: Client lost | H68: 12:00-02:30 | I68: Client lost | J68: 02:30-04:30 | K68: Client lost | L68: 04:30-06:00 | M68: Client lost | O68: enroll in banoqabil course
B69: 92 307 4775583 | E69: Awaiting Response | F69: 10:00 - 12:00 PM | H69: 12:00-02:30 | J69: 02:30-04:30 | L69: 04:30-06:00 | O69: will contact again on 13 june
B70: 92 325 8167090 | D70: Not Attended | E70: enroll in next batch | F70: 10:00 - 12:00 PM | H70: 12:00-02:30 | I70: Not Recieved | J70: 02:30-04:30 | L70: 04:30-06:00 | M70: Not Recieved | O70: no response
B71: 92 343 2453441 | D71: Not Attended | E71: Closed - Lost | F71: 10:00 - 12:00 PM | G71: Client lost | H71: 12:00-02:30 | I71: Client lost | J71: 02:30-04:30 | K71: Client lost | L71: 04:30-06:00 | M71: Client lost | O71: interested in summer vacation course
B72: 92 316 5621995 | D72: Call Attended | E72: Awaiting Response | F72: 10:00 - 12:00 PM | H72: 12:00-02:30 | J72: 02:30-04:30 | L72: 04:30-06:00 | M72: Call Recieved | O72: interested, form shared
B73: 92 333 3401044 | D73: Not Attended | E73: Closed - Lost | F73: 10:00 - 12:00 PM | G73: Client lost | H73: 12:00-02:30 | I73: Client lost | J73: 02:30-04:30 | K73: Client lost | L73: 04:30-06:00 | M73: Client lost | O73: timing isn't suitable for him
B74: 92 335 3844971 | D74: Not Attended | E74: Closed - Lost | F74: 10:00 - 12:00 PM | G74: Client lost | H74: 12:00-02:30 | I74: Client lost | J74: 02:30-04:30 | K74: Client lost | L74: 04:30-06:00 | M74: Client lost | O74: signal issue, texted him on whatsapp
B75: 92 310 9972109 | D75: Not Attended | E75: Call not Recieved | F75: 10:00 - 12:00 PM | G75: Not Recieved | H75: 12:00-02:30 | I75: Not Recieved | J75: 02:30-04:30 | K75: Not Recieved | L75: 04:30-06:00 | M75: Not Recieved | O75: no response
B76: 92 321 2256441 | D76: Call Attended | E76: Contacted | F76: 10:00 - 12:00 PM | G76: Call Recieved | H76: 12:00-02:30 | I76: Not Recieved | J76: 02:30-04:30 | K76: Not Recieved | L76: 04:30-06:00 | M76: Please Call later | O76: details shared again on whatsapp
B77: 92 308 2804529 | D77: Not Attended | E77: Call not Recieved | F77: 10:00 - 12:00 PM | G77: Not Recieved | H77: 12:00-02:30 | I77: Not Recieved | J77: 02:30-04:30 | K77: Not Recieved | L77: 04:30-06:00 | M77: Not Recieved
B78: 92 331 6677422 | D78: Not Attended | E78: Call not Recieved | F78: 10:00 - 12:00 PM | G78: Not Recieved | H78: 12:00-02:30 | I78: Not Recieved | J78: 02:30-04:30 | K78: Not Recieved | L78: 04:30-06:00 | M78: Not Recieved | O78: no response
O88: no response

Sheet Sheet10
A1: Name | B1: Phone Number
A2: Samra | B2: 92 344 4853224
A3: Hadia | B3: 0331 5600623
A4: Shams | B4: 92 307 0079544
A5: Unknown-2 | B5: 0347-3063900
A6: Mamoona | B6: 0347-2292892
A7: Ahmed | B7: 0320-7807857
A8: Unknown-4 | B8: 0330-8675442
A9: Dr Farzana | B9: 92 332 3633535
A10: Irfan | B10: 92 342 0821163
A11: Farhan | B11: 92 314 5001584
A12: Unknown-6 | B12: 92 336 6222293
... A42: Wasif | B42: 92 332 5130344

Sheet Sheet11
A1: 92 314 2639113
A2: 92 301 2073908
A3: 0311 1575311
A4: 0332 3740133
A5: 0329 8167660
A6: 0300 7872645
A7: 0317 0920130
A8: 0331 2133552
A9: 0308 2181928
A10: 0333 0218820
A11: 0347 3786945
A12: 0300 5447177
... A130: 0344 4045609

Sheet 1
A1: Prospect Name | B1: Number | C1: Attempts done | D1: Status | E1: stage | F1: Call Slot 1 | G1: Attempt 1 | H1: Call Slot 2 | I1: Attempt 2 | J1: Call Slot 3 | K1: Attempt-3 | L1: Call Slot 4 | M1: Attempt-4 | N1: Notes | O1: Next Step | P1: Column 1
A2: zulfiqar Ali | B2: 0328 4781718 | C2: =COUNTIF(G2:M2, "Not attempted") + COUNTIF(G2:M2, "Not Recieved") -> 0 | D2: Call Attended | E2: Closed - Lost | F2: 10:00 - 12:00 PM | G2: Client lost | H2: 12:00-02:30 | I2: Call Recieved | J2: 02:30-04:30 | K2: Client lost | L2: 04:30-06:00 | M2: Client lost | N2: lost lead
A3: muhaamad zeeshan | B3: 0348 0619993 | C3: =COUNTIF(G3:M3, "Not attempted") + COUNTIF(G3:M3, "Not Recieved") -> 2 | D3: Call Attended | E3: Contacted | F3: 10:00 - 12:00 PM | G3: Call Recieved | H3: 12:00-02:30 | I3: Not Recieved | J3: 02:30-04:30 | K3: Call Recieved | L3: 04:30-06:00 | M3: Not Recieved | N3: will inform by today evening
B4: 0348 8915568/ 0313 0159585 | C4: =COUNTIF(G4:M4, "Not attempted") + COUNTIF(G4:M4, "Not Recieved") -> 1 | D4: Call Attended | E4: Closed - Won | F4: 10:00 - 12:00 PM | G4: Call Recieved | H4: 12:00-02:30 | I4: Call Recieved | J4: 02:30-04:30 | K4: Not Recieved | L4: 04:30-06:00 | M4: Call Recieved | N4: paid
A5: Unknown | B5: 0336 6491115 | C5: =COUNTIF(G5:M5, "Not attempted") + COUNTIF(G5:M5, "Not Recieved") -> 0 | D5: Call Attended | E5: Closed - Lost | F5: 10:00 - 12:00 PM | G5: Client lost | H5: 12:00-02:30 | I5: Call Recieved | J5: 02:30-04:30 | K5: Client lost | L5: 04:30-06:00 | M5: Client lost | N5: lost lead
A6: Unknown | B6: 0346 7124633 | C6: =COUNTIF(G6:M6, "Not attempted") + COUNTIF(G6:M6, "Not Recieved") -> 2 | D6: Call Attended | E6: Closed - Lost | F6: 10:00 - 12:00 PM | G6: Call Recieved | H6: 12:00-02:30 | I6: Not attempted | J6: 02:30-04:30 | K6: Call Recieved | L6: 04:30-06:00 | M6: Not attempted | N6: lost lead
A7: muhammad sohail | B7: 0333 6900114 | C7: =COUNTIF(G7:M7, "Not attempted") + COUNTIF(G7:M7, "Not Recieved") -> 0 | D7: Call Attended | E7: Closed - Lost | F7: 10:00 - 12:00 PM | G7: Call Recieved | H7: 12:00-02:30 | I7: Call Recieved | J7: 02:30-04:30 | K7: Call Recieved | L7: 04:30-06:00 | M7: Call Recieved | N7: lost lead
A8: Unknown | B8: 0316 1316907 | C8: =COUNTIF(G8:M8, "Not attempted") + COUNTIF(G8:M8, "Not Recieved") -> 0 | D8: Call Attended | E8: Closed - Lost | F8: 10:00 - 12:00 PM | G8: Client lost | H8: 12:00-02:30 | I8: Call Recieved | J8: 02:30-04:30 | K8: Client lost | L8: 04:30-06:00 | M8: Client lost | N8: lost lead
A9: Unknown | B9: 0319 3509440 | C9: =COUNTIF(G9:M9, "Not attempted") + COUNTIF(G9:M9, "Not Recieved") -> 0 | D9: Call Attended | E9: Closed - Lost | G9: Client lost | I9: Client lost | K9: Call Recieved | M9: Client lost | N9: lost lead
A10: Aftab Ashiq | B10: 0345 9208701 | C10: =COUNTIF(G10:M10, "Not attempted") + COUNTIF(G10:M10, "Not Recieved") -> 1 | D10: Call Attended | E10: Closed - Lost | F10: 10:00 - 12:00 PM | G10: Client lost | H10: 12:00-02:30 | I10: Call Recieved | J10: 02:30-04:30 | K10: Not Recieved | L10: 04:30-06:00 | M10: Client lost | N10: lost lead
B11: 0300 4754980 | C11: =COUNTIF(G11:M11, "Not attempted") + COUNTIF(G11:M11, "Not Recieved") -> 1 | D11: Call Attended | E11: Closed - Won | F11: 10:00 - 12:00 PM | G11: Call Recieved | H11: 12:00-02:30 | I11: Not Recieved | J11: 02:30-04:30 | K11: Call Recieved | L11: 04:30-06:00 | M11: Call Recieved | N11: pay by 25
A12: Unknown | B12: 0307 8647992 | C12: =COUNTIF(G12:M12, "Not attempted") + COUNTIF(G12:M12, "Not Recieved") -> 1 | D12: Call Attended | E12: Closed - Lost | F12: 10:00 - 12:00 PM | G12: Call Recieved | H12: 12:00-02:30 | I12: Call Recieved | J12: 02:30-04:30 | K12: Call Recieved | L12: 04:30-06:00 | M12: Not Recieved | N12: lost lead
A13: Unknown | B13: 0332 3154075 | C13: =COUNTIF(G13:M13, "Not attempted") + COUNTIF(G13:M13, "Not Recieved") -> 1 | D13: Not Attended | E13: Closed - Lost | F13: 10:00 - 12:00 PM | G13: Not Recieved | H13: 12:00-02:30 | I13: Client lost | J13: 02:30-04:30 | K13: Client lost | L13: 04:30-06:00 | M13: Client lost | N13: lost lead
A14: Unknown | B14: 0322 7567955 | C14: =COUNTIF(G14:M14, "Not attempted") + COUNTIF(G14:M14, "Not Recieved") -> 3 | D14: Call Attended | E14: Closed - Won | F14: 10:00 - 12:00 PM | G14: Not Recieved | H14: 12:00-02:30 | I14: Call Recieved | J14: 02:30-04:30 | K14: Not Recieved | L14: 04:30-06:00 | M14: Not Recieved | N14: no response
A15: Unknown | B15: 0319 8046813 | C15: =COUNTIF(G15:M15, "Not attempted") + COUNTIF(G15:M15, "Not Recieved") -> 0 | D15: Call Attended | E15: Closed - Lost | F15: 10:00 - 12:00 PM | G15: Call Recieved | H15: 12:00-02:30 | I15: Call Recieved | J15: 02:30-04:30 | K15: Client lost | L15: 04:30-06:00 | M15: Client lost | N15: lost lead
A16: Huzaifa | B16: 0336 2333934/ 0336 2333933 | C16: =COUNTIF(G16:M16, "Not attempted") + COUNTIF(G16:M16, "Not Recieved") -> 0 | D16: Call Attended | E16: Closed - Won | F16: 10:00 - 12:00 PM | G16: Call Recieved | H16: 12:00-02:30 | I16: Call Recieved | J16: 02:30-04:30 | K16: Call Recieved | L16: 04:30-06:00 | M16: Call Recieved | N16: paid
A17: Unknown | B17: 0312 9061344 | C17: =COUNTIF(G17:M17, "Not attempted") + COUNTIF(G17:M17, "Not Recieved") -> 2 | D17: Call Attended | E17: Demo | F17: 10:00 - 12:00 PM | G17: Not Recieved | H17: 12:00-02:30 | I17: Please Call later | J17: 02:30-04:30 | K17: Not Recieved | L17: 04:30-06:00 | M17: Call Recieved | N17: demo then decide
A18: Unknown | B18: 0342 0475836 | C18: =COUNTIF(G18:M18, "Not attempted") + COUNTIF(G18:M18, "Not Recieved") -> 0 | D18: Call Attended | E18: Closed - Lost | F18: 10:00 - 12:00 PM | G18: Call Recieved | H18: 12:00-02:30 | I18: Call Recieved | J18: 02:30-04:30 | K18: Client lost | L18: 04:30-06:00 | M18: Client lost | N18: lost lead
A19: Unknown | B19: 0355 5647456/ 0341 8993261 | C19: =COUNTIF(G19:M19, "Not attempted") + COUNTIF(G19:M19, "Not Recieved") -> 1 | D19: Call Attended | E19: Closed - Lost | F19: 10:00 - 12:00 PM | G19: Client lost | H19: 12:00-02:30 | I19: Client lost | J19: 02:30-04:30 | K19: Client lost | L19: 04:30-06:00 | M19: Not Recieved | N19: lost lead
A20: Unknown | B20: 0343 5585163 | C20: =COUNTIF(G20:M20, "Not attempted") + COUNTIF(G20:M20, "Not Recieved") -> 0 | D20: Call Attended | E20: Closed - Lost | F20: 10:00 - 12:00 PM | G20: Call Recieved | H20: 12:00-02:30 | I20: Client lost | J20: 02:30-04:30 | K20: Client lost | L20: 04:30-06:00 | M20: Client lost | N20: lost lead
B21: 0308 0864165 | C21: =COUNTIF(G21:M21, "Not attempted") + COUNTIF(G21:M21, "Not Recieved") -> 3 | D21: Call Attended | E21: Closed - Lost | F21: 10:00 - 12:00 PM | G21: Not Recieved | H21: 12:00-02:30 | I21: Call Recieved | J21: 02:30-04:30 | K21: Not Recieved | L21: 04:30-06:00 | M21: Not Recieved | N21: lost lead
B22: 0333 2366141 | C22: =COUNTIF(G22:M22, "Not attempted") + COUNTIF(G22:M22, "Not Recieved") -> 1 | D22: Call Attended | E22: Closed - Lost | F22: 10:00 - 12:00 PM | G22: Please Call later | H22: 12:00-02:30 | I22: Not Recieved | J22: 02:30-04:30 | K22: Call Recieved | L22: 04:30-06:00 | M22: Call Recieved | N22: lost lead
A23: Unknown | B23: 0314 8380754 | C23: =COUNTIF(G23:M23, "Not attempted") + COUNTIF(G23:M23, "Not Recieved") -> 1 | D23: Call Attended | E23: Closed - Lost | F23: 10:00 - 12:00 PM | G23: Client lost | H23: 12:00-02:30 | I23: Not Recieved | J23: 02:30-04:30 | K23: Please Call later | L23: 04:30-06:00 | M23: Client lost | N23: lost lead
A24: Unknown | B24: 0326 9784378 | C24: =COUNTIF(G24:M24, "Not attempted") + COUNTIF(G24:M24, "Not Recieved") -> 0 | D24: Call Attended | E24: Closed - Lost | F24: 10:00 - 12:00 PM | G24: Client lost | H24: 12:00-02:30 | I24: Call Recieved | J24: 02:30-04:30 | K24: Client lost | L24: 04:30-06:00 | M24: Client lost | N24: lost lead
A25: Unknown | B25: 0313 1160140 | C25: =COUNTIF(G25:M25, "Not attempted") + COUNTIF(G25:M25, "Not Recieved") -> 4 | D25: Call Attended | E25: Contacted | F25: 10:00 - 12:00 PM | G25: Not Recieved | H25: 12:00-02:30 | I25: Not Recieved | J25: 02:30-04:30 | K25: Not Recieved | L25: 04:30-06:00 | M25: Not Recieved | N25: no response
A26: Unknown | B26: 0312 1640492 | C26: =COUNTIF(G26:M26, "Not attempted") + COUNTIF(G26:M26, "Not Recieved") -> 0 | D26: Call Attended | E26: Closed - Lost | F26: 10:00 - 12:00 PM | G26: Client lost | H26: 12:00-02:30 | I26: Call Recieved | J26: 02:30-04:30 | K26: Client lost | L26: 04:30-06:00 | M26: Client lost | N26: lost lead
A27: saddiqa | B27: 0333 2351659 | C27: =COUNTIF(G27:M27, "Not attempted") + COUNTIF(G27:M27, "Not Recieved") -> 2 | D27: Call Attended | E27: Closed - Lost | F27: 10:00 - 12:00 PM | G27: Call Recieved | H27: 12:00-02:30 | I27: Not Recieved | J27: 02:30-04:30 | K27: Call Recieved | L27: 04:30-06:00 | M27: Not Recieved | N27: lost lead
A28: Unknown | B28: 0340 5160363 | C28: =COUNTIF(G28:M28, "Not attempted") + COUNTIF(G28:M28, "Not Recieved") -> 1 | D28: Not Attended | E28: Closed - Lost | F28: 10:00 - 12:00 PM | G28: Not Recieved | H28: 12:00-02:30 | I28: Client lost | J28: 02:30-04:30 | K28: Client lost | L28: 04:30-06:00 | M28: Client lost | N28: lost lead
A29: Unknown | B29: 0332 6400818 | C29: =COUNTIF(G29:M29, "Not attempted") + COUNTIF(G29:M29, "Not Recieved") -> 2 | D29: Call Attended | E29: Closed - Lost | F29: 10:00 - 12:00 PM | G29: Client lost | H29: 12:00-02:30 | I29: Call Recieved | J29: 02:30-04:30 | K29: Not Recieved | L29: 04:30-06:00 | M29: Not Recieved | N29: lost lead
A30: Unknown | B30: 0314 9716172 | C30: =COUNTIF(G30:M30, "Not attempted") + COUNTIF(G30:M30, "Not Recieved") -> 0 | D30: Call Attended | E30: Awaiting Response | F30: 10:00 - 12:00 PM | G30: Call Recieved | H30: 12:00-02:30 | I30: Call Recieved | J30: 02:30-04:30 | K30: Call Recieved | L30: 04:30-06:00 | M30: Call Recieved | N30: interested, need discount
A31: Unknown | B31: 0355 4350784 | C31: =COUNTIF(G31:M31, "Not attempted") + COUNTIF(G31:M31, "Not Recieved") -> 0 | D31: Call Attended | E31: Closed - Lost | F31: 10:00 - 12:00 PM | G31: Client lost | H31: 12:00-02:30 | I31: Client lost | J31: 02:30-04:30 | K31: Call Recieved | L31: 04:30-06:00 | M31: Client lost | N31: need free course
B32: 0330 9865000 | C32: =COUNTIF(G32:M32, "Not attempted") + COUNTIF(G32:M32, "Not Recieved") -> 2 | D32: Call Attended | E32: Closed - Lost | F32: 10:00 - 12:00 PM | G32: Not Recieved | H32: 12:00-02:30 | I32: Call Recieved | J32: 02:30-04:30 | K32: Call Recieved | L32: 04:30-06:00 | M32: Not attempted | N32: lost leafd
A33: Unknown | B33: 0304 8200211 | C33: =COUNTIF(G33:M33, "Not attempted") + COUNTIF(G33:M33, "Not Recieved") -> 1 | D33: Call Attended | E33: Closed - Lost | F33: 10:00 - 12:00 PM | G33: Client lost | H33: 12:00-02:30 | I33: Client lost | J33: 02:30-04:30 | K33: Client lost | L33: 04:30-06:00 | M33: Not Recieved | N33: lost lead
B34: 0307 9143435 | C34: =COUNTIF(G34:M34, "Not attempted") + COUNTIF(G34:M34, "Not Recieved") -> 0 | D34: Call Attended | E34: Closed - Won | F34: 10:00 - 12:00 PM | G34: Call Recieved | H34: 12:00-02:30 | I34: Call Recieved | J34: 02:30-04:30 | K34: Call Recieved | L34: 04:30-06:00 | M34: Call Recieved | N34: paid
A35: Unknown | B35: 0309 5771866 | C35: =COUNTIF(G35:M35, "Not attempted") + COUNTIF(G35:M35, "Not Recieved") -> 4 | D35: Call Attended | E35: Closed - Lost | F35: 10:00 - 12:00 PM | G35: Not Recieved | H35: 12:00-02:30 | I35: Not Recieved | J35: 02:30-04:30 | K35: Not Recieved | L35: 04:30-06:00 | M35: Not Recieved | N35: lost lead
A36: Unknown | B36: 0314 1014974 | C36: =COUNTIF(G36:M36, "Not attempted") + COUNTIF(G36:M36, "Not Recieved") -> 0 | D36: Call Attended | E36: Closed - Lost | F36: 10:00 - 12:00 PM | G36: Client lost | H36: 12:00-02:30 | I36: Client lost | J36: 02:30-04:30 | K36: Client lost | L36: 04:30-06:00 | M36: Client lost | N36: lost lead
A37: Unknown | B37: 0345 6663161 | C37: =COUNTIF(G37:M37, "Not attempted") + COUNTIF(G37:M37, "Not Recieved") -> 0 | D37: Call Attended | E37: Closed - Lost | F37: 10:00 - 12:00 PM | G37: Call Recieved | H37: 12:00-02:30 | I37: Client lost | J37: 02:30-04:30 | K37: Client lost | L37: 04:30-06:00 | M37: Client lost | N37: lost lead
A38: Tabinda | B38: 0333 2354410 | C38: =COUNTIF(G38:M38, "Not attempted") + COUNTIF(G38:M38, "Not Recieved") -> 3 | D38: Call Attended | E38: Closed - Won | F38: 10:00 - 12:00 PM | G38: Call Recieved | H38: 12:00-02:30 | I38: Not Recieved | J38: 02:30-04:30 | K38: Not Recieved | L38: 04:30-06:00 | M38: Not Recieved | N38: interested will join | O38: will inform
A39: Unknown | B39: 0324 3649217 | C39: =COUNTIF(G39:M39, "Not attempted") + COUNTIF(G39:M39, "Not Recieved") -> 0 | D39: Not Attended | E39: Closed - Lost | F39: 10:00 - 12:00 PM | G39: Client lost | H39: 12:00-02:30 | I39: Client lost | J39: 02:30-04:30 | K39: Client lost | L39: 04:30-06:00 | M39: Client lost | N39: lost lead
A40: Unknown | B40: 0300 3599194 | C40: =COUNTIF(G40:M40, "Not attempted") + COUNTIF(G40:M40, "Not Recieved") -> 0 | D40: Call Attended | E40: Closed - Lost | F40: 10:00 - 12:00 PM | G40: Client lost | H40: 12:00-02:30 | I40: Call Recieved | J40: 02:30-04:30 | K40: Client lost | L40: 04:30-06:00 | M40: Client lost | N40: lost lead
A41: Unknown | B41: 0341 0122018 | C41: =COUNTIF(G41:M41, "Not attempted") + COUNTIF(G41:M41, "Not Recieved") -> 1 | D41: Not Attended | E41: Closed - Lost | F41: 10:00 - 12:00 PM | G41: Client lost | H41: 12:00-02:30 | I41: Client lost | J41: 02:30-04:30 | K41: Not Recieved | L41: 04:30-06:00 | M41: Client lost | N41: lost lead
A42: Unknown | B42: 0346 6801724 | C42: =COUNTIF(G42:M42, "Not attempted") + COUNTIF(G42:M42, "Not Recieved") -> 0 | D42: Call Attended | E42: Closed - Lost | F42: 10:00 - 12:00 PM | G42: Call Recieved | H42: 12:00-02:30 | I42: Call Recieved | J42: 02:30-04:30 | K42: Client lost | L42: 04:30-06:00 | M42: Client lost | N42: lost lead
A43: Unknown | B43: 0331 7222272 | C43: =COUNTIF(G43:M43, "Not attempted") + COUNTIF(G43:M43, "Not Recieved") -> 1 | D43: Call Attended | E43: Closed - Lost | F43: 10:00 - 12:00 PM | G43: Not Recieved | H43: 12:00-02:30 | I43: Client lost | J43: 02:30-04:30 | K43: Client lost | L43: 04:30-06:00 | M43: Client lost | N43: lost lead
A44: umar farooq | B44: 0306 0346401 | C44: =COUNTIF(G44:M44, "Not attempted") + COUNTIF(G44:M44, "Not Recieved") -> 0 | D44: Call Attended | E44: Closed - Lost | F44: 10:00 - 12:00 PM | G44: Call Recieved | H44: 12:00-02:30 | I44: Call Recieved | J44: 02:30-04:30 | K44: Client lost | L44: 04:30-06:00 | M44: Client lost | N44: lost lead
A45: Unknown | B45: 0334 1360017 | C45: =COUNTIF(G45:M45, "Not attempted") + COUNTIF(G45:M45, "Not Recieved") -> 1 | D45: Call Attended | E45: Closed - Lost | F45: 10:00 - 12:00 PM | G45: Not Recieved | H45: 12:00-02:30 | I45: Call Recieved | J45: 02:30-04:30 | K45: Call Recieved | L45: 04:30-06:00 | M45: Client lost | N45: lost lead
A46: Sobia Noreen | B46: 0332 3285513 | C46: =COUNTIF(G46:M46, "Not attempted") + COUNTIF(G46:M46, "Not Recieved") -> 3 | D46: Call Attended | E46: Contacted | F46: 10:00 - 12:00 PM | G46: Call Recieved | H46: 12:00-02:30 | I46: Not Recieved | J46: 02:30-04:30 | K46: Not Recieved | L46: 04:30-06:00 | M46: Not Recieved | N46: share info via whatsapp
A47: Unknown | B47: 0332 2382883 | C47: =COUNTIF(G47:M47, "Not attempted") + COUNTIF(G47:M47, "Not Recieved") -> 0 | D47: Call Attended | E47: Closed - Lost | F47: 10:00 - 12:00 PM | G47: Client lost | H47: 12:00-02:30 | I47: Client lost | J47: 02:30-04:30 | K47: Client lost | L47: 04:30-06:00 | M47: Call Recieved | N47: lost lead
A48: Unknown | B48: 0322 7846874 | C48: =COUNTIF(G48:M48, "Not attempted") + COUNTIF(G48:M48, "Not Recieved") -> 0 | D48: Call Attended | E48: Closed - Lost | F48: 10:00 - 12:00 PM | G48: Call Recieved | H48: 12:00-02:30 | I48: Client lost | J48: 02:30-04:30 | K48: Client lost | L48: 04:30-06:00 | M48: Client lost | N48: lost lead
A49: Unknown | B49: 0315 5359795 | C49: =COUNTIF(G49:M49, "Not attempted") + COUNTIF(G49:M49, "Not Recieved") -> 0 | D49: Call Attended | E49: Closed - Lost | F49: 10:00 - 12:00 PM | G49: Call Recieved | H49: 12:00-02:30 | I49: Client lost | J49: 02:30-04:30 | K49: Client lost | L49: 04:30-06:00 | M49: Client lost | N49: lost lead
A50: Unknown-1 | B50: 0318 8464520 | C50: =COUNTIF(G50:M50, "Not attempted") + COUNTIF(G50:M50, "Not Recieved") -> 0 | D50: Call Attended | E50: Closed - Lost | F50: 10:00 - 12:00 PM | G50: Client lost | H50: 12:00-02:30 | I50: Client lost | J50: 02:30-04:30 | K50: Client lost | L50: 04:30-06:00 | M50: Call Recieved | N50: lost lead
... A52: Unknown | B52: 0324 1691774 | C52: =COUNTIF(G52:M52, "Not attempted") + COUNTIF(G52:M52, "Not Recieved") -> 0 | D52: Call Attended | E52: Closed - Lost | F52: 10:00 - 12:00 PM | G52: Call Recieved | H52: 12:00-02:30 | I52: Client lost | J52: 02:30-04:30 | K52: Client lost | L52: 04:30-06:00 | M52: Client lost | N52: lost lead
B53: 0316 1404474 | C53: =COUNTIF(G53:M53, "Not attempted") + COUNTIF(G53:M53, "Not Recieved") -> 4 | D53: Not Attended | E53: Closed - Lost | F53: 10:00 - 12:00 PM | G53: Not Recieved | H53: 12:00-02:30 | I53: Not Recieved | J53: 02:30-04:30 | K53: Not Recieved | L53: 04:30-06:00 | M53: Not Recieved | N53: lost lead
A54: Unknown | B54: 0349 1986855 | C54: =COUNTIF(G54:M54, "Not attempted") + COUNTIF(G54:M54, "Not Recieved") -> 1 | D54: Call Attended | E54: Closed - Lost | F54: 10:00 - 12:00 PM | G54: Not Recieved | H54: 12:00-02:30 | I54: Client lost | J54: 02:30-04:30 | K54: Client lost | L54: 04:30-06:00 | M54: Call Recieved | N54: lost lead
B55: 0305 6440943 | C55: =COUNTIF(G55:M55, "Not attempted") + COUNTIF(G55:M55, "Not Recieved") -> 2 | D55: Call Attended | E55: Demo | F55: 10:00 - 12:00 PM | G55: Not Recieved | H55: 12:00-02:30 | I55: Call Recieved | J55: 02:30-04:30 | K55: Not Recieved | L55: 04:30-06:00 | M55: Call Recieved
A56: Unknown | B56: 0346 7446531 | C56: =COUNTIF(G56:M56, "Not attempted") + COUNTIF(G56:M56, "Not Recieved") -> 1 | D56: Not Attended | E56: Closed - Lost | F56: 10:00 - 12:00 PM | G56: Not Recieved | H56: 12:00-02:30 | I56: Client lost | J56: 02:30-04:30 | K56: Client lost | L56: 04:30-06:00 | M56: Client lost | N56: lost lead
A57: Unknown | B57: 0301 9192143 | C57: =COUNTIF(G57:M57, "Not attempted") + COUNTIF(G57:M57, "Not Recieved") -> 1 | D57: Call Attended | E57: Closed - Lost | F57: 10:00 - 12:00 PM | G57: Not Recieved | H57: 12:00-02:30 | I57: Client lost | J57: 02:30-04:30 | K57: Client lost | L57: 04:30-06:00 | M57: Call Recieved | N57: lost lead
A58: syed tayyab akhtar | B58: 0322 3876867/ 0314 7874979 | C58: =COUNTIF(G58:M58, "Not attempted") + COUNTIF(G58:M58, "Not Recieved") -> 0 | D58: Call Attended | E58: Closed - Won | F58: 10:00 - 12:00 PM | G58: Call Recieved | H58: 12:00-02:30 | I58: Call Recieved | J58: 02:30-04:30 | K58: Call Recieved | L58: 04:30-06:00 | M58: Call Recieved | N58: interested | O58: will pay
A59: Shumaila | B59: 0318 1012011 | C59: =COUNTIF(G59:M59, "Not attempted") + COUNTIF(G59:M59, "Not Recieved") -> 0 | D59: Call Attended | E59: Closed - Lost | F59: 10:00 - 12:00 PM | G59: Call Recieved | H59: 12:00-02:30 | I59: Call Recieved | J59: 02:30-04:30 | K59: Call Recieved | L59: 04:30-06:00 | M59: Call Recieved | N59: lost lead
B60: 0317 3905543 | C60: =COUNTIF(G60:M60, "Not attempted") + COUNTIF(G60:M60, "Not Recieved") -> 2 | D60: Call Attended | E60: Closed - Lost | F60: 10:00 - 12:00 PM | G60: Call Recieved | H60: 12:00-02:30 | I60: Call Recieved | J60: 02:30-04:30 | K60: Not Recieved | L60: 04:30-06:00 | M60: Not Recieved | N60: need pyhsical
B61: 0311 0156510 | C61: =COUNTIF(G61:M61, "Not attempted") + COUNTIF(G61:M61, "Not Recieved") -> 0 | D61: Call Attended | E61: Demo | K61: Call Recieved | N61: interested
A62: Unknown | B62: 0334 3947129 | C62: =COUNTIF(G62:M62, "Not attempted") + COUNTIF(G62:M62, "Not Recieved") -> 0 | D62: Call Attended | E62: Closed - Lost | F62: 10:00 - 12:00 PM | G62: Call Recieved | H62: 12:00-02:30 | I62: Client lost | J62: 02:30-04:30 | K62: Client lost | L62: 04:30-06:00 | M62: Client lost | N62: need pyhsical
A63: Unknown | B63: 0320 9864478 | C63: =COUNTIF(G63:M63, "Not attempted") + COUNTIF(G63:M63, "Not Recieved") -> 0 | D63: Not Attended | E63: Closed - Lost | F63: 10:00 - 12:00 PM | G63: Client lost | H63: 12:00-02:30 | I63: Client lost | J63: 02:30-04:30 | K63: Client lost | L63: 04:30-06:00 | M63: Client lost | N63: lost lead
A64: Unknown | B64: 0301 7247178 | C64: =COUNTIF(G64:M64, "Not attempted") + COUNTIF(G64:M64, "Not Recieved") -> 0 | D64: Call Attended | E64: Closed - Lost | F64: 10:00 - 12:00 PM | G64: Call Recieved | H64: 12:00-02:30 | I64: Client lost | J64: 02:30-04:30 | K64: Call Recieved | L64: 04:30-06:00 | M64: Client lost | N64: lost lead
A65: Unknown | B65: 0355 5768242 | C65: =COUNTIF(G65:M65, "Not attempted") + COUNTIF(G65:M65, "Not Recieved") -> 0 | D65: Call Attended | E65: Closed - Lost | F65: 10:00 - 12:00 PM | G65: Call Recieved | H65: 12:00-02:30 | I65: Client lost | J65: 02:30-04:30 | K65: Client lost | L65: 04:30-06:00 | M65: Client lost | N65: lost lead
A66: Unknown | B66: 0355 4834563 | C66: =COUNTIF(G66:M66, "Not attempted") + COUNTIF(G66:M66, "Not Recieved") -> 0 | D66: Call Attended | E66: Closed - Lost | F66: 10:00 - 12:00 PM | G66: Call Recieved | H66: 12:00-02:30 | I66: Client lost | J66: 02:30-04:30 | K66: Client lost | L66: 04:30-06:00 | M66: Client lost | N66: lost lead
A67: Zaid | B67: 0315 4046402 | C67: =COUNTIF(G67:M67, "Not attempted") + COUNTIF(G67:M67, "Not Recieved") -> 0 | D67: Call Attended | E67: Closed - Lost | F67: 10:00 - 12:00 PM | G67: Call Recieved | H67: 12:00-02:30 | I67: Call Recieved | J67: 02:30-04:30 | K67: Call Recieved | L67: 04:30-06:00 | M67: Call Recieved | N67: lost lead
B68: 0310 1334350 | C68: =COUNTIF(G68:M68, "Not attempted") + COUNTIF(G68:M68, "Not Recieved") -> 1 | D68: Call Attended | E68: Demo | F68: 10:00 - 12:00 PM | G68: Call Recieved | H68: 12:00-02:30 | I68: Call Recieved | J68: 02:30-04:30 | K68: Not Recieved | L68: 04:30-06:00 | M68: Call Recieved | N68: demo
A69: Unknown | B69: 0321 7824794 | C69: =COUNTIF(G69:M69, "Not attempted") + COUNTIF(G69:M69, "Not Recieved") -> 2 | D69: Call Attended | E69: Contacted | F69: 10:00 - 12:00 PM | G69: Not Recieved | H69: 12:00-02:30 | I69: Call Recieved | J69: 02:30-04:30 | K69: Call Recieved | L69: 04:30-06:00 | M69: Not Recieved | N69: share info via whatsapp
A70: Unknown | B70: 0317 5547313 | C70: =COUNTIF(G70:M70, "Not attempted") + COUNTIF(G70:M70, "Not Recieved") -> 0 | D70: Call Attended | E70: Closed - Lost | F70: 10:00 - 12:00 PM | G70: Call Recieved | H70: 12:00-02:30 | I70: Call Recieved | J70: 02:30-04:30 | K70: Client lost | L70: 04:30-06:00 | M70: Client lost | N70: lost lead
A71: Unknown | B71: 0324 3872998 | C71: =COUNTIF(G71:M71, "Not attempted") + COUNTIF(G71:M71, "Not Recieved") -> 0 | D71: Call Attended | E71: Closed - Lost | F71: 10:00 - 12:00 PM | G71: Client lost | H71: 12:00-02:30 | I71: Call Recieved | J71: 02:30-04:30 | K71: Client lost | L71: 04:30-06:00 | M71: Client lost | N71: lost lead
A72: Unknown | B72: 0346 5397471 | C72: =COUNTIF(G72:M72, "Not attempted") + COUNTIF(G72:M72, "Not Recieved") -> 1 | D72: Call Attended | E72: Closed - Lost | F72: 10:00 - 12:00 PM | G72: Client lost | H72: 12:00-02:30 | I72: Call Recieved | J72: 02:30-04:30 | K72: Client lost | L72: 04:30-06:00 | M72: Not Recieved | N72: lost lead
A73: Unknown | B73: 0334 3767481 | C73: =COUNTIF(G73:M73, "Not attempted") + COUNTIF(G73:M73, "Not Recieved") -> 3 | D73: Call Attended | E73: Contacted | F73: 10:00 - 12:00 PM | G73: Not Recieved | H73: 12:00-02:30 | I73: Not Recieved | J73: 02:30-04:30 | K73: Call Recieved | L73: 04:30-06:00 | M73: Not Recieved | N73: no response
A74: Unknown | B74: 0349 3575263 | C74: =COUNTIF(G74:M74, "Not attempted") + COUNTIF(G74:M74, "Not Recieved") -> 0 | D74: Call Attended | E74: Closed - Lost | F74: 10:00 - 12:00 PM | G74: Client lost | H74: 12:00-02:30 | I74: Client lost | J74: 02:30-04:30 | K74: Client lost | L74: 04:30-06:00 | M74: Client lost | N74: lost lead
A75: Unknown | B75: 0333 3253241 | C75: =COUNTIF(G75:M75, "Not attempted") + COUNTIF(G75:M75, "Not Recieved") -> 4 | D75: Call Attended | E75: Contacted | F75: 10:00 - 12:00 PM | G75: Not Recieved | H75: 12:00-02:30 | I75: Not Recieved | J75: 02:30-04:30 | K75: Not Recieved | L75: 04:30-06:00 | M75: Not Recieved | N75: no response
A76: Unknown | B76: 0322 3264196 | C76: =COUNTIF(G76:M76, "Not attempted") + COUNTIF(G76:M76, "Not Recieved") -> 1 | D76: Call Attended | E76: Closed - Lost | F76: 10:00 - 12:00 PM | G76: Call Recieved | H76: 12:00-02:30 | I76: Client lost | J76: 02:30-04:30 | K76: Client lost | L76: 04:30-06:00 | M76: Not Recieved | N76: lost lead
A77: Hamna | B77: 0315 2436714 | C77: =COUNTIF(G77:M77, "Not attempted") + COUNTIF(G77:M77, "Not Recieved") -> 3 | D77: Call Attended | E77: Closed - Lost | F77: 10:00 - 12:00 PM | G77: Call Recieved | H77: 12:00-02:30 | I77: Not Recieved | J77: 02:30-04:30 | K77: Not Recieved | L77: 04:30-06:00 | M77: Not Recieved | N77: inform by sat
A78: Unknown | B78: 0311 6176747 | C78: =COUNTIF(G78:M78, "Not attempted") + COUNTIF(G78:M78, "Not Recieved") -> 0 | D78: Call Attended | E78: Closed - Lost | F78: 10:00 - 12:00 PM | G78: Call Recieved | H78: 12:00-02:30 | I78: Client lost | J78: 02:30-04:30 | K78: Client lost | L78: 04:30-06:00 | M78: Client lost | N78: lost lead
A79: Unknown | B79: 0321 0011156 | C79: =COUNTIF(G79:M79, "Not attempted") + COUNTIF(G79:M79, "Not Recieved") -> 0 | D79: Call Attended | E79: Closed - Lost | G79: Client lost | I79: Client lost | K79: Call Recieved | M79: Client lost | N79: lost lead
A80: zahid ul haq | B80: 0333 3848819 | C80: =COUNTIF(G80:M80, "Not attempted") + COUNTIF(G80:M80, "Not Recieved") -> 1 | D80: Call Attended | E80: Demo | F80: 10:00 - 12:00 PM | G80: Call Recieved | H80: 12:00-02:30 | I80: Call Recieved | J80: 02:30-04:30 | K80: Call Recieved | L80: 04:30-06:00 | M80: Not Recieved | N80: enroll after Eid
A81: furqan khan | B81: 0347 8919020 | C81: =COUNTIF(G81:M81, "Not attempted") + COUNTIF(G81:M81, "Not Recieved") -> 1 | D81: Call Attended | E81: Closed - Lost | F81: 10:00 - 12:00 PM | G81: Client lost | H81: 12:00-02:30 | I81: Not Recieved | J81: 02:30-04:30 | K81: Client lost | L81: 04:30-06:00 | M81: Client lost | N81: not interested
A82: Sabeen Adil | B82: 0319 1572842 | C82: =COUNTIF(G82:M82, "Not attempted") + COUNTIF(G82:M82, "Not Recieved") -> 3 | D82: Call Attended | E82: Contacted | F82: 10:00 - 12:00 PM | G82: Not Recieved | H82: 12:00-02:30 | I82: Call Recieved | J82: 02:30-04:30 | K82: Not Recieved | L82: 04:30-06:00 | M82: Not Recieved | N82: no response
A83: Unknown | B83: 0345 2894906 | C83: =COUNTIF(G83:M83, "Not attempted") + COUNTIF(G83:M83, "Not Recieved") -> 1 | D83: Call Attended | E83: Closed - Lost | F83: 10:00 - 12:00 PM | G83: Call Recieved | H83: 12:00-02:30 | I83: Client lost | J83: 02:30-04:30 | K83: Client lost | L83: 04:30-06:00 | M83: Not Recieved | N83: lost lead
A84: Zareen Amir | B84: 0310 0015241 | C84: =COUNTIF(G84:M84, "Not attempted") + COUNTIF(G84:M84, "Not Recieved") -> 0 | D84: Call Attended | E84: Closed - Lost | F84: 10:00 - 12:00 PM | G84: Call Recieved | H84: 12:00-02:30 | I84: Client lost | J84: 02:30-04:30 | K84: Client lost | L84: 04:30-06:00 | M84: Client lost | N84: not interested
A85: Mohsin Shareef | B85: 0304 1212291 | C85: =COUNTIF(G85:M85, "Not attempted") + COUNTIF(G85:M85, "Not Recieved") -> 2 | D85: Call Attended | E85: Demo | F85: 10:00 - 12:00 PM | G85: Not Recieved | H85: 12:00-02:30 | I85: Not Recieved | J85: 02:30-04:30 | K85: Call Recieved | L85: 04:30-06:00 | M85: Call Recieved | N85: demo
B86: 92 344 8011296 | C86: =COUNTIF(G86:M86, "Not attempted") + COUNTIF(G86:M86, "Not Recieved") -> 1 | D86: Not Attended | E86: Closed - Lost | F86: 10:00 - 12:00 PM | G86: Not Recieved | H86: 12:00-02:30 | I86: Client lost | J86: 02:30-04:30 | K86: Client lost | L86: 04:30-06:00 | M86: Client lost | N86: lost lead
A87: Unknown | B87: 0319 0971562 | C87: =COUNTIF(G87:M87, "Not attempted") + COUNTIF(G87:M87, "Not Recieved") -> 1 | D87: Call Attended | E87: Closed - Lost | F87: 10:00 - 12:00 PM | G87: Client lost | H87: 12:00-02:30 | I87: Call Recieved | J87: 02:30-04:30 | K87: Client lost | L87: 04:30-06:00 | M87: Not Recieved | N87: lost lead
A88: Abdur Rehman | B88: 0332 7311117 | C88: =COUNTIF(G88:M88, "Not attempted") + COUNTIF(G88:M88, "Not Recieved") -> 3 | D88: Call Attended | E88: Closed - Lost | F88: 10:00 - 12:00 PM | G88: Call Recieved | H88: 12:00-02:30 | I88: Not Recieved | J88: 02:30-04:30 | K88: Not Recieved | L88: 04:30-06:00 | M88: Not Recieved | N88: lost lead
A89: Hareem | B89: 0313 2669898 | C89: =COUNTIF(G89:M89, "Not attempted") + COUNTIF(G89:M89, "Not Recieved") -> 3 | D89: Call Attended | E89: Closed - Lost | F89: 10:00 - 12:00 PM | G89: Call Recieved | H89: 12:00-02:30 | I89: Not Recieved | J89: 02:30-04:30 | K89: Not Recieved | L89: 04:30-06:00 | M89: Not Recieved | N89: lost lead
A90: Unknown | B90: 0300 4500486 | C90: =COUNTIF(G90:M90, "Not attempted") + COUNTIF(G90:M90, "Not Recieved") -> 2 | D90: Call Attended | E90: Contacted | F90: 10:00 - 12:00 PM | G90: Call Recieved | H90: 12:00-02:30 | I90: Not Recieved | J90: 02:30-04:30 | K90: Call Recieved | L90: 04:30-06:00 | M90: Not Recieved | N90: share info via whatsapp
A91: Unknown | B91: 0346 5587948 | C91: =COUNTIF(G91:M91, "Not attempted") + COUNTIF(G91:M91, "Not Recieved") -> 1 | D91: Call Attended | E91: Closed - Lost | F91: 10:00 - 12:00 PM | G91: Not Recieved | H91: 12:00-02:30 | I91: Call Recieved | J91: 02:30-04:30 | K91: Client lost | L91: 04:30-06:00 | M91: Client lost | N91: lost lead
A92: Asif Hanif | B92: 0314 2913388 | C92: =COUNTIF(G92:M92, "Not attempted") + COUNTIF(G92:M92, "Not Recieved") -> 2 | D92: Call Attended | E92: Closed - Lost | F92: 10:00 - 12:00 PM | G92: Call Recieved | H92: 12:00-02:30 | I92: Call Recieved | J92: 02:30-04:30 | K92: Not Recieved | L92: 04:30-06:00 | M92: Not attempted | N92: lost lead
A93: Unknown | B93: 0333 0940781 | C93: =COUNTIF(G93:M93, "Not attempted") + COUNTIF(G93:M93, "Not Recieved") -> 0 | D93: Call Attended | E93: Closed - Lost | F93: 10:00 - 12:00 PM | G93: Call Recieved | H93: 12:00-02:30 | I93: Client lost | J93: 02:30-04:30 | K93: Client lost | L93: 04:30-06:00 | M93: Client lost | N93: lost lead
A94: shahbaz | B94: 0333 8311986 | C94: =COUNTIF(G94:M94, "Not attempted") + COUNTIF(G94:M94, "Not Recieved") -> 1 | D94: Call Attended | E94: Closed - Won | F94: 10:00 - 12:00 PM | G94: Not Recieved | H94: 12:00-02:30 | I94: Call Recieved | J94: 02:30-04:30 | K94: Call Recieved | L94: 04:30-06:00 | M94: Call Recieved | N94: interested will inform | O94: inform by today
A95: Unknown | B95: 0300 4244211 | C95: =COUNTIF(G95:M95, "Not attempted") + COUNTIF(G95:M95, "Not Recieved") -> 1 | D95: Call Attended | E95: Closed - Lost | F95: 10:00 - 12:00 PM | G95: Call Recieved | H95: 12:00-02:30 | I95: Not Recieved | J95: 02:30-04:30 | K95: Call Recieved | L95: 04:30-06:00 | M95: Client lost | N95: lost lead
A96: Unknown | B96: 0333 2909262 | C96: =COUNTIF(G96:M96, "Not attempted") + COUNTIF(G96:M96, "Not Recieved") -> 3 | D96: Call Attended | E96: Closed - Lost | F96: 10:00 - 12:00 PM | G96: Not Recieved | H96: 12:00-02:30 | I96: Not Recieved | J96: 02:30-04:30 | K96: Call Recieved | L96: 04:30-06:00 | M96: Not attempted | N96: lost lead
A97: Bushra | B97: 0316 8325012 | C97: =COUNTIF(G97:M97, "Not attempted") + COUNTIF(G97:M97, "Not Recieved") -> 0 | D97: Call Attended | E97: Closed - Lost | F97: 10:00 - 12:00 PM | G97: Call Recieved | H97: 12:00-02:30 | I97: Call Recieved | J97: 02:30-04:30 | K97: Call Recieved | L97: 04:30-06:00 | M97: Call Recieved | N97: lost lead
A98: Unknown | B98: 0349 0721618 | C98: =COUNTIF(G98:M98, "Not attempted") + COUNTIF(G98:M98, "Not Recieved") -> 3 | D98: Call Attended | E98: Demo | F98: 10:00 - 12:00 PM | G98: Call Recieved | H98: 12:00-02:30 | I98: Not Recieved | J98: 02:30-04:30 | K98: Not Recieved | L98: 04:30-06:00 | M98: Not Recieved | N98: add him in demo
A99: Unknown-2 | B99: 0304 9432400 | C99: =COUNTIF(G99:M99, "Not attempted") + COUNTIF(G99:M99, "Not Recieved") -> 4 | D99: Not Attended | E99: Call not Recieved | F99: 10:00 - 12:00 PM | G99: Not Recieved | H99: 12:00-02:30 | I99: Not Recieved | J99: 02:30-04:30 | K99: Not Recieved | L99: 04:30-06:00 | M99: Not Recieved | N99: no response
B100: 0320 3600513 | C100: =COUNTIF(G100:M100, "Not attempted") + COUNTIF(G100:M100, "Not Recieved") -> 1 | D100: Call Attended | E100: Demo | F100: 10:00 - 12:00 PM | G100: Not attempted | H100: 12:00-02:30 | I100: Call Recieved | J100: 02:30-04:30 | K100: Please Call later | L100: 04:30-06:00 | M100: Call Recieved | N100: intersted
A101: Unknown-3 | B101: 0346 4229873 | C101: =COUNTIF(G101:M101, "Not attempted") + COUNTIF(G101:M101, "Not Recieved") -> 4 | D101: Not Attended | E101: Call not Recieved | F101: 10:00 - 12:00 PM | G101: Not Recieved | H101: 12:00-02:30 | I101: Not Recieved | J101: 02:30-04:30 | K101: Not Recieved | L101: 04:30-06:00 | M101: Not Recieved | N101: no response
...

Sheet 2
A1: Prospect Name | B1: Number | C1: Attempts Missing | D1: Status | E1: stage | F1: Call Slot 1 | G1: Attempt 1 | H1: Call Slot 2 | I1: Attempt 2 | J1: Call Slot 3 | K1: Attempt-3 | L1: Call Slot 4 | M1: Attempt-4 | N1: Lead Type | O1: Notes | P1: Next Step | Q1: date
B2: 92 331 8293629 | C2: =COUNTIF(G2:M2, "Not attempted") -> 0 | D2: Call Attended | E2: Closed - Lost | F2: 10:00 - 12:00 PM | G2: Client lost | H2: 12:00-02:30 | I2: Client lost | J2: 02:30-04:30 | K2: Client lost | L2: 04:30-06:00 | M2: Client lost | O2: busy, already enrolled in any other course | Q2: 14-5-2025
B3: 92 342 1691429 | C3: =COUNTIF(G3:M3, "Not attempted") -> 0 | D3: Call Attended | E3: Closed - Lost | F3: 10:00 - 12:00 PM | G3: Client lost | H3: 12:00-02:30 | I3: Client lost | J3: 02:30-04:30 | K3: Client lost | L3: 04:30-06:00 | M3: Client lost | O3: not interested. | Q3: 14-5-2025
B4: 92 340 8913963 | C4: =COUNTIF(G4:M4, "Not attempted") -> 0 | D4: Not Attended | E4: Closed - Lost | F4: 10:00 - 12:00 PM | G4: Client lost | H4: 12:00-02:30 | I4: Client lost | J4: 02:30-04:30 | K4: Client lost | L4: 04:30-06:00 | M4: Client lost | O4: cannot afford the course. | Q4: 14-5-2025
B5: 92 304 7107981 | C5: =COUNTIF(G5:M5, "Not attempted") -> 0 | D5: Not Attended | E5: Call not Recieved | F5: 10:00 - 12:00 PM | G5: Not Recieved | H5: 12:00-02:30 | I5: Not Recieved | J5: 02:30-04:30 | K5: Not Recieved | L5: 04:30-06:00 | M5: Not Recieved | O5: no response | Q5: 14-5-2025
B6: 92 311 2410698 | C6: =COUNTIF(G6:M6, "Not attempted") -> 0 | D6: Not Attended | E6: Call not Recieved | F6: 10:00 - 12:00 PM | G6: Not Recieved | H6: 12:00-02:30 | I6: Not Recieved | J6: 02:30-04:30 | K6: Not Recieved | L6: 04:30-06:00 | M6: Not Recieved | O6: no response | Q6: 14-5-2025
B7: 92 347 7491762 | C7: =COUNTIF(G7:M7, "Not attempted") -> 1 | D7: Call Attended | E7: enroll in next batch | F7: 10:00 - 12:00 PM | G7: Call Recieved | H7: 12:00-02:30 | I7: Client lost | J7: 02:30-04:30 | K7: Not attempted | L7: 04:30-06:00 | M7: Client lost | O7: busy now. enroll in next batch. | Q7: 14-5-2025
B8: 92 316 1615889 | C8: =COUNTIF(G8:M8, "Not attempted") -> 0 | D8: Call Attended | E8: Closed - Lost | F8: 10:00 - 12:00 PM | G8: Client lost | H8: 12:00-02:30 | I8: Client lost | J8: 02:30-04:30 | K8: Client lost | L8: 04:30-06:00 | M8: Client lost | O8: currently enrolled in marketing course. will join next batch | Q8: 14-5-2025
B9: 92 301 7920441 | C9: =COUNTIF(G9:M9, "Not attempted") -> 0 | D9: Call Attended | E9: Closed - Lost | F9: 10:00 - 12:00 PM | G9: Client lost | H9: 12:00-02:30 | I9: Client lost | J9: 02:30-04:30 | K9: Client lost | L9: 04:30-06:00 | M9: Client lost | O9: not interested, he is interested in onsite classes | Q9: 14-5-2025
B10: 92 334 7777851 | C10: =COUNTIF(G10:M10, "Not attempted") -> 0 | D10: Not Attended | E10: Call not Recieved | F10: 10:00 - 12:00 PM | G10: Not Recieved | H10: 12:00-02:30 | I10: Not Recieved | J10: 02:30-04:30 | K10: Not Recieved | L10: 04:30-06:00 | M10: Not Recieved | O10: no response | Q10: 14-5-2025
B11: 92 334 4377598 | C11: =COUNTIF(G11:M11, "Not attempted") -> 4 | D11: Call Attended | E11: Closed - Won | F11: 10:00 - 12:00 PM | G11: Not attempted | H11: 12:00-02:30 | I11: Not attempted | J11: 02:30-04:30 | K11: Not attempted | L11: 04:30-06:00 | M11: Not attempted | N11: qualified | O11: paid | Q11: 14-5-2025
B12: 92 312 3593749 | C12: =COUNTIF(G12:M12, "Not attempted") -> 0 | D12: Call Attended | E12: Closed - Lost | F12: 10:00 - 12:00 PM | G12: Client lost | H12: 12:00-02:30 | I12: Client lost | J12: 02:30-04:30 | K12: Client lost | L12: 04:30-06:00 | M12: Client lost | O12: her son doesn't allow her for the course | Q12: 14-5-2025
B13: 92 323 7001233 | C13: =COUNTIF(G13:M13, "Not attempted") -> 0 | D13: Not Attended | E13: Call not Recieved | F13: 10:00 - 12:00 PM | G13: Not Recieved | H13: 12:00-02:30 | I13: Not Recieved | J13: 02:30-04:30 | K13: Not Recieved | L13: 04:30-06:00 | M13: Not Recieved | O13: no response | Q13: 14-5-2025
B14: 92 303 4523810 | C14: =COUNTIF(G14:M14, "Not attempted") -> 0 | D14: Call Attended | E14: Closed - Lost | F14: 10:00 - 12:00 PM | G14: Client lost | H14: 12:00-02:30 | I14: Client lost | J14: 02:30-04:30 | K14: Client lost | L14: 04:30-06:00 | M14: Client lost | O14: cannot afford the course. | Q14: 14-5-2025
B15: 92 326 9507624 | C15: =COUNTIF(G15:M15, "Not attempted") -> 0 | D15: Not Attended | E15: Closed - Lost | F15: 10:00 - 12:00 PM | G15: Client lost | H15: 12:00-02:30 | I15: Client lost | J15: 02:30-04:30 | K15: Client lost | L15: 04:30-06:00 | M15: Client lost | O15: not interested, he is interested in onsite classes | Q15: 14-5-2025
B16: 92 341 8194127 | C16: =COUNTIF(G16:M16, "Not attempted") -> 0 | D16: Call Attended | E16: Contacted | F16: 10:00 - 12:00 PM | G16: Not Recieved | H16: 12:00-02:30 | I16: Please Call later | J16: 02:30-04:30 | K16: Not Recieved | L16: 04:30-06:00 | M16: Not Recieved | O16: awaiting response/ not reachable. | Q16: 14-5-2025
B17: 92 335 3483018 | C17: =COUNTIF(G17:M17, "Not attempted") -> 0 | D17: Not Attended | E17: Call not Recieved | F17: 10:00 - 12:00 PM | G17: Not Recieved | H17: 12:00-02:30 | I17: Not Recieved | J17: 02:30-04:30 | K17: Not Recieved | L17: 04:30-06:00 | M17: Not Recieved | O17: no response | Q17: 14-5-2025
B18: 92 320 7448330 | C18: =COUNTIF(G18:M18, "Not attempted") -> 0 | D18: Not Attended | E18: Call not Recieved | F18: 10:00 - 12:00 PM | G18: Not Recieved | H18: 12:00-02:30 | I18: Not Recieved | J18: 02:30-04:30 | K18: Not Recieved | L18: 04:30-06:00 | M18: Not Recieved | O18: no response | Q18: 14-5-2025
B19: 92 355 4741513 | C19: =COUNTIF(G19:M19, "Not attempted") -> 0 | D19: Not Attended | E19: Call not Recieved | F19: 10:00 - 12:00 PM | G19: Not Recieved | H19: 12:00-02:30 | I19: Not Recieved | J19: 02:30-04:30 | K19: Not Recieved | L19: 04:30-06:00 | M19: Not Recieved | O19: no response | Q19: 14-5-2025
B20: 92 335 0045016 | C20: =COUNTIF(G20:M20, "Not attempted") -> 1 | D20: Call Attended | E20: Closed - Lost | F20: 10:00 - 12:00 PM | G20: Not Recieved | H20: 12:00-02:30 | I20: Not Recieved | J20: 02:30-04:30 | K20: Call Recieved | L20: 04:30-06:00 | M20: Not attempted | N20: qualified | O20: cannot possible because of her personal issues. | Q20: 14-5-2025
B21: 92 347 8264716 | C21: =COUNTIF(G21:M21, "Not attempted") -> 0 | D21: Not Attended | E21: Call not Recieved | F21: 10:00 - 12:00 PM | G21: Not Recieved | H21: 12:00-02:30 | I21: Not Recieved | J21: 02:30-04:30 | K21: Not Recieved | L21: 04:30-06:00 | M21: Not Recieved | O21: no response | Q21: 14-5-2025
B22: 92 315 8057419 | C22: =COUNTIF(G22:M22, "Not attempted") -> 0 | D22: Call Attended | E22: Closed - Lost | F22: 10:00 - 12:00 PM | G22: Client lost | H22: 12:00-02:30 | I22: Client lost | J22: 02:30-04:30 | K22: Client lost | L22: 04:30-06:00 | M22: Client lost | O22: He's in a school, he doesn't have a pc or laptop | Q22: 14-5-2025
B23: 92 312 3593749 | C23: =COUNTIF(G23:M23, "Not attempted") -> 0 | D23: Not Attended | E23: Closed - Lost | F23: 10:00 - 12:00 PM | G23: Client lost | H23: 12:00-02:30 | I23: Client lost | J23: 02:30-04:30 | K23: Client lost | L23: 04:30-06:00 | M23: Client lost | O23: not interested. busy in studies | Q23: 14-5-2025
B24: 92 303 9578152 | C24: =COUNTIF(G24:M24, "Not attempted") -> 0 | D24: Not Attended | E24: Contacted | F24: 10:00 - 12:00 PM | G24: Not Recieved | H24: 12:00-02:30 | I24: Call Recieved | J24: 02:30-04:30 | K24: Not Recieved | L24: 04:30-06:00 | M24: Not Recieved | O24: awaiting response/ not reachable.cut the call immediately | Q24: 15-5-2025
B25: 92 304 2846019 | C25: =COUNTIF(G25:M25, "Not attempted") -> 0 | D25: Not Attended | E25: Closed - Lost | F25: 10:00 - 12:00 PM | G25: Client lost | H25: 12:00-02:30 | I25: Client lost | J25: 02:30-04:30 | K25: Client lost | L25: 04:30-06:00 | M25: Client lost | O25: he said internet problem | Q25: 15-5-2025
B26: 92 325 2899329 | C26: =COUNTIF(G26:M26, "Not attempted") -> 0 | D26: Call Attended | E26: Closed - Lost | F26: 10:00 - 12:00 PM | G26: Client lost | H26: 12:00-02:30 | I26: Client lost | J26: 02:30-04:30 | K26: Client lost | L26: 04:30-06:00 | M26: Client lost | O26: awaiting response/ not reachable. | Q26: 15-5-2025
B27: 92 342 4969217 | C27: =COUNTIF(G27:M27, "Not attempted") -> 0 | D27: Not Attended | E27: Closed - Lost | F27: 10:00 - 12:00 PM | G27: Client lost | H27: 12:00-02:30 | I27: Client lost | J27: 02:30-04:30 | K27: Client lost | L27: 04:30-06:00 | M27: Client lost | O27: not interested. | Q27: 15-5-2025
B28: 92 334 7879077 | C28: =COUNTIF(G28:M28, "Not attempted") -> 0 | D28: Call Attended | E28: Contacted | F28: 10:00 - 12:00 PM | G28: Call Recieved | H28: 12:00-02:30 | I28: Call Recieved | J28: 02:30-04:30 | K28: Not Recieved | L28: 04:30-06:00 | M28: Not Recieved | N28: qualified | O28: interested, will call him back at 6pm 17th may. call not receive. | Q28: 15-5-2025
B29: 92 307 0148989 | C29: =COUNTIF(G29:M29, "Not attempted") -> 0 | D29: Not Attended | E29: Closed - Lost | F29: 10:00 - 12:00 PM | G29: Client lost | H29: 12:00-02:30 | I29: Client lost | J29: 02:30-04:30 | K29: Client lost | L29: 04:30-06:00 | M29: Client lost | O29: physical classes | Q29: 15-5-2025
B30: 92 348 2900659 | C30: =COUNTIF(G30:M30, "Not attempted") -> 0 | D30: Call Attended | E30: Closed - Lost | F30: 10:00 - 12:00 PM | G30: Client lost | H30: 12:00-02:30 | I30: Client lost | J30: 02:30-04:30 | K30: Client lost | L30: 04:30-06:00 | M30: Client lost | O30: not interested in data science | Q30: 15-5-2025
B31: 92 313 2894151 | C31: =COUNTIF(G31:M31, "Not attempted") -> 1 | D31: Call Attended | E31: Awaiting Response | F31: 10:00 - 12:00 PM | G31: Call Recieved | H31: 12:00-02:30 | I31: Call Recieved | J31: 02:30-04:30 | K31: Not attempted | L31: 04:30-06:00 | M31: Not Recieved | O31: interested, will call him back at 5pm 19th may. not reachable | Q31: 15-5-2025
B32: 92 334 8668349 | C32: =COUNTIF(G32:M32, "Not attempted") -> 0 | D32: Call Attended | E32: Closed - Lost | F32: 10:00 - 12:00 PM | G32: Client lost | H32: 12:00-02:30 | I32: Client lost | J32: 02:30-04:30 | K32: Client lost | L32: 04:30-06:00 | M32: Client lost | N32: qualified | O32: She didn't get the permission. | Q32: 15-5-2025
B33: 92 315 5734149 | C33: =COUNTIF(G33:M33, "Not attempted") -> 0 | D33: Not Attended | E33: Contacted | F33: 10:00 - 12:00 PM | G33: Not Recieved | H33: 12:00-02:30 | I33: Call Recieved | J33: 02:30-04:30 | K33: Not Recieved | L33: 04:30-06:00 | M33: Not Recieved | O33: awaiting response/ not reachable. | Q33: 15-5-2025
B34: 92 315 4507252 | C34: =COUNTIF(G34:M34, "Not attempted") -> 0 | D34: Call Attended | E34: Closed - Lost | F34: 10:00 - 12:00 PM | G34: Client lost | H34: 12:00-02:30 | I34: Client lost | J34: 02:30-04:30 | K34: Client lost | L34: 04:30-06:00 | M34: Client lost | O34: not interested. | Q34: 15-5-2025
B35: 92 319 7682037 | C35: =COUNTIF(G35:M35, "Not attempted") -> 0 | D35: Call Attended | E35: Contacted | F35: 10:00 - 12:00 PM | G35: Not Recieved | H35: 12:00-02:30 | I35: Call Recieved | J35: 02:30-04:30 | K35: Not Recieved | L35: 04:30-06:00 | M35: Not Recieved | O35: She is filling out the form./ not reachable. | Q35: 15-5-2025
B36: 92 301 0909651 | C36: =COUNTIF(G36:M36, "Not attempted") -> 0 | D36: Call Attended | E36: Closed - Lost | F36: 10:00 - 12:00 PM | G36: Client lost | H36: 12:00-02:30 | I36: Client lost | J36: 02:30-04:30 | K36: Client lost | L36: 04:30-06:00 | M36: Client lost | O36: not interested, he is interested in onsite classes | Q36: 15-5-2025
B37: 92 318 1050520 | C37: =COUNTIF(G37:M37, "Not attempted") -> 1 | D37: Not Attended | E37: Awaiting payment | F37: 10:00 - 12:00 PM | G37: Call Recieved | H37: 12:00-02:30 | I37: Not Recieved | J37: 02:30-04:30 | K37: Not Recieved | L37: 04:30-06:00 | M37: Not attempted | O37: waiting for the payment / not reachable | Q37: 15-5-2025
B38: 92 313 2076659 | C38: =COUNTIF(G38:M38, "Not attempted") -> 0 | D38: Call Attended | E38: Awaiting Response | F38: 10:00 - 12:00 PM | G38: Not Recieved | H38: 12:00-02:30 | I38: Call Recieved | J38: 02:30-04:30 | K38: Call Recieved | L38: 04:30-06:00 | M38: Not Recieved | N38: qualified | O38: interested, she will come office. will call her back on 27 may. | Q38: 15-5-2025
B39: 92 348 8561743 | C39: =COUNTIF(G39:M39, "Not attempted") -> 0 | D39: Not Attended | E39: Call not Recieved | F39: 10:00 - 12:00 PM | G39: Not Recieved | H39: 12:00-02:30 | I39: Not Recieved | J39: 02:30-04:30 | K39: Not Recieved | L39: 04:30-06:00 | M39: Not Recieved | O39: no response | Q39: 15-5-2025
B40: 92 333 5758174 | C40: =COUNTIF(G40:M40, "Not attempted") -> 0 | D40: Call Attended | E40: Closed - Lost | F40: 10:00 - 12:00 PM | G40: Client lost | H40: 12:00-02:30 | I40: Client lost | J40: 02:30-04:30 | K40: Client lost | L40: 04:30-06:00 | M40: Client lost | N40: qualified | O40: not interested. | Q40: 15-5-2025
B41: 92 342 3507517 | C41: =COUNTIF(G41:M41, "Not attempted") -> 0 | D41: Not Attended | E41: Call not Recieved | F41: 10:00 - 12:00 PM | G41: Not Recieved | H41: 12:00-02:30 | I41: Not Recieved | J41: 02:30-04:30 | K41: Not Recieved | L41: 04:30-06:00 | M41: Not Recieved | O41: no response | Q41: 15-5-2025
B42: 92 317 3704910 | C42: =COUNTIF(G42:M42, "Not attempted") -> 0 | D42: Not Attended | E42: Call not Recieved | F42: 10:00 - 12:00 PM | G42: Not Recieved | H42: 12:00-02:30 | I42: Not Recieved | J42: 02:30-04:30 | K42: Not Recieved | L42: 04:30-06:00 | M42: Not Recieved | O42: no response | Q42: 15-5-2025
B43: 92 355 4759505 | C43: =COUNTIF(G43:M43, "Not attempted") -> 0 | D43: Call Attended | E43: Closed - Lost | F43: 10:00 - 12:00 PM | G43: Client lost | H43: 12:00-02:30 | I43: Client lost | J43: 02:30-04:30 | K43: Client lost | L43: 04:30-06:00 | M43: Client lost | O43: not interested | Q43: 15-5-2025
B44: 92 319 0345400 | C44: =COUNTIF(G44:M44, "Not attempted") -> 0 | D44: Not Attended | E44: Closed - Lost | F44: 10:00 - 12:00 PM | G44: Client lost | H44: 12:00-02:30 | I44: Client lost | J44: 02:30-04:30 | K44: Client lost | L44: 04:30-06:00 | M44: Client lost | O44: not interested. | Q44: 15-5-2025
B45: 92 355 4213453 | C45: =COUNTIF(G45:M45, "Not attempted") -> 0 | D45: Not Attended | E45: Call not Recieved | F45: 10:00 - 12:00 PM | G45: Not Recieved | H45: 12:00-02:30 | I45: Not Recieved | J45: 02:30-04:30 | K45: Not Recieved | L45: 04:30-06:00 | M45: Not Recieved | O45: no response | Q45: 15-5-2025
B46: 92 321 8760538 | C46: =COUNTIF(G46:M46, "Not attempted") -> 0 | D46: Call Attended | E46: Closed - Lost | F46: 10:00 - 12:00 PM | G46: Client lost | H46: 12:00-02:30 | I46: Client lost | J46: 02:30-04:30 | K46: Client lost | L46: 04:30-06:00 | M46: Client lost | O46: not interested. high fees, don't have time and teacher isn't mature. | Q46: 16-5-2025
B47: 92 320 3624471 | C47: =COUNTIF(G47:M47, "Not attempted") -> 0 | D47: Not Attended | E47: Closed - Lost | F47: 10:00 - 12:00 PM | G47: Client lost | H47: 12:00-02:30 | I47: Client lost | J47: 02:30-04:30 | K47: Client lost | L47: 04:30-06:00 | M47: Client lost | O47: not interested. | Q47: 16-5-2025
B48: 92 327 3017621 | C48: =COUNTIF(G48:M48, "Not attempted") -> 0 | D48: Not Attended | E48: Closed - Lost | F48: 10:00 - 12:00 PM | G48: Client lost | H48: 12:00-02:30 | I48: Client lost | J48: 02:30-04:30 | K48: Client lost | L48: 04:30-06:00 | M48: Client lost | O48: cannot afford the course. | Q48: 16-5-2025
B49: 92 337 9852670 | C49: =COUNTIF(G49:M49, "Not attempted") -> 0 | D49: Not Attended | E49: Call not Recieved | F49: 10:00 - 12:00 PM | G49: Not Recieved | H49: 12:00-02:30 | I49: Not Recieved | J49: 02:30-04:30 | K49: Not Recieved | L49: 04:30-06:00 | M49: Not Recieved | O49: no response | Q49: 16-5-2025
B50: 92 321 2318355 | C50: =COUNTIF(G50:M50, "Not attempted") -> 0 | D50: Not Attended | E50: Call not Recieved | F50: 10:00 - 12:00 PM | G50: Not Recieved | H50: 12:00-02:30 | I50: Not Recieved | J50: 02:30-04:30 | K50: Not Recieved | L50: 04:30-06:00 | M50: Not Recieved | O50: no response | Q50: 16-5-2025
B51: 92 355 5680328 | C51: =COUNTIF(G51:M51, "Not attempted") -> 0 | D51: Not Attended | E51: Call not Recieved | F51: 10:00 - 12:00 PM | G51: Not Recieved | H51: 12:00-02:30 | I51: Not Recieved | J51: 02:30-04:30 | K51: Not Recieved | L51: 04:30-06:00 | M51: Not Recieved | O51: no response | Q51: 16-5-2025
B52: 92 316 3764776 | C52: =COUNTIF(G52:M52, "Not attempted") -> 3 | D52: Call Attended | E52: enroll in next batch | F52: 10:00 - 12:00 PM | G52: Not attempted | H52: 12:00-02:30 | I52: Call Recieved | J52: 02:30-04:30 | K52: Not attempted | L52: 04:30-06:00 | M52: Not attempted | O52: next batch | Q52: 16-5-2025
... B56: 92 342 5505617 | C56: =COUNTIF(G56:M56, "Not attempted") -> 0 | D56: Not Attended | E56: Closed - Lost | F56: 10:00 - 12:00 PM | G56: Client lost | H56: 12:00-02:30 | I56: Client lost | J56: 02:30-04:30 | K56: Client lost | L56: 04:30-06:00 | M56: Client lost | O56: cannot join course because of light issue. | Q56: 16-5-2025
B57: 255 778 480 942 | C57: =COUNTIF(G57:M57, "Not attempted") -> 4 | E57: Closed - Won | F57: 10:00 - 12:00 PM | G57: Not attempted | H57: 12:00-02:30 | I57: Not attempted | J57: 02:30-04:30 | K57: Not attempted | L57: 04:30-06:00 | M57: Not attempted | Q57: 16-5-2025
B58: 92 324 5102557 | C58: =COUNTIF(G58:M58, "Not attempted") -> 0 | D58: Not Attended | E58: Contacted | F58: 10:00 - 12:00 PM | G58: Not Recieved | H58: 12:00-02:30 | I58: Not Recieved | J58: 02:30-04:30 | K58: Not Recieved | L58: 04:30-06:00 | M58: Call Recieved | O58: he will get back to me after see the details. / not reachable. | Q58: 16-5-2025
B59: 92 326 8722716 | C59: =COUNTIF(G59:M59, "Not attempted") -> 0 | D59: Call Attended | E59: Closed - Lost | F59: 10:00 - 12:00 PM | G59: Client lost | H59: 12:00-02:30 | I59: Client lost | J59: 02:30-04:30 | K59: Client lost | L59: 04:30-06:00 | M59: Client lost | O59: fees is too high. can pay only 1k | Q59: 16-5-2025
B60: 92 322 1261822 | C60: =COUNTIF(G60:M60, "Not attempted") -> 2 | D60: Call Attended | E60: enroll in next batch | F60: 10:00 - 12:00 PM | G60: Not Recieved | H60: 12:00-02:30 | I60: Not attempted | J60: 02:30-04:30 | K60: Call Recieved | L60: 04:30-06:00 | M60: Not attempted | N60: qualified | O60: Already enroll in ebay course. Will join us in next batch | Q60: 16-5-2025
B61: 92 310 3713633 | C61: =COUNTIF(G61:M61, "Not attempted") -> 0 | D61: Not Attended | E61: Contacted | F61: 10:00 - 12:00 PM | G61: Not Recieved | H61: 12:00-02:30 | I61: Not Recieved | J61: 02:30-04:30 | K61: Not Recieved | L61: 04:30-06:00 | M61: Call Recieved | N61: qualified | O61: Interested. not reachable. | Q61: 16-5-2025
B62: 92 305 3480035 | C62: =COUNTIF(G62:M62, "Not attempted") -> 0 | D62: Call Attended | E62: Closed - Lost | F62: 10:00 - 12:00 PM | G62: Client lost | H62: 12:00-02:30 | I62: Client lost | J62: 02:30-04:30 | K62: Client lost | L62: 04:30-06:00 | M62: Client lost | O62: He can pay only 1000 month/ cannot pay any money now | Q62: 16-5-2025
B63: 92 317 7099581 | C63: =COUNTIF(G63:M63, "Not attempted") -> 0 | D63: Call Attended | E63: Closed - Lost | F63: 10:00 - 12:00 PM | G63: Client lost | H63: 12:00-02:30 | I63: Client lost | J63: 02:30-04:30 | K63: Client lost | L63: 04:30-06:00 | M63: Client lost | O63: cannot afford the fees. | Q63: 16-5-2025
B64: 92 315 8025203 | C64: =COUNTIF(G64:M64, "Not attempted") -> 0 | D64: Not Attended | E64: Closed - Lost | F64: 10:00 - 12:00 PM | G64: Client lost | H64: 12:00-02:30 | I64: Client lost | J64: 02:30-04:30 | K64: Client lost | L64: 04:30-06:00 | M64: Client lost | O64: doesn't have pc or laptop | Q64: 16-5-2025
B65: 92 315 2799560 | C65: =COUNTIF(G65:M65, "Not attempted") -> 0 | D65: Not Attended | E65: Contacted | F65: 10:00 - 12:00 PM | G65: Call Recieved | H65: 12:00-02:30 | I65: Not Recieved | J65: 02:30-04:30 | K65: Not Recieved | L65: 04:30-06:00 | M65: Not Recieved | O65: will confirm me soon / not reachable | Q65: 16-5-2025
B66: 92 301 7185377 | C66: =COUNTIF(G66:M66, "Not attempted") -> 0 | D66: Call Attended | E66: Closed - Lost | F66: 10:00 - 12:00 PM | G66: Client lost | H66: 12:00-02:30 | I66: Client lost | J66: 02:30-04:30 | K66: Client lost | L66: 04:30-06:00 | M66: Client lost | O66: not interested for data sceince, only interested for marketing internship | Q66: 16-5-2025
B67: 92 370 1500487 | C67: =COUNTIF(G67:M67, "Not attempted") -> 0 | D67: Not Attended | E67: Call not Recieved | F67: 10:00 - 12:00 PM | G67: Not Recieved | H67: 12:00-02:30 | I67: Not Recieved | J67: 02:30-04:30 | K67: Not Recieved | L67: 04:30-06:00 | M67: Not Recieved | O67: no response | Q67: 16-5-2025
A68: zia | B68: 92 303 4328334 | C68: =COUNTIF(G68:M68, "Not attempted") -> 0 | D68: Call Attended | E68: Closed - Won | F68: 10:00 - 12:00 PM | G68: Client lost | H68: 12:00-02:30 | I68: Client lost | J68: 02:30-04:30 | K68: Client lost | L68: 04:30-06:00 | M68: Client lost | O68: demo shared | Q68: 16-5-2025
B69: 92 324 3608510 | C69: =COUNTIF(G69:M69, "Not attempted") -> 1 | D69: Not Attended | E69: enroll in next batch | F69: 10:00 - 12:00 PM | G69: Client lost | H69: 12:00-02:30 | I69: Client lost | J69: 02:30-04:30 | K69: Not attempted | L69: 04:30-06:00 | M69: Client lost | O69: cannot join classes due to internet problem. will join nect batch. | Q69: 16-5-2025
B70: 92 302 6696737 | C70: =COUNTIF(G70:M70, "Not attempted") -> 0 | D70: Call Attended | E70: Closed - Lost | F70: 10:00 - 12:00 PM | G70: Client lost | H70: 12:00-02:30 | I70: Client lost | J70: 02:30-04:30 | K70: Client lost | L70: 04:30-06:00 | M70: Client lost | O70: not interested | Q70: 16-5-2025
B71: 92 311 1812318 | C71: =COUNTIF(G71:M71, "Not attempted") -> 0 | D71: Not Attended | E71: Closed - Lost | F71: 10:00 - 12:00 PM | G71: Client lost | H71: 12:00-02:30 | I71: Client lost | J71: 02:30-04:30 | K71: Client lost | L71: 04:30-06:00 | M71: Client lost | O71: not interested. | Q71: 16-5-2025
A72: Abdullah Azim | B72: 92 333 2702549 | C72: =COUNTIF(G72:M72, "Not attempted") -> 1 | D72: Call Attended | E72: Awaiting payment | F72: 10:00 - 12:00 PM | G72: Not Recieved | H72: 12:00-02:30 | I72: Call Recieved | J72: 02:30-04:30 | K72: Call Recieved | L72: 04:30-06:00 | M72: Not attempted | O72: form filled, / waiting for fees | Q72: 16-5-2025
B73: 92 323 0766491 | C73: =COUNTIF(G73:M73, "Not attempted") -> 3 | D73: Call Attended | E73: enroll in next batch | F73: 10:00 - 12:00 PM | G73: Not attempted | H73: 12:00-02:30 | I73: Call Recieved | J73: 02:30-04:30 | K73: Not attempted | L73: 04:30-06:00 | M73: Not attempted | O73: she already have knowledge of this course, she will enroll her self after 3 month | Q73: 16-5-2025
B74: 92 336 8027056 | C74: =COUNTIF(G74:M74, "Not attempted") -> 0 | D74: Call Attended | E74: enroll in next batch | F74: 10:00 - 12:00 PM | G74: Call Recieved | H74: 12:00-02:30 | I74: Not Recieved | J74: 02:30-04:30 | K74: Not Recieved | L74: 04:30-06:00 | M74: Call Recieved | O74: going on vacations. | Q74: 16-5-2025
B75: 92 310 8501861 | C75: =COUNTIF(G75:M75, "Not attempted") -> 0 | D75: Not Attended | E75: Closed - Lost | F75: 10:00 - 12:00 PM | G75: Client lost | H75: 12:00-02:30 | I75: Client lost | J75: 02:30-04:30 | K75: Client lost | L75: 04:30-06:00 | M75: Client lost | O75: not interested. | Q75: 17-5-2025
B76: 92 346 4503377 | C76: =COUNTIF(G76:M76, "Not attempted") -> 0 | D76: Not Attended | E76: Call not Recieved | F76: 10:00 - 12:00 PM | G76: Not Recieved | H76: 12:00-02:30 | I76: Not Recieved | J76: 02:30-04:30 | K76: Not Recieved | L76: 04:30-06:00 | M76: Not Recieved | O76: no response | Q76: 17-5-2025
B77: 92 332 8220634 | C77: =COUNTIF(G77:M77, "Not attempted") -> 1 | D77: Call Attended | E77: Awaiting Response | F77: 10:00 - 12:00 PM | G77: Call Recieved | H77: 12:00-02:30 | I77: Call Recieved | J77: 02:30-04:30 | K77: Not attempted | L77: 04:30-06:00 | M77: Call Recieved | O77: he'll confirm me by 26th may evening / in a meeting. | Q77: 17-5-2025
B78: 92 324 3549119 | C78: =COUNTIF(G78:M78, "Not attempted") -> 0 | D78: Call Attended | E78: Contacted | F78: 10:00 - 12:00 PM | G78: Not Recieved | H78: 12:00-02:30 | I78: Call Recieved | J78: 02:30-04:30 | K78: Not Recieved | L78: 04:30-06:00 | M78: Call Recieved | N78: non qualified | O78: awaiting response / not reachable | Q78: 17-5-2025
B79: 92 329 6197751 | C79: =COUNTIF(G79:M79, "Not attempted") -> 0 | D79: Call Attended | E79: Contacted | F79: 10:00 - 12:00 PM | G79: Not Recieved | H79: 12:00-02:30 | I79: Call Recieved | J79: 02:30-04:30 | K79: Call Recieved | L79: 04:30-06:00 | M79: Call Recieved | N79: non qualified | O79: awaiting response / not reachable | Q79: 17-5-2025
B80: 92 314 1929179 | C80: =COUNTIF(G80:M80, "Not attempted") -> 0 | D80: Not Attended | E80: Closed - Lost | F80: 10:00 - 12:00 PM | G80: Client lost | H80: 12:00-02:30 | I80: Client lost | J80: 02:30-04:30 | K80: Client lost | L80: 04:30-06:00 | M80: Client lost | N80: non qualified | O80: not interested. | Q80: 17-5-2025
B81: 92 325 5402881 | C81: =COUNTIF(G81:M81, "Not attempted") -> 0 | D81: Call Attended | E81: Closed - Lost | F81: 10:00 - 12:00 PM | G81: Client lost | H81: 12:00-02:30 | I81: Client lost | J81: 02:30-04:30 | K81: Client lost | L81: 04:30-06:00 | M81: Client lost | N81: non qualified | O81: busy in studies. | Q81: 17-5-2025
B82: 92 334 1243831 | C82: =COUNTIF(G82:M82, "Not attempted") -> 0 | D82: Not Attended | E82: Call not Recieved | F82: 10:00 - 12:00 PM | G82: Not Recieved | H82: 12:00-02:30 | I82: Not Recieved | J82: 02:30-04:30 | K82: Not Recieved | L82: 04:30-06:00 | M82: Not Recieved | N82: non qualified | O82: no response | Q82: 17-5-2025
B83: 92 313 4502853 | C83: =COUNTIF(G83:M83, "Not attempted") -> 0 | D83: Not Attended | E83: Closed - Lost | F83: 10:00 - 12:00 PM | G83: Client lost | H83: 12:00-02:30 | I83: Client lost | J83: 02:30-04:30 | K83: Client lost | L83: 04:30-06:00 | M83: Client lost | N83: qualified | O83: he got offer from another institute, 7k fees and paid internship | Q83: 17-5-2025
B84: 92 332 4765750 | C84: =COUNTIF(G84:M84, "Not attempted") -> 0 | E84: Closed - Lost | F84: 10:00 - 12:00 PM | G84: Client lost | H84: 12:00-02:30 | I84: Client lost | J84: 02:30-04:30 | K84: Client lost | L84: 04:30-06:00 | M84: Client lost | N84: qualified | O84: Interested in onsite class. | Q84: 17-5-2025
B85: 92 347 3432922 | C85: =COUNTIF(G85:M85, "Not attempted") -> 0 | D85: Call Attended | E85: Closed - Lost | F85: 10:00 - 12:00 PM | G85: Client lost | H85: 12:00-02:30 | I85: Client lost | J85: 02:30-04:30 | K85: Client lost | L85: 04:30-06:00 | M85: Client lost | O85: not interested. | Q85: 19-5-2025
B86: 92 314 7212749 | C86: =COUNTIF(G86:M86, "Not attempted") -> 0 | D86: Not Attended | E86: Call not Recieved | F86: 10:00 - 12:00 PM | G86: Not Recieved | H86: 12:00-02:30 | I86: Not Recieved | J86: 02:30-04:30 | K86: Not Recieved | L86: 04:30-06:00 | M86: Not Recieved | O86: no response | Q86: 19-5-2025
B87: 92 330 0690070 / 03114117951 | C87: =COUNTIF(G87:M87, "Not attempted") -> 1 | D87: Not Attended | E87: Awaiting payment | F87: 10:00 - 12:00 PM | G87: Call Recieved | H87: 12:00-02:30 | I87: Not Recieved | J87: 02:30-04:30 | K87: Not Recieved | L87: 04:30-06:00 | M87: Not attempted | O87: interested, will pay fees by 21 may./ 26 may / no response | Q87: 19-5-2025
B88: 92 332 4918324 | C88: =COUNTIF(G88:M88, "Not attempted") -> 0 | D88: Not Attended | E88: Contacted | F88: 10:00 - 12:00 PM | G88: Call Recieved | H88: 12:00-02:30 | I88: Not Recieved | J88: 02:30-04:30 | K88: Not Recieved | L88: 04:30-06:00 | M88: Call Recieved | O88: details share again | Q88: 19-5-2025
B89: 92 340 3145012 | C89: =COUNTIF(G89:M89, "Not attempted") -> 0 | D89: Not Attended | E89: Call not Recieved | F89: 10:00 - 12:00 PM | G89: Not Recieved | H89: 12:00-02:30 | I89: Not Recieved | J89: 02:30-04:30 | K89: Not Recieved | L89: 04:30-06:00 | M89: Not Recieved | O89: no response | Q89: 19-5-2025
B90: 92 337 2627563 | C90: =COUNTIF(G90:M90, "Not attempted") -> 0 | D90: Call Attended | E90: Closed - Lost | F90: 10:00 - 12:00 PM | G90: Client lost | H90: 12:00-02:30 | I90: Client lost | J90: 02:30-04:30 | K90: Client lost | L90: 04:30-06:00 | M90: Client lost | N90: non qualified | O90: he's under matric, cannot afford the course | Q90: 19-5-2025
B91: 92 315 2500025 / 92 300 5018448 | C91: =COUNTIF(G91:M91, "Not attempted") -> 1 | D91: Call Attended | E91: Closed - Won | F91: 10:00 - 12:00 PM | G91: Call Recieved | H91: 12:00-02:30 | I91: Not attempted | J91: 02:30-04:30 | K91: Call Recieved | L91: 04:30-06:00 | M91: Call Recieved | N91: qualified | O91: will pay after eid | Q91: 19-5-2025
A92: Fatima | B92: 92 302 6224594 | C92: =COUNTIF(G92:M92, "Not attempted") -> 1 | D92: Call Attended | E92: Awaiting payment | F92: 10:00 - 12:00 PM | G92: Not Recieved | H92: 12:00-02:30 | I92: Not Recieved | J92: 02:30-04:30 | K92: Call Recieved | L92: 04:30-06:00 | M92: Not attempted | N92: qualified | O92: she's waiting fir her payment, will pay fees till 24th may. / no response | Q92: 19-5-2025
B93: 92 343 3207759 | C93: =COUNTIF(G93:M93, "Not attempted") -> 0 | D93: Not Attended | E93: Closed - Lost | F93: 10:00 - 12:00 PM | G93: Client lost | H93: 12:00-02:30 | I93: Client lost | J93: 02:30-04:30 | K93: Client lost | L93: 04:30-06:00 | M93: Client lost | O93: interested in onsite class. | Q93: 19-5-2025
B94: 92 321 4546486 | C94: =COUNTIF(G94:M94, "Not attempted") -> 0 | D94: Call Attended | E94: Closed - Lost | F94: 10:00 - 12:00 PM | G94: Client lost | H94: 12:00-02:30 | I94: Client lost | J94: 02:30-04:30 | K94: Client lost | L94: 04:30-06:00 | M94: Client lost | O94: not interested | Q94: 19-5-2025
B95: 92 335 3161841 | C95: =COUNTIF(G95:M95, "Not attempted") -> 0 | D95: Call Attended | E95: Closed - Lost | F95: 10:00 - 12:00 PM | G95: Client lost | H95: 12:00-02:30 | I95: Client lost | J95: 02:30-04:30 | K95: Client lost | L95: 04:30-06:00 | M95: Client lost | O95: not interested | Q95: 19-5-2025
B96: 92 305 2169970 | C96: =COUNTIF(G96:M96, "Not attempted") -> 0 | D96: Not Attended | E96: Call not Recieved | F96: 10:00 - 12:00 PM | G96: Not Recieved | H96: 12:00-02:30 | I96: Not Recieved | J96: 02:30-04:30 | K96: Not Recieved | L96: 04:30-06:00 | M96: Not Recieved | O96: no response | Q96: 19-5-2025
B97: 92 333 7287541 | C97: =COUNTIF(G97:M97, "Not attempted") -> 0 | D97: Not Attended | E97: Closed - Lost | F97: 10:00 - 12:00 PM | G97: Client lost | H97: 12:00-02:30 | I97: Client lost | J97: 02:30-04:30 | K97: Client lost | L97: 04:30-06:00 | M97: Client lost | O97: not interested | Q97: 19-5-2025
B98: 92 341 2179643 | C98: =COUNTIF(G98:M98, "Not attempted") -> 0 | D98: Call Attended | E98: Closed - Lost | F98: 10:00 - 12:00 PM | G98: Client lost | H98: 12:00-02:30 | I98: Client lost | J98: 02:30-04:30 | K98: Client lost | L98: 04:30-06:00 | M98: Client lost | O98: not interested | Q98: 19-5-2025
B99: 92 313 0008867 | C99: =COUNTIF(G99:M99, "Not attempted") -> 0 | D99: Call Attended | E99: Contacted | F99: 10:00 - 12:00 PM | G99: Not Recieved | H99: 12:00-02:30 | I99: Please Call later | J99: 02:30-04:30 | K99: Call Recieved | L99: 04:30-06:00 | M99: Not Recieved | O99: call him back at 2:30. not responding | Q99: 19-5-2025
A100: SALEEM | B100: 92 344 5612485 | C100: =COUNTIF(G100:M100, "Not attempted") -> 0 | D100: Not Attended | E100: Closed - Lost | F100: 10:00 - 12:00 PM | G100: Client lost | H100: 12:00-02:30 | I100: Client lost | J100: 02:30-04:30 | K100: Client lost | L100: 04:30-06:00 | M100: Client lost | N100: qualified | O100: the student is going to army academy | Q100: 19-5-2025
B101: 92 329 1672497 | C101: =COUNTIF(G101:M101, "Not attempted") -> 0 | D101: Not Attended | E101: Closed - Lost | F101: 10:00 - 12:00 PM | G101: Client lost | H101: 12:00-02:30 | I101: Client lost | J101: 02:30-04:30 | K101: Client lost | L101: 04:30-06:00 | M101: Client lost | O101: not interested. | Q101: 19-5-2025
B102: 92 344 7457442 | C102: =COUNTIF(G102:M102, "Not attempted") -> 0 | D102: Not Attended | E102: Closed - Lost | F102: 10:00 - 12:00 PM | G102: Client lost | H102: 12:00-02:30 | I102: Client lost | J102: 02:30-04:30 | K102: Client lost | L102: 04:30-06:00 | M102: Client lost | O102: not interested. | Q102: 19-5-2025
B103: 92 370 3020434 | C103: =COUNTIF(G103:M103, "Not attempted") -> 0 | D103: Call Attended | E103: Closed - Lost | F103: 10:00 - 12:00 PM | G103: Client lost | H103: 12:00-02:30 | I103: Client lost | J103: 02:30-04:30 | K103: Client lost | L103: 04:30-06:00 | M103: Client lost | O103: doesn't have PC or laptop | Q103: 19-5-2025
...

Sheet 3
A1: Prospect Name | B1: Number | C1: Attempts Missing | D1: Status | E1: stage | F1: Call Slot 1 | G1: Attempt 1 | H1: Call Slot 2 | I1: Attempt 2 | J1: Call Slot 3 | K1: Attempt-3 | L1: Call Slot 4 | M1: Attempt-4 | N1: Lead Type | O1: Notes | P1: Next Step | Q1: date
A2: Unknown | B2: 92 320 0666300 | D2: Call Attended | E2: demo | F2: 10:00 - 12:00 PM | G2: Not Recieved | H2: 12:00-02:30 | I2: Not Recieved | J2: 02:30-04:30 | K2: Call Recieved | L2: 04:30-06:00 | M2: Not attempted | N2: Pending | Q2: 45632
A3: Unknown | B3: 92 326 0822475 | D3: Call Attended | E3: Closed - Lost | F3: 10:00 - 12:00 PM | G3: Client lost | H3: 12:00-02:30 | I3: Client lost | J3: 02:30-04:30 | K3: Call Recieved | L3: 04:30-06:00 | M3: Client lost | N3: Pending | Q3: 45632
A4: Unknown | B4: 92 316 4133981 | D4: Call Attended | E4: Contacted | F4: 10:00 - 12:00 PM | G4: Not Recieved | H4: 12:00-02:30 | I4: Call Recieved | J4: 02:30-04:30 | K4: Not attempted | L4: 04:30-06:00 | M4: Not attempted | N4: Pending | Q4: 45632
A5: Unknown | B5: 92 333 5881325 | D5: Call Attended | E5: Contacted | F5: 10:00 - 12:00 PM | G5: Not attempted | H5: 12:00-02:30 | I5: Call Recieved | J5: 02:30-04:30 | K5: Not Recieved | L5: 04:30-06:00 | M5: Not attempted | N5: Pending | O5: call at 4:30 to 5:00 pm | Q5: 45632
A6: Unknown | B6: 92 311 1371213 | D6: Call Attended | E6: Closed - Lost | F6: 10:00 - 12:00 PM | G6: Client lost | H6: 12:00-02:30 | I6: Client lost | J6: 02:30-04:30 | K6: Call Recieved | L6: 04:30-06:00 | M6: Client lost | N6: Pending | O6: lost lead | Q6: 45632
A7: Unknown | B7: 92 314 7933268 | D7: Call Attended | E7: Contacted | F7: 10:00 - 12:00 PM | G7: Not attempted | H7: 12:00-02:30 | I7: Not attempted | J7: 02:30-04:30 | K7: Call Recieved | L7: 04:30-06:00 | M7: Not Recieved | N7: Pending | O7: share info via whatsapp | Q7: 45632
A8: Unknown | B8: 92 345 6196051 | D8: Not Attended | E8: Call not Recieved | F8: 10:00 - 12:00 PM | G8: Not Recieved | H8: 12:00-02:30 | I8: Not Recieved | J8: 02:30-04:30 | K8: Not Recieved | L8: 04:30-06:00 | M8: Not attempted | N8: Pending | Q8: 45632
A9: Unknown | B9: 92 349 7923078 | D9: Not Attended | E9: Call not Recieved | F9: 10:00 - 12:00 PM | G9: Not Recieved | H9: 12:00-02:30 | I9: Not Recieved | J9: 02:30-04:30 | K9: Not Recieved | L9: 04:30-06:00 | M9: Not attempted | N9: Pending | Q9: 45632
A10: Unknown | B10: 92 308 3726657 | D10: Not Attended | E10: Call not Recieved | F10: 10:00 - 12:00 PM | G10: Not Recieved | H10: 12:00-02:30 | I10: Not Recieved | J10: 02:30-04:30 | K10: Not Recieved | L10: 04:30-06:00 | M10: Not attempted | N10: Pending | Q10: 45632
A11: Unknown | B11: 92 314 0064411 | D11: Not Attended | E11: Call not Recieved | F11: 10:00 - 12:00 PM | G11: Not Recieved | H11: 12:00-02:30 | I11: Not Recieved | J11: 02:30-04:30 | K11: Not Recieved | L11: 04:30-06:00 | M11: Not attempted | N11: Pending | Q11: 45632
A12: Unknown | B12: 92 304 3067324 | D12: Call Attended | E12: Closed - Lost | F12: 10:00 - 12:00 PM | G12: Call Recieved | H12: 12:00-02:30 | I12: Client lost | J12: 02:30-04:30 | K12: Call Recieved | L12: 04:30-06:00 | M12: Call Recieved | N12: Pending | O12: need free | Q12: 45632
A13: Unknown | B13: 92 301 6114457 | D13: Call Attended | E13: Closed - Lost | F13: 10:00 - 12:00 PM | G13: Not attempted | H13: 12:00-02:30 | I13: Not attempted | J13: 02:30-04:30 | K13: Call Recieved | L13: 04:30-06:00 | M13: Not attempted | N13: Pending | O13: demo and then pay | Q13: 45632
A14: Unknown | B14: 93 301 6114457 | D14: Call Attended | E14: Contacted | F14: 10:00 - 12:00 PM | G14: Not attempted | H14: 12:00-02:30 | I14: Not attempted | J14: 02:30-04:30 | K14: Call Recieved | L14: 04:30-06:00 | M14: Call Recieved | N14: Pending | O14: will inform within 2 days | Q14: 45632
A15: Unknown | B15: 92 324 9554609 | D15: Call Attended | E15: Contacted | F15: 10:00 - 12:00 PM | G15: Not attempted | H15: 12:00-02:30 | I15: Not attempted | J15: 02:30-04:30 | K15: Call Recieved | L15: 04:30-06:00 | M15: Not Recieved | N15: Pending | O15: share infoo via whatsapp | Q15: 45632
A16: Unknown | B16: 92 314 4453497 | D16: Not Attended | E16: Call not Recieved | F16: 10:00 - 12:00 PM | G16: Not Recieved | H16: 12:00-02:30 | I16: Not Recieved | J16: 02:30-04:30 | K16: Not Recieved | L16: 04:30-06:00 | M16: Not attempted | N16: Pending | Q16: 45632
A17: Unknown | B17: 92 319 1078815 | D17: Call Attended | E17: Closed - Lost | F17: 10:00 - 12:00 PM | G17: Client lost | H17: 12:00-02:30 | I17: Call Recieved | J17: 02:30-04:30 | K17: Client lost | L17: 04:30-06:00 | M17: Client lost | N17: Pending | O17: lost lead | Q17: 14-6-2024
A18: Unknown | B18: 92 312 6269517 | D18: Call Attended | E18: Closed - Lost | F18: 10:00 - 12:00 PM | G18: Client lost | H18: 12:00-02:30 | I18: Client lost | J18: 02:30-04:30 | K18: Client lost | L18: 04:30-06:00 | M18: Call Recieved | N18: Pending | O18: lost lead | Q18: 45632
A19: Unknown | B19: 92 342 2261417 | D19: Not Attended | E19: Call not Recieved | F19: 10:00 - 12:00 PM | G19: Not Recieved | H19: 12:00-02:30 | I19: Not Recieved | J19: 02:30-04:30 | K19: Not attempted | L19: 04:30-06:00 | M19: Not Recieved | N19: Pending | Q19: 45632
A20: Unknown | B20: 92 323 6802368 | D20: Not Attended | E20: Call not Recieved | F20: 10:00 - 12:00 PM | G20: Not Recieved | H20: 12:00-02:30 | I20: Not Recieved | J20: 02:30-04:30 | K20: Not attempted | L20: 04:30-06:00 | M20: Not Recieved | N20: Pending | Q20: 45632
A21: Unknown | B21: 92 314 3134270 | D21: Not Attended | E21: Call not Recieved | F21: 10:00 - 12:00 PM | G21: Not Recieved | H21: 12:00-02:30 | I21: Not Recieved | J21: 02:30-04:30 | K21: Not attempted | L21: 04:30-06:00 | M21: Not Recieved | N21: Pending | Q21: 45632
A22: Unknown | B22: 92 328 2527505 | D22: Call Attended | E22: Closed - Lost | F22: 10:00 - 12:00 PM | G22: Client lost | H22: 12:00-02:30 | I22: Client lost | J22: 02:30-04:30 | K22: Client lost | L22: 04:30-06:00 | M22: Call Recieved | N22: Pending | Q22: 45632
A23: Unknown | B23: 92 347 3819815 | D23: Not Attended | E23: Call not Recieved | F23: 10:00 - 12:00 PM | G23: Not attempted | H23: 12:00-02:30 | I23: Not Recieved | J23: 02:30-04:30 | K23: Not Recieved | L23: 04:30-06:00 | M23: Not Recieved | N23: Pending | Q23: 45632
A24: Unknown | B24: 92 306 4685191 | D24: Call Attended | E24: Closed - Lost | F24: 10:00 - 12:00 PM | G24: Client lost | H24: 12:00-02:30 | I24: Client lost | J24: 02:30-04:30 | K24: Client lost | L24: 04:30-06:00 | M24: Call Recieved | N24: Pending | O24: lost lead | Q24: 45632
A25: Unknown | B25: 92 333 3181897 | D25: Call Attended | E25: Closed - Lost | F25: 10:00 - 12:00 PM | G25: Client lost | H25: 12:00-02:30 | I25: Call Recieved | J25: 02:30-04:30 | K25: Client lost | L25: 04:30-06:00 | M25: Client lost | N25: Pending | O25: lost lead | Q25: 45632
A26: Unknown | B26: 92 303 0244323 | D26: Call Attended | E26: Closed - Lost | F26: 10:00 - 12:00 PM | G26: Call Recieved | H26: 12:00-02:30 | I26: Client lost | J26: 02:30-04:30 | K26: Client lost | L26: 04:30-06:00 | M26: Client lost | N26: Pending | O26: lost lead | Q26: 45632
A27: Unknown | B27: 92 311 8037168 | D27: Not Attended | E27: Call not Recieved | F27: 10:00 - 12:00 PM | G27: Not attempted | H27: 12:00-02:30 | I27: Not Recieved | J27: 02:30-04:30 | K27: Not Recieved | L27: 04:30-06:00 | M27: Not Recieved | N27: Pending | Q27: 45632
A28: Unknown | B28: 92 321 4551093 | D28: Not Attended | E28: Call not Recieved | F28: 10:00 - 12:00 PM | G28: Not attempted | H28: 12:00-02:30 | I28: Not Recieved | J28: 02:30-04:30 | K28: Not Recieved | L28: 04:30-06:00 | M28: Not Recieved | N28: Pending | Q28: 45632
A29: Unknown | B29: 92 322 2556438 | D29: Call Attended | E29: demo | F29: 10:00 - 12:00 PM | G29: Not attempted | H29: 12:00-02:30 | I29: Not attempted | J29: 02:30-04:30 | K29: Not attempted | L29: 04:30-06:00 | M29: Call Recieved | N29: Pending | O29: will join demo, will join as he is interested in freelancing | Q29: 45632
A30: Unknown | B30: 92 308 8084244 | D30: Call Attended | E30: Closed - Lost | F30: 10:00 - 12:00 PM | G30: Client lost | H30: 12:00-02:30 | I30: Client lost | J30: 02:30-04:30 | K30: Client lost | L30: 04:30-06:00 | M30: Call Recieved | N30: Pending | O30: lost lead | Q30: 45632
A31: Unknown | B31: 92 333 5881325 | D31: Call Attended | E31: demo | F31: 10:00 - 12:00 PM | G31: Call Recieved | H31: 12:00-02:30 | I31: Call Recieved | J31: 02:30-04:30 | K31: Not attempted | L31: 04:30-06:00 | M31: Call Recieved | N31: Pending | Q31: 45632
A32: Unknown | B32: 92 316 3065334 | D32: Call Attended | E32: demo | F32: 10:00 - 12:00 PM | G32: Not attempted | H32: 12:00-02:30 | I32: Not attempted | J32: 02:30-04:30 | K32: Not attempted | L32: 04:30-06:00 | M32: Call Recieved | N32: Pending | O32: pay after demo | Q32: 45632
A33: Unknown | B33: 92 333 0338224 | D33: Not Attended | E33: form filled | F33: 10:00 - 12:00 PM | G33: Not attempted | H33: 12:00-02:30 | I33: Not attempted | J33: 02:30-04:30 | K33: Not attempted | L33: 04:30-06:00 | M33: Not Recieved | N33: Pending | Q33: 45632
A34: Unknown | B34: 92 318 9205638 | D34: Not Attended | E34: Call not Recieved | F34: 10:00 - 12:00 PM | G34: Not attempted | H34: 12:00-02:30 | I34: Not Recieved | J34: 02:30-04:30 | K34: Not Recieved | L34: 04:30-06:00 | M34: Not Recieved | N34: Pending | Q34: 45632
A35: Unknown | B35: 92 316 3381193 | D35: Not Attended | E35: Call not Recieved | F35: 10:00 - 12:00 PM | G35: Not attempted | H35: 12:00-02:30 | I35: Not Recieved | J35: 02:30-04:30 | K35: Not Recieved | L35: 04:30-06:00 | M35: Not Recieved | N35: Pending | Q35: 45632
A36: Unknown | B36: 92 305 5792780 | D36: Not Attended | E36: Call not Recieved | F36: 10:00 - 12:00 PM | G36: Not attempted | H36: 12:00-02:30 | I36: Not Recieved | J36: 02:30-04:30 | K36: Not Recieved | L36: 04:30-06:00 | M36: Not Recieved | N36: Pending | Q36: 45632
A37: Unknown | B37: 92 331 9595766 | D37: Call Attended | E37: Closed - Lost | F37: 10:00 - 12:00 PM | G37: Client lost | H37: 12:00-02:30 | I37: Client lost | J37: 02:30-04:30 | K37: Client lost | L37: 04:30-06:00 | M37: Call Recieved | N37: Pending | O37: lost lead | Q37: 45632
A38: Unknown | B38: 92 341 9618630 | D38: Not Attended | E38: Closed - Lost | F38: 10:00 - 12:00 PM | G38: Client lost | H38: 12:00-02:30 | I38: Client lost | J38: 02:30-04:30 | K38: Client lost | L38: 04:30-06:00 | M38: Not Recieved | N38: Pending | Q38: 45632
A39: Unknown | B39: 92 320 3904860 | D39: Not Attended | E39: Call not Recieved | F39: 10:00 - 12:00 PM | G39: Not attempted | H39: 12:00-02:30 | I39: Not Recieved | J39: 02:30-04:30 | K39: Not Recieved | L39: 04:30-06:00 | M39: Not Recieved | N39: Pending | Q39: 45632
A40: Unknown | B40: 92 309 8286669 | D40: Call Attended | E40: Contacted | F40: 10:00 - 12:00 PM | G40: Not attempted | H40: 12:00-02:30 | I40: Not attempted | J40: 02:30-04:30 | K40: Not Recieved | L40: 04:30-06:00 | M40: Call Recieved | N40: Pending | O40: kal isko discount msg krna hai | Q40: 45632
A41: Unknown | B41: 92 345 6343257 | D41: Not Attended | E41: Call not Recieved | F41: 10:00 - 12:00 PM | G41: Not attempted | H41: 12:00-02:30 | I41: Not Recieved | J41: 02:30-04:30 | K41: Not Recieved | L41: 04:30-06:00 | M41: Not Recieved | N41: Pending | Q41: 45632
A42: Unknown | B42: 92 336 3185152 | D42: Call Attended | E42: Closed - Lost | F42: 10:00 - 12:00 PM | G42: Client lost | H42: 12:00-02:30 | I42: Client lost | J42: 02:30-04:30 | K42: Call Recieved | L42: 04:30-06:00 | M42: Client lost | N42: Pending | O42: lost lead | Q42: 45632
A43: Unknown | B43: 92 324 9570456 | D43: Call Attended | E43: Contacted | F43: 10:00 - 12:00 PM | G43: Not attempted | H43: 12:00-02:30 | I43: Call Recieved | J43: 02:30-04:30 | K43: Not Recieved | L43: 04:30-06:00 | M43: Not Recieved | N43: Pending | Q43: 45632
A44: Unknown | B44: 92 321 1326240 | D44: Call Attended | E44: Awaiting payment | F44: 10:00 - 12:00 PM | G44: Not attempted | H44: 12:00-02:30 | I44: Not attempted | J44: 02:30-04:30 | K44: Not attempted | L44: 04:30-06:00 | M44: Call Recieved | N44: Pending | O44: pay by sat after course starting | Q44: 45632
A45: Unknown | B45: 92 333 5830425 | D45: Call Attended | E45: Contacted | F45: 10:00 - 12:00 PM | G45: Call Recieved | H45: 12:00-02:30 | I45: Not attempted | J45: 02:30-04:30 | K45: Not Recieved | L45: 04:30-06:00 | M45: Not attempted | N45: Pending | O45: will inform within 2 3 days | Q45: 13-6-2024
A46: Unknown | B46: 92 340 7919544 | D46: Not Attended | E46: Call not Recieved | F46: 10:00 - 12:00 PM | G46: Not Recieved | H46: 12:00-02:30 | I46: Not Recieved | J46: 02:30-04:30 | K46: Not Recieved | L46: 04:30-06:00 | M46: Not attempted | N46: Pending | Q46: 13-6-2024
A47: Arsalan | B47: 92 345 2028887 | D47: Call Attended | E47: Awaiting payment | F47: 10:00 - 12:00 PM | G47: Call Recieved | H47: 12:00-02:30 | I47: Call Recieved | J47: 02:30-04:30 | K47: Not attempted | L47: 04:30-06:00 | M47: Not attempted | N47: Pending | O47: pay before 21st, 5000 per month | Q47: 13-6-2024
A48: Unknown | B48: 92 340 0628620 | D48: Call Attended | E48: Contacted | F48: 10:00 - 12:00 PM | G48: Not Recieved | H48: 12:00-02:30 | I48: Please Call later | J48: 02:30-04:30 | K48: Not attempted | L48: 04:30-06:00 | M48: Not attempted | N48: Pending | Q48: 13-6-2024
A49: Unknown | B49: 92 309 0307368 | D49: Call Attended | E49: Contacted | F49: 10:00 - 12:00 PM | G49: Call Recieved | H49: 12:00-02:30 | I49: Not attempted | J49: 02:30-04:30 | K49: Call Recieved | L49: 04:30-06:00 | M49: Not attempted | N49: Pending | O49: will inform by tomorrow | Q49: 13-6-2024
A50: Unknown | B50: 92 306 2165006 | D50: Call Attended | E50: Closed - Lost | F50: 10:00 - 12:00 PM | G50: Client lost | H50: 12:00-02:30 | I50: Client lost | J50: 02:30-04:30 | K50: Client lost | L50: 04:30-06:00 | M50: Client lost | N50: Pending | O50: lost lead | Q50: 13-6-2024
A51: Unknown | B51: 92 302 8724411 | D51: Call Attended | E51: Contacted | F51: 10:00 - 12:00 PM | G51: Call Recieved | H51: 12:00-02:30 | I51: Not attempted | J51: 02:30-04:30 | K51: Not Recieved | L51: 04:30-06:00 | M51: Not attempted | N51: Pending | O51: share info via whatsapp | Q51: 13-6-2024
A52: Unknown | B52: 92 324 4885418 | D52: Call Attended | E52: Closed - Won | F52: 10:00 - 12:00 PM | G52: Call Recieved | H52: 12:00-02:30 | I52: Call Recieved | J52: 02:30-04:30 | K52: Not attempted | L52: 04:30-06:00 | M52: Not attempted | N52: Pending | Q52: 13-6-2024
A53: Unknown | B53: 92 348 0179966 | D53: Not Attended | E53: Call not Recieved | F53: 10:00 - 12:00 PM | G53: Not Recieved | H53: 12:00-02:30 | I53: Not Recieved | J53: 02:30-04:30 | K53: Not Recieved | L53: 04:30-06:00 | M53: Not attempted | N53: Pending | Q53: 13-6-2024
A54: Unknown | B54: 92 349 3130886 | D54: Call Attended | E54: Closed - Lost | F54: 10:00 - 12:00 PM | G54: Call Recieved | H54: 12:00-02:30 | I54: Client lost | J54: 02:30-04:30 | K54: Client lost | L54: 04:30-06:00 | M54: Client lost | N54: Pending | O54: can't afford | Q54: 13-6-2024
A55: Unknown | B55: 92 321 7444114 | D55: Call Attended | E55: demo | F55: 10:00 - 12:00 PM | G55: Call Recieved | H55: 12:00-02:30 | I55: Not attempted | J55: 02:30-04:30 | K55: Not attempted | L55: 04:30-06:00 | M55: Not attempted | N55: Pending | O55: interested , demo required | Q55: 13-6-2024
A56: Unknown | B56: 92 345 2468056 | D56: Call Attended | E56: Closed - Lost | F56: 10:00 - 12:00 PM | G56: Call Recieved | H56: 12:00-02:30 | I56: Client lost | J56: 02:30-04:30 | K56: Client lost | L56: 04:30-06:00 | M56: Client lost | N56: Pending | O56: lost lead | Q56: 13-6-2024
A57: Unknown | B57: 92 324 1375023 | D57: Call Attended | E57: Closed - Lost | F57: 10:00 - 12:00 PM | G57: Call Recieved | H57: 12:00-02:30 | I57: Client lost | J57: 02:30-04:30 | K57: Client lost | L57: 04:30-06:00 | M57: Client lost | N57: Pending | O57: free course | Q57: 13-6-2024
A58: Unknown | B58: 92 340 0470814 | D58: Not Attended | E58: Call not Recieved | F58: 10:00 - 12:00 PM | G58: Not Recieved | H58: 12:00-02:30 | I58: Not Recieved | J58: 02:30-04:30 | K58: Not Recieved | L58: 04:30-06:00 | M58: Not attempted | N58: Pending | Q58: 13-6-2024
A59: Unknown | B59: 92 311 2104966 | D59: Not Attended | E59: Call not Recieved | F59: 10:00 - 12:00 PM | G59: Not Recieved | H59: 12:00-02:30 | I59: Not Recieved | J59: 02:30-04:30 | K59: Not Recieved | L59: 04:30-06:00 | M59: Not attempted | N59: Pending | Q59: 13-6-2024
A60: Unknown | B60: 92 325 9168040 | D60: Not Attended | E60: Call not Recieved | F60: 10:00 - 12:00 PM | G60: Not Recieved | H60: 12:00-02:30 | I60: Not Recieved | J60: 02:30-04:30 | K60: Not Recieved | L60: 04:30-06:00 | M60: Not attempted | N60: Pending | Q60: 13-6-2024
A61: Unknown | B61: 92 314 7560825 | D61: Call Attended | E61: Contacted | F61: 10:00 - 12:00 PM | G61: Not Recieved | H61: 12:00-02:30 | I61: Call Recieved | J61: 02:30-04:30 | K61: Not attempted | L61: 04:30-06:00 | M61: Not attempted | N61: Pending | Q61: 13-6-2024
A62: Unknown | B62: 92 333 8545834 | D62: Call Attended | E62: Contacted | F62: 10:00 - 12:00 PM | G62: Please Call later | H62: 12:00-02:30 | I62: Not attempted | J62: 02:30-04:30 | K62: Call Recieved | L62: 04:30-06:00 | M62: Not attempted | N62: Pending | O62: share info via whatsapp | Q62: 13-6-2024
A63: Unknown | B63: 92 309 6575682 | D63: Call Attended | E63: Closed - Lost | F63: 10:00 - 12:00 PM | G63: Call Recieved | H63: 12:00-02:30 | I63: Client lost | J63: 02:30-04:30 | K63: Client lost | L63: 04:30-06:00 | M63: Client lost | N63: Pending | O63: lost lead | Q63: 13-6-2024
A64: Unknown | B64: 92 313 2609919 | D64: Not Attended | E64: Call not Recieved | F64: 10:00 - 12:00 PM | G64: Not Recieved | H64: 12:00-02:30 | I64: Not Recieved | J64: 02:30-04:30 | K64: Not Recieved | L64: 04:30-06:00 | M64: Not attempted | N64: Pending | Q64: 13-6-2024
A65: Unknown | B65: 92 347 0800568 | D65: Not Attended | E65: Call not Recieved | F65: 10:00 - 12:00 PM | G65: Not Recieved | H65: 12:00-02:30 | I65: Not Recieved | J65: 02:30-04:30 | K65: Not Recieved | L65: 04:30-06:00 | M65: Not attempted | N65: Pending | Q65: 13-6-2024
A66: Unknown | B66: 92 311 3502427 | D66: Call Attended | E66: Closed - Lost | F66: 10:00 - 12:00 PM | G66: Not Recieved | H66: 12:00-02:30 | I66: Call Recieved | J66: 02:30-04:30 | K66: Client lost | L66: 04:30-06:00 | M66: Client lost | N66: Pending | O66: lost lead | Q66: 13-6-2024
A67: Unknown | B67: 92 333 7594734 | D67: Not Attended | E67: Contacted | F67: 10:00 - 12:00 PM | G67: Not Recieved | H67: 12:00-02:30 | I67: Call Recieved | J67: 02:30-04:30 | K67: Not attempted | L67: 04:30-06:00 | M67: Not attempted | N67: Pending | Q67: 13-6-2024
A68: Unknown | B68: 92 330 9877977 | D68: Call Attended | E68: Contacted | F68: 10:00 - 12:00 PM | G68: Call Recieved | H68: 12:00-02:30 | I68: Not attempted | J68: 02:30-04:30 | K68: Call Recieved | L68: 04:30-06:00 | M68: Not attempted | N68: Pending | O68: inform b y 19th june | Q68: 13-6-2024
A69: Unknown | B69: 92 329 7165958 | D69: Not Attended | E69: Call not Recieved | F69: 10:00 - 12:00 PM | G69: Not Recieved | H69: 12:00-02:30 | I69: Not Recieved | J69: 02:30-04:30 | K69: Not Recieved | L69: 04:30-06:00 | M69: Not attempted | N69: Pending | Q69: 13-6-2024
A70: Unknown | B70: 92 322 3237574 | D70: Call Attended | E70: Contacted | F70: 10:00 - 12:00 PM | G70: Call Recieved | H70: 12:00-02:30 | I70: Call Recieved | J70: 02:30-04:30 | K70: Not attempted | L70: 04:30-06:00 | M70: Not attempted | N70: Pending | O70: will inform | Q70: 13-6-2024
A71: Unknown | B71: 92 322 0226423 | D71: Not Attended | E71: Call not Recieved | F71: 10:00 - 12:00 PM | G71: Not Recieved | H71: 12:00-02:30 | I71: Not Recieved | J71: 02:30-04:30 | K71: Not Recieved | L71: 04:30-06:00 | M71: Not attempted | N71: Pending | Q71: 13-6-2024
A72: Unknown | B72: 92 316 4354442 | D72: Not Attended | E72: Call not Recieved | F72: 10:00 - 12:00 PM | G72: Not Recieved | H72: 12:00-02:30 | I72: Not Recieved | J72: 02:30-04:30 | K72: Not attempted | L72: 04:30-06:00 | M72: Not attempted | N72: Pending | Q72: 13-6-2024
A73: Unknown | B73: 92 347 3292580 | D73: Call Attended | E73: Closed - Lost | F73: 10:00 - 12:00 PM | G73: Call Recieved | H73: 12:00-02:30 | I73: Client lost | J73: 02:30-04:30 | K73: Client lost | L73: 04:30-06:00 | M73: Client lost | N73: Pending | O73: lost need free | Q73: 13-6-2024
A74: Unknown | B74: 92 333 3467825 | D74: Call Attended | E74: Closed - Lost | F74: 10:00 - 12:00 PM | G74: Call Recieved | H74: 12:00-02:30 | I74: Client lost | J74: 02:30-04:30 | K74: Client lost | L74: 04:30-06:00 | M74: Client lost | N74: Pending | O74: lost lead | Q74: 13-6-2024
A75: Unknown | B75: 92 306 4311505 | D75: Not Attended | E75: Call not Recieved | F75: 10:00 - 12:00 PM | G75: Not Recieved | H75: 12:00-02:30 | I75: Not Recieved | J75: 02:30-04:30 | K75: Not attempted | L75: 04:30-06:00 | M75: Not attempted | N75: Pending | Q75: 13-6-2024
A76: Unknown | B76: 92 331 7518028 | D76: Call Attended | E76: Closed - Lost | F76: 10:00 - 12:00 PM | G76: Call Recieved | H76: 12:00-02:30 | I76: Client lost | J76: 02:30-04:30 | K76: Client lost | L76: 04:30-06:00 | M76: Client lost | N76: Pending | O76: lost lead | Q76: 13-6-2024
A77: Unknown | B77: 92 331 5542432 | D77: Not Attended | E77: Call not Recieved | F77: 10:00 - 12:00 PM | G77: Not Recieved | H77: 12:00-02:30 | I77: Not Recieved | J77: 02:30-04:30 | K77: Not attempted | L77: 04:30-06:00 | M77: Not attempted | N77: Pending | Q77: 13-6-2024
A78: Unknown | B78: 92 317 2852463 | D78: Not Attended | E78: Call not Recieved | F78: 10:00 - 12:00 PM | G78: Not Recieved | H78: 12:00-02:30 | I78: Not Recieved | J78: 02:30-04:30 | K78: Not attempted | L78: 04:30-06:00 | M78: Not attempted | N78: Pending | Q78: 13-6-2024
A79: Unknown | B79: 92 300 9692115 | D79: Call Attended | E79: Contacted | F79: 10:00 - 12:00 PM | G79: Call Recieved | H79: 12:00-02:30 | I79: Not attempted | J79: 02:30-04:30 | K79: Not Recieved | L79: 04:30-06:00 | M79: Not attempted | N79: Pending | Q79: 13-6-2024
A80: Unknown | B80: 92 304 1778741 | D80: Not Attended | E80: Call not Recieved | F80: 10:00 - 12:00 PM | G80: Not Recieved | H80: 12:00-02:30 | I80: Not Recieved | J80: 02:30-04:30 | K80: Not attempted | L80: 04:30-06:00 | M80: Not attempted | N80: Pending | Q80: 13-6-2024
A81: Unknown | B81: 92 331 5194715 | D81: Call Attended | E81: Awaiting payment | F81: 10:00 - 12:00 PM | G81: Not Recieved | H81: 12:00-02:30 | I81: Not Recieved | J81: 02:30-04:30 | K81: Call Recieved | L81: 04:30-06:00 | M81: Not attempted | N81: Pending | O81: pay by monday, share grp link | Q81: 13-6-2024
A82: Unknown | B82: 92 303 6515022 | D82: Not Attended | E82: Closed - Lost | F82: 10:00 - 12:00 PM | G82: Client lost | H82: 12:00-02:30 | I82: Client lost | J82: 02:30-04:30 | K82: Client lost | L82: 04:30-06:00 | M82: Client lost | N82: Pending | O82: lost lead | Q82: 13-6-2024
A83: Unknown | B83: 92 341 3027497 | D83: Call Attended | E83: Closed - Lost | F83: 10:00 - 12:00 PM | G83: Client lost | H83: 12:00-02:30 | I83: Client lost | J83: 02:30-04:30 | K83: Client lost | L83: 04:30-06:00 | M83: Client lost | N83: Pending | O83: lost lead | Q83: 13-6-2024
A84: Unknown | B84: 92 322 3063401 | D84: Call Attended | E84: Closed - Lost | F84: 10:00 - 12:00 PM | G84: Client lost | H84: 12:00-02:30 | I84: Client lost | J84: 02:30-04:30 | K84: Client lost | L84: 04:30-06:00 | M84: Client lost | N84: Pending | O84: lost lead | Q84: 13-6-2024
A85: Unknown | B85: 92 328 6644965 | D85: Not Attended | E85: Call not Recieved | F85: 10:00 - 12:00 PM | G85: Not Recieved | H85: 12:00-02:30 | I85: Not Recieved | J85: 02:30-04:30 | K85: Not attempted | L85: 04:30-06:00 | M85: Not attempted | N85: Pending | Q85: 13-6-2024
A86: Unknown | B86: 92 335 4102136 | D86: Call Attended | E86: Closed - Lost | F86: 10:00 - 12:00 PM | G86: Client lost | H86: 12:00-02:30 | I86: Client lost | J86: 02:30-04:30 | K86: Client lost | L86: 04:30-06:00 | M86: Client lost | N86: Pending | O86: lost lead | Q86: 13-6-2024
A87: Unknown | B87: 92 348 0179966 | D87: Not Attended | E87: Closed - Lost | F87: 10:00 - 12:00 PM | G87: Client lost | H87: 12:00-02:30 | I87: Client lost | J87: 02:30-04:30 | K87: Client lost | L87: 04:30-06:00 | M87: Client lost | N87: Pending | O87: lost lead | Q87: 13-6-2024
A88: Unknown | B88: 92 322 7760080 | D88: Call Attended | E88: Awaiting payment | F88: 10:00 - 12:00 PM | G88: Call Recieved | H88: 12:00-02:30 | I88: Call Recieved | J88: 02:30-04:30 | K88: Not attempted | L88: 04:30-06:00 | M88: Not attempted | N88: Pending | O88: pay by this week but timing issue that's why he'll join the 1st class | Q88: 13-6-2024
A89: Unknown | B89: 92 321 7486083 | D89: Call Attended | E89: Contacted | F89: 10:00 - 12:00 PM | G89: Not attempted | H89: 12:00-02:30 | I89: Call Recieved | J89: 02:30-04:30 | K89: Not attempted | L89: 04:30-06:00 | M89: Not attempted | N89: Pending | O89: will inform | Q89: 13-6-2024
A90: Unknown | B90: 92 331 1281661 | D90: Call Attended | E90: Closed - Lost | F90: 10:00 - 12:00 PM | G90: Client lost | H90: 12:00-02:30 | I90: Call Recieved | J90: 02:30-04:30 | K90: Client lost | L90: 04:30-06:00 | M90: Client lost | N90: Pending | O90: need job | Q90: 13-6-2024
A91: Unknown | B91: 92 326 1137419 | D91: Not Attended | E91: Call not Recieved | F91: 10:00 - 12:00 PM | G91: Not Recieved | H91: 12:00-02:30 | I91: Not Recieved | J91: 02:30-04:30 | K91: Not attempted | L91: 04:30-06:00 | M91: Not attempted | N91: Pending | Q91: 13-6-2024
A92: Unknown | B92: 92 311 2222701 | D92: Call Attended | E92: Awaiting payment | F92: 10:00 - 12:00 PM | G92: Call Recieved | H92: 12:00-02:30 | I92: Call Recieved | J92: 02:30-04:30 | K92: Not attempted | L92: 04:30-06:00 | M92: Not attempted | N92: Pending | O92: will pay | Q92: 13-6-2024
A93: Unknown | B93: 92 345 1357977 | D93: Not Attended | E93: Call not Recieved | F93: 10:00 - 12:00 PM | G93: Not Recieved | H93: 12:00-02:30 | I93: Not Recieved | J93: 02:30-04:30 | K93: Not attempted | L93: 04:30-06:00 | M93: Not attempted | N93: Pending | O93: no response | Q93: 13-6-2024
A94: Unknown | B94: 92 344 3177168 | D94: Not Attended | E94: Closed - Lost | F94: 10:00 - 12:00 PM | G94: Not Recieved | H94: 12:00-02:30 | I94: Client lost | J94: 02:30-04:30 | K94: Client lost | L94: 04:30-06:00 | M94: Client lost | N94: Pending | O94: lost lead | Q94: 13-6-2024
A95: Unknown | B95: 92 335 7369660 | D95: Not Attended | E95: Call not Recieved | F95: 10:00 - 12:00 PM | G95: Not Recieved | H95: 12:00-02:30 | I95: Not Recieved | J95: 02:30-04:30 | K95: Not Recieved | L95: 04:30-06:00 | M95: Not attempted | N95: Pending | Q95: 13-6-2024
A96: Unknown | B96: 92 340 2346466 | D96: Not Attended | E96: Call not Recieved | F96: 10:00 - 12:00 PM | G96: Not Recieved | H96: 12:00-02:30 | I96: Not Recieved | J96: 02:30-04:30 | K96: Not Recieved | L96: 04:30-06:00 | M96: Not attempted | N96: Pending | Q96: 13-6-2024
A97: Unknown | B97: 92 343 0426901 | D97: Call Attended | E97: Contacted | F97: 10:00 - 12:00 PM | G97: Not attempted | H97: 12:00-02:30 | I97: Not attempted | J97: 02:30-04:30 | K97: Call Recieved | L97: 04:30-06:00 | M97: Not attempted | N97: Pending | O97: provide her discount | Q97: 13-6-2024
A98: Unknown | B98: 92 327 5937103 | D98: Call Attended | E98: Closed - Lost | F98: 10:00 - 12:00 PM | G98: Client lost | H98: 12:00-02:30 | I98: Client lost | J98: 02:30-04:30 | K98: Call Recieved | L98: 04:30-06:00 | M98: Client lost | N98: Pending | O98: lost lead | Q98: 13-6-2024
A99: Unknown | B99: 92 336 6444998 | D99: Not Attended | E99: Call not Recieved | F99: 10:00 - 12:00 PM | G99: Not Recieved | H99: 12:00-02:30 | I99: Not Recieved | J99: 02:30-04:30 | K99: Not Recieved | L99: 04:30-06:00 | M99: Not attempted | N99: Pending | Q99: 13-6-2024
A100: Unknown | B100: 92 329 4454305 | D100: Not Attended | E100: Call not Recieved | F100: 10:00 - 12:00 PM | G100: Not Recieved | H100: 12:00-02:30 | I100: Not Recieved | J100: 02:30-04:30 | K100: Not Recieved | L100: 04:30-06:00 | M100: Not attempted | N100: Pending | Q100: 13-6-2024
...

Sheet Sheet14
A1: S.No | B1: Approach Date | C1: Prospect Name | D1: Number | E1: Followup Date | F1: stage | G1: Interest Level | H1: Price Proposed | I1: Reason (applicable if client lost) | J1: Column 1
A2: 1 | B2: 7/8/2024 | C2: Nareesha | D2: 03463361005 | E2: 44385 | F2: Awaiting Response
A3: 2 | B3: 7/8/2024 | C3: Irshad | D3: 0340 8703176 | E3: 45481 | F3: Awaiting Response
A4: 3 | B4: 7/8/2024 | C4: Asad | D4: 03470263463 | E4: 45481 | F4: Awaiting Response
A5: 4 | B5: 7/8/2024 | C5: Ali | D5: 03035113903 | E5: 45481 | F5: Awaiting Response
A6: 5 | B6: 7/8/2024 | C6: Qurat ul aine | D6: 03410223340 | E6: 45481 | F6: Closed - Won
A7: 6 | B7: 8/8/2024 | C7: Ayesha | D7: 03035901289 | E7: 45512 | F7: Awaiting Response | J7: 100 baclog
A8: 7 | B8: 15/8/2024 | C8: Mehran Gorsi | D8: 03131862557 | E8: 45512 | F8: Awaiting Response
A9: 8 | B9: 15/8/2024 | C9: Ghayoor Iqbal | D9: 03009264631 | E9: 19/8/2024 | F9: Awaiting Response
A10: 9 | B10: 15/8/2024 | C10: Sarim | D10: 03000884313 | E10: 19/8/2024 | F10: Awaiting Response
A11: 10 | B11: 15/8/2024 | C11: Abdul Haseeb | D11: 03150323440 | E11: 19/8/2024 | F11: Closed - Lost
A12: 11 | B12: 15/8/2024 | D12: 03186983988 | E12: 19/8/2024 | F12: Call not Recieved
A13: 12 | B13: 15/8/2024 | C13: Zain ul abedin | D13: 03339607009 | E13: 19/8/2024 | F13: Form Filled
A14: 13 | B14: 15/8/2024 | C14: Daniyal | D14: 03362255532 | E14: 19/8/2024 | F14: Awaiting Response
A15: 14 | B15: 15/8/2024 | D15: 03474828062 | E15: 19/8/2024 | F15: Call not Recieved
A16: 15 | B16: 15/8/2024 | C16: Waleed | D16: 03104394336 | E16: 19/8/2024 | F16: Call not Recieved
A17: 16 | B17: 15/8/2024 | C17: Gulam Rasool | D17: 03042373757 | E17: 19/8/2024 | F17: Closed - Won
A18: 17 | B18: 15/8/2024 | C18: Syed hussain | D18: 03157667284 | E18: 19/8/2024 | F18: Closed - Won
A19: 18 | B19: 15/8/2024 | C19: Okasha | D19: 03322264342 | E19: 19/8/2024 | F19: Call not Recieved
A20: 19 | B20: 15/8/2024 | D20: 03339477665 | E20: Why does he want to take part in the course e.g money, career | F20: Form unfilled
A21: 20 | B21: 16/8/2024 | C21: Tajamul rajper | D21: 03093169199 | E21: 19/8/2024 | F21: Form unfilled
A22: 21 | B22: 16/8/2024 | C22: Salman | D22: 03308437479 | E22: 19/8/2024 | F22: Awaiting Response
A23: 22 | B23: 16/8/2024 | C23: Awais Ali | D23: 03122010185 | E23: 19/8/2024 | F23: Awaiting Response
A24: 23 | B24: 16/8/2024 | D24: 03157040668 | E24: 19/8/2024 | F24: Form unfilled
A25: 24 | B25: 16/8/2024 | C25: Hassan Ul Haq | D25: 03200247198 | E25: 20/8/2024 | F25: Awaiting Response
A26: 25 | B26: 16/8/2024 | C26: Adeel Sheikh | D26: 03453084454 | E26: 20/8/2024 | F26: Awaiting Response
A27: 26 | B27: 16/8/2024 | C27: Haris Ahmed | D27: 03118639290 | E27: 20/8/2024 | F27: Closed - Won
A28: 27 | B28: 16/8/2024 | D28: 03061103887 | E28: 20/8/2024 | F28: Awaiting Response
A29: 28 | B29: 16/8/2024 | C29: Simran modi | D29: 03332145602 | E29: 20/8/2024 | F29: Form Filled
A30: 29 | B30: 16/8/2024 | C30: Huzaifa Asghar | D30: 03168958142 | E30: 20/8/2024 | F30: Closed - Lost
A31: 30 | B31: 16/8/2024 | C31: Muhammad Azaan | D31: 03432647815 | E31: 20/8/2024 | F31: Form unfilled
A32: 31 | B32: 16/8/2024 | C32: Mohiuddin | D32: 03333795434 | E32: 20/8/2024 | F32: Form unfilled
A33: 32 | B33: 16/8/2024 | C33: Talha | D33: 03096663943 | E33: 20/8/2024 | F33: Form unfilled
A34: 33 | B34: 16/8/2024 | C34: Mustafa | D34: 03212022768 | E34: 20/8/2024 | F34: Form unfilled
A35: 34 | B35: 16/8/2024 | C35: Eriba | D35: 03019354175 | E35: 20/8/2024 | F35: Closed - Won
A36: 35 | B36: 16/8/2024 | C36: M.hadi | D36: 03172563120 | E36: 22/8/2024 | F36: Form unfilled
A37: 36 | B37: 16/8/2024 | D37: 03363305243 | E37: 22/8/2024 | F37: Form unfilled
A38: 37 | B38: 16/8/2024 | C38: SAJID HUSSAIN | D38: 03008974571 | E38: 22/8/2024 | F38: Form unfilled
A39: 38 | B39: 16/8/2024 | D39: 60 11-7249 9780 | E39: Why does he want to take part in the course e.g money, career | F39: Form unfilled
A40: 39 | B40: 16/8/2024 | D40: 03081001532 | E40: 22/8/2024 | F40: Form unfilled
A41: 40 | B41: 16/8/2024 | D41: 03432106570 | E41: 22/8/2024 | F41: Form unfilled
A42: 41 | B42: 16/8/2024 | D42: 03074254897 | E42: 22/8/2024 | F42: Form unfilled
A43: 42 | B43: 16/8/2024 | C43: Shoaib Rehman | D43: 03209667432 | E43: 22/8/2024 | F43: Form unfilled
A44: 43 | B44: 16/8/2024 | C44: Naeem Mustiyaq | D44: 03218754015 | E44: 22/8/2024 | F44: Awaiting Response
A45: 44 | B45: 16/8/2024 | C45: Baseerat | D45: 03092377360 | E45: 22/8/2024 | F45: Awaiting Response
A46: 45 | B46: 16/8/2024 | D46: 03120214111 | E46: 22/8/2024 | F46: Form unfilled
A47: 46 | B47: 16/8/2024 | C47: Syed hunain | D47: 03132343459 | E47: 22/8/2024 | F47: Form unfilled
A48: 47 | B48: 16/8/2024 | C48: Munibulhassan | D48: 03231399054 | E48: 22/8/2024 | F48: Closed - Won
A49: 48 | B49: 16/8/2024 | C49: Tariq Arshad | D49: 03002137050 | E49: 27/8/2024 | F49: Form unfilled
A50: 49 | B50: 16/8/2024 | C50: AsimKhan | D50: 03072112966 | E50: 27/8/2024 | F50: Form unfilled
A51: 50 | B51: 16/8/2024 | C51: Huzaifa | D51: 03244201764 | E51: 27/8/2024 | F51: Form unfilled
A52: 51 | B52: 16/8/2024 | C52: Faisal Shah | D52: 03336481207 | E52: 27/8/2024 | F52: Form Filled
A53: 52 | B53: 16/8/2024 | C53: Asim Raza | D53: 03146103304 | E53: 27/8/2024 | F53: Please call later
A54: 53 | B54: 16/8/2024 | D54: 325 2705385 | E54: 27/8/2024 | F54: Form unfilled
A55: 54 | B55: 16/8/2024 | D55: 03252705385 | E55: 27/8/2024 | F55: Form unfilled
A56: 55 | B56: 16/8/2024 | C56: Daniyal wahab | D56: 03472068273 | E56: Why does he want to take part in the course e.g money, career | F56: Awaiting Response
A57: 56 | B57: 16/8/2024 | C57: Shohaib | D57: 03232295301 | E57: 27/8/2024 | F57: Form unfilled
A58: 57 | B58: 16/8/2024 | D58: 03232295302 | E58: 27/8/2024 | F58: Form unfilled
A59: 58 | B59: 16/8/2024 | D59: 03232295303 | E59: 27/8/2024 | F59: Form unfilled
A60: 59 | B60: 16/8/2024 | D60: 03232295304 | E60: 27/8/2024 | F60: Form unfilled
A61: 60 | B61: 16/8/2024 | D61: 03232295305 | E61: 27/8/2024 | F61: Form unfilled
A62: 61 | B62: 16/8/2024 | D62: 03232295306 | E62: 27/8/2024 | F62: Form unfilled
A63: 62 | B63: 16/8/2024 | D63: 03232295307 | E63: 27/8/2024 | F63: Form unfilled
A64: 63 | B64: 16/8/2024 | D64: 03104229928 | E64: 27/8/2024 | F64: Closed - Lost
A65: 64 | B65: 16/8/2024 | D65: 03026577496 | E65: 27/8/2024 | F65: Form unfilled
A66: 65 | B66: 18/8/2024 | C66: Ayesha Ashraf | D66: 03470235619 | E66: 27/8/2024 | F66: Closed - Won
A67: 66 | B67: 19/8/2024 | D67: 03037328702 | E67: 27/8/2024 | F67: Form unfilled
A68: 67 | B68: 19/8/2024 | D68: 03047600573 | E68: 27/8/2024 | F68: Closed - Lost
A69: 68 | B69: 19/8/2024 | D69: 03178825400 | E69: 27/8/2024 | F69: Please call later
A70: 69 | B70: 19/8/2024 | D70: 90534089 74 57 | E70: Why does he want to take part in the course e.g money, career | F70: Form unfilled
A71: 70 | B71: 19/8/2024 | C71: Haider Asif | D71: 03080178118 | E71: 27/8/2024 | F71: Form unfilled
A72: 71 | B72: 19//8/2024 | C72: Syed Imran | D72: 03352676046 | E72: Why does he want to take part in the course e.g money, career | F72: Closed - Won
A73: 72 | B73: 19/8/2024 | D73: 03353001378 | E73: 27/8/2024 | F73: Form unfilled
A74: 73 | B74: 19/8/2024 | C74: Sufyan | D74: 03182350763 | E74: 27/8/2024 | F74: Form unfilled
A75: 74 | B75: 19/8/2024 | C75: Abdul Quddus Memon | D75: 03000881819 | E75: 19/8/2024 | F75: Closed - Won
A76: 75 | B76: 19/8/2024 | C76: Touseef Ahmed | D76: 03122713862 | E76: 21/8/2024 | F76: Form unfilled
A77: 76 | B77: 19/8/2024 | D77: 03062145142 | E77: 21/8/2024 | F77: Form unfilled
A78: 77 | B78: 19/8/2024 | D78: 03066748412 | E78: 21/8/2024 | F78: Form unfilled
A79: 78 | B79: 19/8/2024 | D79: 03345510143 | E79: 21/8/2024 | F79: Form unfilled
A80: 79 | B80: 19/8/2024 | D80: 03107775168 | E80: 21/8/2024 | F80: Form unfilled
A81: 80 | B81: 19/8/2024 | C81: Abdulsalam | D81: 03222291959 | E81: 21/8/2024 | F81: Form unfilled
A82: 81 | B82: 20/8/2024 | C82: marium shiraz | D82: 03110588326 | E82: 20/8/2024 | F82: Form Filled
A83: 82 | B83: 20/8/2024 | C83: Shahid Saleem | D83: 03224818569 | E83: 20/8/2024 | F83: Awaiting Response
A84: 83 | B84: 20/8/2024 | D84: 03378370197 | E84: 21/8/2024 | F84: Form unfilled
A85: 84 | B85: 20/8/2024 | D85: 03135259162 | E85: 21/8/2024 | F85: Form unfilled
A86: 85 | B86: 20/8/2024 | C86: Hamza | D86: 03344432479 | E86: 21/8/2024 | F86: Form unfilled
A87: 86 | B87: 20/8/2024 | C87: Abdul Rasool | D87: 03160365911 | E87: 21/8/2024 | F87: Form Filled
A88: 87 | B88: 20/8/2024 | C88: Shahrukh khan | D88: 03013361246 | E88: 21/8/2024 | F88: Form unfilled
A89: 88 | B89: 21/8/2024 | C89: Muhammad tayyab Irfan | D89: 03100446369 | E89: 21/8/2024 | F89: Form Filled
A90: 89 | B90: 21/8/2024 | C90: Umar farooq | D90: 03014044102 | E90: 21/8/2024 | F90: Closed - Lost
A91: 90 | B91: 21/8/2024 | C91: Hamza Ayyub | D91: 03140165834 | E91: 21/8/2024 | F91: Form Filled
A92: 91 | B92: 21/8/2024 | C92: Prem Sagar | D92: 03322514972 | E92: 21/8/2024 | F92: Form Filled
A93: 92 | B93: 21/8/2024 | C93: Wali Ullah Siddique | D93: 03174353203 | E93: 21/8/2024 | F93: Form Filled
A94: 93 | B94: 21/8/2024 | C94: Asim Qaiser | D94: 03216372310 | E94: 21/8/2024 | F94: Form Filled
A95: 94 | B95: 21/8/2024 | C95: Haseebullah | D95: 03224814481 | E95: 21/8/2024 | F95: Form Filled
A96: 95 | B96: 21/8/2024 | C96: Alweena Murtaza | D96: 03064450591 | E96: 21/8/2024 | F96: Form Filled
A97: 96 | B97: 21/8/2024 | C97: Muhammad Mujahid | D97: 03455012890 | E97: 21/8/2024 | F97: Form Filled
... A107: 106 | B107: 21/8/2024 | C107: Syed Sarim | D107: 0323-7034858 | E107: 21/8/2024 | F107: Closed - Lost
A108: 107 | B108: 21/8/2024 | D108: 03408047882 | E108: 23/8/2024 | F108: Form unfilled
A109: 108 | B109: 21/8/2024 | C109: Moiz | D109: 03432802631 | E109: 23/8/2024 | F109: Form unfilled
...

Sheet Sheet13
A1: Date | B1: Prospect Name | C1: Number | D1: Date of Reach | E1: Why join? | F1: Called on (Date/Time) | G1: stage | H1: First Followup (+2) | I1: Second Followup (+5) | J1: Third Followup (+7) | K1: Fourth Followup (+14) | L1: Notes
A2: June | B2: Tech Fusion Works | C2: 03222726399 | D2: The background can be finance, marketing, engineering with __ years of experience | E2: Why does he want to take part in the course e.g money, career | F2: 45543 | G2: Closed - Lost
A3: July | B3: Unknown | C3: 03472483315 | D3: The background can be finance, marketing, engineering with __ years of experience | E3: Why does he want to take part in the course e.g money, career | G3: Contacted
A4: June | B4: Faheem Soomro | C4: 03062115885 | D4: The background can be finance, marketing, engineering with __ years of experience | E4: Why does he want to take part in the course e.g money, career | F4: 45543 | G4: Closed - Lost
A5: July | B5: Umais Jalalkhel | C5: 03239705489 | D5: The background can be finance, marketing, engineering with __ years of experience | E5: Why does he want to take part in the course e.g money, career | F5: 45543 | G5: Call not Recieved
A6: June | B6: Hadia rizwan | C6: 03408196357 | D6: The background can be finance, marketing, engineering with __ years of experience | E6: Why does he want to take part in the course e.g money, career | F6: 45543 | G6: Closed - Won
A7: July | B7: Muhammad Raza | C7: 03332263248 | D7: The background can be finance, marketing, engineering with __ years of experience | E7: Why does he want to take part in the course e.g money, career | G7: Closed - Lost
A8: June | B8: Adnan Anwer Ali | C8: 03323148262 | D8: The background can be finance, marketing, engineering with __ years of experience | E8: Why does he want to take part in the course e.g money, career | F8: 45543 | G8: Closed - Lost
A9: July | B9: Faizan Rasheed | C9: 03055567776 | D9: The background can be finance, marketing, engineering with __ years of experience | E9: Why does he want to take part in the course e.g money, career | F9: 45543 | G9: Form Filled
A10: June | B10: Abu Hurera | C10: 03138396788 | D10: The background can be finance, marketing, engineering with __ years of experience | E10: Why does he want to take part in the course e.g money, career | F10: 45543 | G10: Awaiting Response
A11: July | B11: Muhammad Rizwan Hameed | C11: 03186983988 | D11: The background can be finance, marketing, engineering with __ years of experience | E11: Why does he want to take part in the course e.g money, career | G11: Awaiting Response
A12: June | B12: Sarim | C12: 03364971887 | D12: The background can be finance, marketing, engineering with __ years of experience | E12: Why does he want to take part in the course e.g money, career | G12: Closed - Lost
A13: July | B13: Muhammad Sajid | C13: 03057795889 | D13: The background can be finance, marketing, engineering with __ years of experience | E13: Why does he want to take part in the course e.g money, career | G13: Closed - Lost
A14: June | B14: Kotak | C14: 03313871037 | D14: The background can be finance, marketing, engineering with __ years of experience | E14: Why does he want to take part in the course e.g money, career | F14: 45543 | G14: Call not Recieved
A15: July | B15: Muhammad Osama Ahmed | C15: 03342984179 | D15: The background can be finance, marketing, engineering with __ years of experience | E15: Why does he want to take part in the course e.g money, career | G15: Closed - Won
A16: June | B16: Uzma | C16: 03002339269 | D16: The background can be finance, marketing, engineering with __ years of experience | E16: Why does he want to take part in the course e.g money, career | G16: Closed - Won
A17: July | B17: Ismail | C17: 03420440587 | D17: The background can be finance, marketing, engineering with __ years of experience | E17: Why does he want to take part in the course e.g money, career | F17: 45543 | G17: Form unfilled
A18: June | B18: Umer Farooq | C18: 03182554546 | D18: The background can be finance, marketing, engineering with __ years of experience | E18: Why does he want to take part in the course e.g money, career | G18: Contacted | L18: He wil reconsider
A19: July | B19: Tayyab Ayub | C19: 03310216049 | D19: The background can be finance, marketing, engineering with __ years of experience | E19: Why does he want to take part in the course e.g money, career | F19: 45510.625 | G19: Form unfilled
A20: June | C20: 03096345921 | D20: The background can be finance, marketing, engineering with __ years of experience | E20: Why does he want to take part in the course e.g money, career | F20: 45543 | G20: Form unfilled
A21: July | B21: Abu Usman | C21: 03408390937 | D21: The background can be finance, marketing, engineering with __ years of experience | E21: Why does he want to take part in the course e.g money, career | F21: 45543 | G21: Form unfilled
A22: June | C22: 03361309426 | D22: The background can be finance, marketing, engineering with __ years of experience | E22: Why does he want to take part in the course e.g money, career | F22: 45481 | G22: Form unfilled
A23: July | B23: Ahmed | C23: 03470800568 | D23: The background can be finance, marketing, engineering with __ years of experience | E23: Why does he want to take part in the course e.g money, career | F23: 45543 | G23: Form unfilled
A24: June | B24: Abdul Rehman Niazi | C24: 03022042822 | D24: The background can be finance, marketing, engineering with __ years of experience | E24: Why does he want to take part in the course e.g money, career | F24: 45543 | G24: Awaiting Response
A25: July | B25: Rabia | C25: 03168934081 | D25: The background can be finance, marketing, engineering with __ years of experience | E25: Why does he want to take part in the course e.g money, career | G25: Closed - Lost
A26: June | B26: Arisha Badar | C26: 03351822157 | D26: The background can be finance, marketing, engineering with __ years of experience | E26: Why does he want to take part in the course e.g money, career | G26: Form Filled
A27: July | B27: Hadia | C27: 03022418641 | D27: The background can be finance, marketing, engineering with __ years of experience | E27: Why does he want to take part in the course e.g money, career | G27: Referred to | H27: Done
A28: June | B28: Ummehani Faisal | C28: 03002160247 | D28: The background can be finance, marketing, engineering with __ years of experience | E28: Why does he want to take part in the course e.g money, career | G28: Form Filled
A29: July | B29: Talha Ahmed | C29: 03256615630 | D29: The background can be finance, marketing, engineering with __ years of experience | E29: Why does he want to take part in the course e.g money, career | G29: Closed - Lost
A30: June | B30: Nabeed Ashfaq Usmani | C30: 03303478037 | D30: The background can be finance, marketing, engineering with __ years of experience | E30: Why does he want to take part in the course e.g money, career | G30: Form Filled
A31: July | C31: 03353793307 | D31: The background can be finance, marketing, engineering with __ years of experience | E31: Why does he want to take part in the course e.g money, career | F31: 45908 | G31: Form unfilled
A32: June | B32: Rahul | C32: 03333775454 | D32: The background can be finance, marketing, engineering with __ years of experience | E32: Why does he want to take part in the course e.g money, career | G32: Closed - Won
A33: July | B33: Asma | C33: 03001007887 | D33: The background can be finance, marketing, engineering with __ years of experience | E33: Why does he want to take part in the course e.g money, career | F33: 45543 | G33: Form unfilled
A34: Aug | C34: 03134749569 | D34: The background can be finance, marketing, engineering with __ years of experience | E34: Why does he want to take part in the course e.g money, career | F34: 45543 | G34: Form unfilled
A35: Aug | B35: Awais | C35: 03214000297 | D35: The background can be finance, marketing, engineering with __ years of experience | E35: Why does he want to take part in the course e.g money, career | F35: 45543 | G35: Form unfilled
A36: Aug | B36: Tabinda Hassan | C36: 03352149953 | D36: The background can be finance, marketing, engineering with __ years of experience | E36: Why does he want to take part in the course e.g money, career | G36: Form Filled
A37: Aug | B37: Aftab | C37: 03046664933 | D37: The background can be finance, marketing, engineering with __ years of experience | E37: Why does he want to take part in the course e.g money, career | G37: Form unfilled
A38: Aug | B38: Anas | C38: 03252823794 | D38: The background can be finance, marketing, engineering with __ years of experience | E38: Why does he want to take part in the course e.g money, career | G38: Form unfilled
B39: Abu Bakr | C39: 03059972559 | D39: The background can be finance, marketing, engineering with __ years of experience | E39: Why does he want to take part in the course e.g money, career | F39: 45543 | G39: Closed - Lost
B40: Sajar Nafees | C40: 03362334111 | D40: The background can be finance, marketing, engineering with __ years of experience | E40: Why does he want to take part in the course e.g money, career | G40: Closed - Lost
C41: 03213358406 | D41: The background can be finance, marketing, engineering with __ years of experience | E41: Why does he want to take part in the course e.g money, career | G41: Form unfilled
C42: 03392009799 | D42: The background can be finance, marketing, engineering with __ years of experience | E42: Why does he want to take part in the course e.g money, career | G42: Form unfilled
B43: Faiq | C43: 03095264550 | D43: The background can be finance, marketing, engineering with __ years of experience | E43: Why does he want to take part in the course e.g money, career | G43: Form unfilled
C44: 03180309993 | D44: The background can be finance, marketing, engineering with __ years of experience | E44: Why does he want to take part in the course e.g money, career | G44: Form unfilled
B45: Anoosh | C45: 03305012922 | D45: The background can be finance, marketing, engineering with __ years of experience | E45: Why does he want to take part in the course e.g money, career | G45: Form unfilled
B46: Zeeshan Ahmed | C46: 03241437989 | D46: The background can be finance, marketing, engineering with __ years of experience | E46: Why does he want to take part in the course e.g money, career | G46: Form unfilled
B47: M. Wasee Shahid | C47: 03082476738 | D47: The background can be finance, marketing, engineering with __ years of experience | E47: Why does he want to take part in the course e.g money, career | G47: Form unfilled
B48: Nida Amin | C48: 03232862712 | D48: The background can be finance, marketing, engineering with __ years of experience | E48: Why does he want to take part in the course e.g money, career | G48: Form unfilled
B49: Saqib Shaikh | C49: 03142416522 | D49: The background can be finance, marketing, engineering with __ years of experience | E49: Why does he want to take part in the course e.g money, career | G49: Form unfilled
B50: Muhammad Bilal | C50: 03408731282 | D50: The background can be finance, marketing, engineering with __ years of experience | E50: Why does he want to take part in the course e.g money, career | G50: Form unfilled
C51: 03168438939 | D51: The background can be finance, marketing, engineering with __ years of experience | E51: Why does he want to take part in the course e.g money, career | G51: Form unfilled
B52: Qarar Ali | C52: 03192660215 | D52: The background can be finance, marketing, engineering with __ years of experience | E52: Why does he want to take part in the course e.g money, career | G52: Form unfilled
B53: Asghar Gujjar | C53: 03146742535 | D53: The background can be finance, marketing, engineering with __ years of experience | E53: Why does he want to take part in the course e.g money, career | G53: Form unfilled
C54: 03414460593 | D54: The background can be finance, marketing, engineering with __ years of experience | E54: Why does he want to take part in the course e.g money, career | G54: Form unfilled
B55: Muhammad Asif | C55: 03029157482 | D55: The background can be finance, marketing, engineering with __ years of experience | E55: Why does he want to take part in the course e.g money, career | G55: Form unfilled
B56: Ammar | C56: 03196192827 | D56: The background can be finance, marketing, engineering with __ years of experience | E56: Why does he want to take part in the course e.g money, career | G56: Form unfilled
B57: Atif | C57: 03421123023 | D57: The background can be finance, marketing, engineering with __ years of experience | E57: Why does he want to take part in the course e.g money, career | G57: Form unfilled
B58: Muhammad Taha | C58: 03311399237 | D58: The background can be finance, marketing, engineering with __ years of experience | E58: Why does he want to take part in the course e.g money, career | G58: Form unfilled
B59: Munawar Alam | C59: 03009200305 | D59: The background can be finance, marketing, engineering with __ years of experience | E59: Why does he want to take part in the course e.g money, career | G59: Form unfilled
B60: Hayaat | C60: 03365585075 | D60: The background can be finance, marketing, engineering with __ years of experience | E60: Why does he want to take part in the course e.g money, career | G60: Form Filled
B61: Abrar Anwar | C61: 03086743094 | D61: The background can be finance, marketing, engineering with __ years of experience | E61: Why does he want to take part in the course e.g money, career | G61: Form unfilled
B62: Bisma | C62: 03158174926 | D62: The background can be finance, marketing, engineering with __ years of experience | E62: Why does he want to take part in the course e.g money, career | G62: Referred to
B63: Gul Soomro | C63: 03360024805 | D63: The background can be finance, marketing, engineering with __ years of experience | E63: Why does he want to take part in the course e.g money, career | G63: Form unfilled
B64: Maham Naz | C64: 03401645210 | D64: The background can be finance, marketing, engineering with __ years of experience | E64: Why does he want to take part in the course e.g money, career | G64: Please call later
B65: Raheel Ahmed | C65: 03214934541 | D65: The background can be finance, marketing, engineering with __ years of experience | E65: Why does he want to take part in the course e.g money, career | G65: Referred to
B66: Muhammad Ahmed | C66: 03343706275 | D66: The background can be finance, marketing, engineering with __ years of experience | E66: Why does he want to take part in the course e.g money, career | G66: Form unfilled
... B69: Hamza Kamelen | C69: 03112474407 | D69: The background can be finance, marketing, engineering with __ years of experience | E69: Why does he want to take part in the course e.g money, career | G69: Form unfilled
C70: 03112020844 | D70: The background can be finance, marketing, engineering with __ years of experience | E70: Why does he want to take part in the course e.g money, career | G70: Why does he want to take part in the course e.g money, career
B71: Muhammad Rehan | C71: 03269000585 | D71: The background can be finance, marketing, engineering with __ years of experience | E71: Why does he want to take part in the course e.g money, career | G71: Why does he want to take part in the course e.g money, career
B72: Mustafa Shahzaib | C72: 03242329870 | D72: The background can be finance, marketing, engineering with __ years of experience | E72: Why does he want to take part in the course e.g money, career | G72: Referred to
B73: Sheikh Usama Nasir | C73: 03332349116 | D73: The background can be finance, marketing, engineering with __ years of experience | E73: Why does he want to take part in the course e.g money, career | G73: Meeting Scheduled
B74: Rameez Hussain | C74: 03411282221 | D74: The background can be finance, marketing, engineering with __ years of experience | E74: Why does he want to take part in the course e.g money, career | G74: Contacted
B75: Mazhar Abbas | C75: 03334222219 | D75: The background can be finance, marketing, engineering with __ years of experience | E75: Why does he want to take part in the course e.g money, career | G75: Contacted
B76: Umer | C76: 03083118503 | D76: The background can be finance, marketing, engineering with __ years of experience | E76: Why does he want to take part in the course e.g money, career | G76: Why does he want to take part in the course e.g money, career
B77: Sajida Abbas | C77: 03441818103 | D77: The background can be finance, marketing, engineering with __ years of experience | E77: Why does he want to take part in the course e.g money, career | G77: Why does he want to take part in the course e.g money, career
B78: Talha Sheikh | C78: 03172290629 | D78: The background can be finance, marketing, engineering with __ years of experience | E78: Why does he want to take part in the course e.g money, career | G78: Why does he want to take part in the course e.g money, career
B79: Tayyaba Abdullah | C79: 03069626908 | D79: The background can be finance, marketing, engineering with __ years of experience | E79: Why does he want to take part in the course e.g money, career | G79: Why does he want to take part in the course e.g money, career
C80: 03322888689 | D80: The background can be finance, marketing, engineering with __ years of experience | E80: Why does he want to take part in the course e.g money, career | G80: Why does he want to take part in the course e.g money, career
B81: Arsalan | C81: 03217841457 | D81: The background can be finance, marketing, engineering with __ years of experience | E81: Why does he want to take part in the course e.g money, career | G81: Why does he want to take part in the course e.g money, career
B82: Hibah Asif | C82: 03462492837 | D82: The background can be finance, marketing, engineering with __ years of experience | E82: Why does he want to take part in the course e.g money, career | G82: Why does he want to take part in the course e.g money, career
B83: Abdullah | C83: 03167805660 | D83: The background can be finance, marketing, engineering with __ years of experience | E83: Why does he want to take part in the course e.g money, career | G83: Why does he want to take part in the course e.g money, career
C84: 03153736103 | D84: The background can be finance, marketing, engineering with __ years of experience | E84: Why does he want to take part in the course e.g money, career | G84: Why does he want to take part in the course e.g money, career
B85: Muhammad Kaif | C85: 03178979407 | D85: The background can be finance, marketing, engineering with __ years of experience | E85: Why does he want to take part in the course e.g money, career | G85: Why does he want to take part in the course e.g money, career
B86: Shahzad Jawed | C86: 03353994804 | D86: The background can be finance, marketing, engineering with __ years of experience | E86: Why does he want to take part in the course e.g money, career | G86: Closed - Won
B87: Faseeh ur Rehman | C87: 03164929893 | D87: The background can be finance, marketing, engineering with __ years of experience | E87: Why does he want to take part in the course e.g money, career | G87: Form Filled
C88: 03322457591 | D88: The background can be finance, marketing, engineering with __ years of experience | E88: Why does he want to take part in the course e.g money, career | G88: Form unfilled
C89: 03232645534 | D89: The background can be finance, marketing, engineering with __ years of experience | E89: Why does he want to take part in the course e.g money, career | G89: Form unfilled
B90: Ahtasham Janjua | C90: 03453876834 | D90: The background can be finance, marketing, engineering with __ years of experience | E90: Why does he want to take part in the course e.g money, career | G90: Form Filled
C91: 03353525363 | D91: The background can be finance, marketing, engineering with __ years of experience | E91: Why does he want to take part in the course e.g money, career | G91: Form unfilled
B92: Syeda Amal Fatima | C92: 03203273818 | D92: The background can be finance, marketing, engineering with __ years of experience | E92: Why does he want to take part in the course e.g money, career | G92: Form unfilled
B93: Muhammad Jawwad Abbas | C93: 03009259514 | D93: The background can be finance, marketing, engineering with __ years of experience | E93: Why does he want to take part in the course e.g money, career | G93: Form unfilled
B94: Huzaifa | C94: 03322236579 | D94: The background can be finance, marketing, engineering with __ years of experience | E94: Why does he want to take part in the course e.g money, career | G94: Form unfilled
B95: Ahsan Asif | C95: 03351038151 | D95: The background can be finance, marketing, engineering with __ years of experience | E95: Why does he want to take part in the course e.g money, career | G95: Form unfilled
B96: Muhammad Zubair | C96: 03212007179 | D96: The background can be finance, marketing, engineering with __ years of experience | E96: Why does he want to take part in the course e.g money, career | G96: Form unfilled
B97: Tahir | C97: 03450434615 | D97: The background can be finance, marketing, engineering with __ years of experience | E97: Why does he want to take part in the course e.g money, career | G97: Form unfilled
B98: Daniyal Faryad | C98: 03034855548 | D98: The background can be finance, marketing, engineering with __ years of experience | E98: Why does he want to take part in the course e.g money, career | G98: Form Filled
B99: Farhan Rind | C99: 03461391969 | D99: The background can be finance, marketing, engineering with __ years of experience | E99: Why does he want to take part in the course e.g money, career | G99: Form unfilled
B100: Abu Bakr Yousuf | C100: 03042388991 | D100: The background can be finance, marketing, engineering with __ years of experience | E100: Why does he want to take part in the course e.g money, career | G100: Why does he want to take part in the course e.g money, career
B101: Maryam Siddiqui | C101: 03312211367 | D101: The background can be finance, marketing, engineering with __ years of experience | E101: Why does he want to take part in the course e.g money, career | G101: Contacted
B102: Areeba | C102: 03133115759 | D102: The background can be finance, marketing, engineering with __ years of experience | E102: Why does he want to take part in the course e.g money, career
...

Sheet Sheet15
A1: Prospect Name | B1: Number | C1: stage | D1: Call Slot 1 | E1: Attempt-1 | F1: Call Slot 2 | G1: Attempt-2 | H1: Call Slot 3 | I1: Attempt-3 | J1: Call Slot 4 | K1: Attempt-4 | L1: Not talked | M1: Notes | N1: Date1 | O1: Column 1
A2: Unknown | B2: 0303 4713263 | C2: Call not Recieved | D2: 10:30 - 12:30 PM | E2: Not Recieved | F2: 12:30-02:30 | G2: Not Recieved | H2: 02:30-04:30 | I2: Not Recieved | J2: 04:30-06:00 | K2: Not Recieved | L2: Not reachable | M2: Not reachable/msg sent
A3: Unknown | B3: 0323 4091646 | C3: Closed - Lost | D3: 10:30 - 12:30 PM | E3: Not attempted | F3: 12:30-02:30 | G3: 114846 | H3: 02:30-04:30 | I3: Not attempt | J3: 04:30-06:00 | K3: Call Recieved | L3: Talked | M3: not interested
A4: Unknown | B4: 0347 1322271 | C4: Closed - Lost | D4: 10:30 - 12:30 PM | E4: Call Recieved | F4: 12:30-02:30 | G4: Not attempt | H4: 02:30-04:30 | I4: Not attempt | J4: 04:30-06:00 | K4: Not attempt | L4: Talked
A5: Shafique Ahmed | B5: 0334 3793834 | C5: Closed - Lost | D5: 10:30 - 12:30 PM | E5: Call Recieved | F5: 12:30-02:30 | G5: Not attempt | H5: 02:30-04:30 | I5: Not attempt | J5: 04:30-06:00 | K5: Not attempt | L5: Talked | M5: final callled him but not interested
A6: Quratulain | B6: 0304 7787073 | C6: Call not Recieved | D6: 10:30 - 12:30 PM | E6: Not Recieved | F6: 12:30-02:30 | G6: Not Recieved | H6: 02:30-04:30 | I6: Not Recieved | J6: 04:30-06:00 | K6: Not Recieved | L6: Not reachable | M6: Not reachable/msg sent
A7: Unknown | B7: 0326 2604263 | C7: Closed - Lost | D7: 10:30 - 12:30 PM | E7: Call Recieved | F7: 12:30-02:30 | G7: Not attempt | H7: 02:30-04:30 | I7: Not attempt | J7: 04:30-06:00 | K7: Not attempt | L7: Talked
A8: Iqra Irshad | B8: 0310 7014245 | C8: Contacted | D8: 10:30 - 12:30 PM | E8: Not Recieved | F8: 12:30-02:30 | G8: Not attempt | H8: 02:30-04:30 | I8: Not attempt | J8: 04:30-06:00 | K8: Call Recieved | L8: Talked | M8: final called her , she will decide/msg sent
A9: Unknown | B9: 314 5802503 | C9: Call not Recieved | D9: 10:30 - 12:30 PM | E9: Not Recieved | F9: 12:30-02:30 | G9: Not Recieved | H9: 02:30-04:30 | I9: Not Recieved | J9: 04:30-06:00 | K9: Not Recieved | L9: Not reachable | M9: Not reachable/msg sent
A10: Aiman Shahnawaz | B10: 0323 4659156 | C10: Contacted | D10: 10:30 - 12:30 PM | E10: Not Recieved | F10: 12:30-02:30 | G10: Call Recieved | H10: 02:30-04:30 | I10: Please Call later | J10: 04:30-06:00 | K10: Not Recieved | L10: Talked | M10: Call her after 3
A11: Arshad Iqbal | B11: 0321 7280686 | C11: Awaiting Response | D11: 10:30 - 12:30 PM | E11: Not Recieved | F11: 12:30-02:30 | G11: Not attempt | H11: 02:30-04:30 | I11: Not attempt | J11: 04:30-06:00 | K11: Call Recieved | L11: Talked | M11: will decide till tomorrow 24 jan
A12: Faizan Ahmed | B12: 0325 1228451 | C12: Call not Recieved | D12: 10:30 - 12:30 PM | E12: Not Recieved | F12: 12:30-02:30 | G12: Not Recieved | H12: 02:30-04:30 | I12: Not Recieved | J12: 04:30-06:00 | K12: Not Recieved | L12: Not reachable | M12: Not reachable/msg sent
A13: Rana shahidjaved | B13: 0329 7441657 | C13: Closed - Lost | D13: 10:30 - 12:30 PM | E13: Call Recieved | F13: 12:30-02:30 | G13: Not attempt | H13: 02:30-04:30 | I13: Not attempt | J13: 04:30-06:00 | K13: Not attempt | L13: Talked | M13: He is not interested now
A14: Unknown | B14: 0333 4222096 | C14: Contacted | D14: 10:30 - 12:30 PM | E14: Call Recieved | F14: 12:30-02:30 | G14: Not attempt | H14: 02:30-04:30 | I14: Not attempt | J14: 04:30-06:00 | K14: Not attempt | L14: Talked
A15: Azeem Khan | B15: 0312 5897927 | C15: Call not Recieved | D15: 10:30 - 12:30 PM | E15: Not Recieved | F15: 12:30-02:30 | G15: Not Recieved | H15: 02:30-04:30 | I15: Not Recieved | J15: 04:30-06:00 | K15: Not Recieved | L15: Not reachable | M15: Not reachable/msg sent
A16: Unknown | B16: 0316 1003769 | C16: Contacted | D16: 10:30 - 12:30 PM | E16: Not Recieved | F16: 12:30-02:30 | G16: Call Recieved | H16: 02:30-04:30 | I16: Not Recieved | J16: 04:30-06:00 | K16: Not Recieved | L16: Talked | M16: final called /He will decide and will inform by himself he have restricted to call him back
A17: liaqatalali | B17: 327 3325537 | C17: Closed - Lost | D17: 10:30 - 12:30 PM | E17: Not Recieved | F17: 12:30-02:30 | G17: Not Recieved | H17: 02:30-04:30 | I17: Not Recieved | J17: 04:30-06:00 | K17: Not Recieved | L17: Not reachable | M17: Not reachable/msg sent
A18: Unknown | B18: 0301 6609394 | C18: Closed - Lost | D18: 10:30 - 12:30 PM | E18: Not Recieved | F18: 12:30-02:30 | G18: Call Recieved | H18: 02:30-04:30 | I18: Not attempt | J18: 04:30-06:00 | K18: Not attempt | L18: Talked | M18: Not interested
A19: 𝗠𝘂𝗻𝗲𝗲𝗯 𝗦𝗵𝗮𝗵 | B19: 0304 7741958 | C19: Closed - Lost | D19: 10:30 - 12:30 PM | E19: Not Recieved | F19: 12:30-02:30 | G19: Call Recieved | H19: 02:30-04:30 | I19: Not attempt | J19: 04:30-06:00 | K19: Not attempt | L19: Talked | M19: not interested
A20: Mujahid | B20: 0307 1068995 | C20: Closed - Lost | D20: 10:30 - 12:30 PM | E20: Not Recieved | F20: 12:30-02:30 | G20: Call Recieved | H20: 02:30-04:30 | I20: Not Recieved | J20: 04:30-06:00 | K20: Not Recieved | L20: Talked | M20: Not interested
A21: Syed Shah | B21: 0313 8763858 | C21: Call not Recieved | D21: 10:30 - 12:30 PM | E21: Not Recieved | F21: 12:30-02:30 | G21: Not Recieved | H21: 02:30-04:30 | I21: Not Recieved | J21: 04:30-06:00 | K21: Not Recieved | L21: Not reachable | M21: Not reachable/msg sent
A22: Unknown | B22: 0339 2001593 | C22: Closed - Lost | D22: 10:30 - 12:30 PM | E22: Not Recieved | F22: 12:30-02:30 | G22: Call Recieved | H22: 02:30-04:30 | I22: Not attempt | J22: 04:30-06:00 | K22: Not attempt | L22: Talked | M22: not interested
A23: Unknown | B23: 0308 3201015 | C23: Call not Recieved | D23: 10:30 - 12:30 PM | E23: Not Recieved | F23: 12:30-02:30 | G23: Not Recieved | H23: 02:30-04:30 | I23: Not Recieved | J23: 04:30-06:00 | K23: Not Recieved | L23: Not reachable | M23: Not reachable/msg sent
A24: Unknown | B24: 0336 8 7280686 | C24: Closed - Lost | D24: 10:30 - 12:30 PM | E24: Not attempted | F24: 12:30-02:30 | G24: Not attempt | H24: 02:30-04:30 | I24: Call Recieved | J24: 04:30-06:00 | K24: Not attempt | L24: Talked | M24: will decide
A25: Talha Imran | B25: 0335 3936519 | C25: Contacted | D25: 10:30 - 12:30 PM | E25: Not attempted | F25: 12:30-02:30 | G25: Call Recieved | H25: 02:30-04:30 | I25: Not Recieved | J25: 04:30-06:00 | K25: Not attempt | L25: Talked | M25: he wanted to visit
A26: Muhammad Imran | B26: 0314 4770019 | C26: Contacted | D26: 10:30 - 12:30 PM | E26: Call Recieved | F26: 12:30-02:30 | G26: Not attempt | H26: 02:30-04:30 | I26: Not attempt | J26: 04:30-06:00 | K26: Not attempt | L26: Talked
A27: Unknown | B27: 0333 2231062 | C27: Contacted | D27: 10:30 - 12:30 PM | E27: Not attempted | F27: 12:30-02:30 | G27: Call Recieved | H27: 02:30-04:30 | I27: Not attempt | J27: 04:30-06:00 | K27: Not attempt | L27: Talked
A28: Ahmad Mujtaba Ali | B28: 0335 8312275 | C28: Contacted | D28: 10:30 - 12:30 PM | E28: Not attempted | F28: 12:30-02:30 | G28: Not attempt | H28: 02:30-04:30 | I28: Call Recieved | J28: 04:30-06:00 | K28: Not attempt | L28: Talked | M28: Final called/ he will decide after looking on details
A29: unknown | B29: 318 5413099 | C29: Closed - Lost | D29: 10:30 - 12:30 PM | E29: Not Recieved | F29: 12:30-02:30 | G29: Not attempt | H29: 02:30-04:30 | I29: Not attempt | J29: 04:30-06:00 | K29: Not attempt | L29: Not talked
A30: unknown | B30: 333 7832904 | C30: Contacted | D30: 10:30 - 12:30 PM | E30: Call Recieved | F30: 12:30-02:30 | G30: Not attempt | H30: 02:30-04:30 | I30: Not attempt | J30: 04:30-06:00 | K30: Not attempt | L30: Talked | M30: aj tk khud bat adneg whhatspp per
A31: Unknown | B31: 0340 9286858 | C31: Contacted | D31: 10:30 - 12:30 PM | E31: Not Recieved | F31: 12:30-02:30 | G31: Please Call later | H31: 02:30-04:30 | I31: Call Recieved | J31: 04:30-06:00 | K31: Not attempt | L31: Talked | M31: Call back him within hour
A32: Unknown | B32: 0302 4346467 | C32: Contacted | D32: 10:30 - 12:30 PM | E32: Not attempted | F32: 12:30-02:30 | G32: Call Recieved | H32: 02:30-04:30 | I32: Not attempt | J32: 04:30-06:00 | K32: Not attempt | L32: Talked | M32: Final called/ he will decide after looking on details
A33: Unknown | B33: 0302 6222415 | C33: Closed - Lost | D33: 10:30 - 12:30 PM | E33: Not Recieved | F33: 12:30-02:30 | G33: Not Recieved | H33: 02:30-04:30 | I33: Not Recieved | J33: 04:30-06:00 | K33: Not Recieved | L33: Not reachable
A34: unknown | B34: 308 0422163 | C34: Contacted | D34: 10:30 - 12:30 PM | E34: Not attempted | F34: 12:30-02:30 | G34: Call Recieved | H34: 02:30-04:30 | I34: Not attempt | J34: 04:30-06:00 | K34: Not attempt | L34: Talked | M34: She will look etails on whatsapp
A35: fiazmianwali | B35: 0309 0266434 | C35: Call not Recieved | D35: 10:30 - 12:30 PM | E35: Not Recieved | F35: 12:30-02:30 | G35: Not Recieved | H35: 02:30-04:30 | I35: Not Recieved | J35: 04:30-06:00 | K35: Not Recieved | L35: Not reachable | M35: Not reachable/msg sent
A36: Unknown | B36: 0347 4805318 | C36: Contacted | D36: 10:30 - 12:30 PM | E36: Not attempted | F36: 12:30-02:30 | G36: Please Call later | H36: 02:30-04:30 | I36: Call Recieved | J36: 04:30-06:00 | K36: Not attempt | L36: Talked
